Workbook

Sheet Method
B1: LLMs for software architecture: forward snowballing from the 23 primary studies, with thematic synthesis
B2: Purpose | C2: Records the forward snowballing of the 23 primary studies of the main synthesis (S1-S23) and the thematic analysis of every study it adds. It is kept apart from the main workbook (Final-TA) so that the two evidence bases can be reported separately and merged later. The procedure is the same as in the main synthesis.
B3: Research questions | C3: RQ1 What has been reported to date for the use of LLMs and Gen AI for architectural design support? RQ2 What techniques are reported to optimize and evaluate LLMs and Gen AI for architectural design support? RQ3 What are the emerging trends in the use of LLMs and Gen AI for architectural design? RQ4 How can the approaches, techniques and trends identified in RQ1-RQ3 be extended to support the architecture design of self-adaptive software systems?
B4: Themes and sub-themes | C4: Six themes, revised from the three of the main synthesis following supervisor feedback: RQ1 is answered by T1, RQ2 by T2 and T3, RQ3 by T4, T5 and T6. The sub-themes are those of the main synthesis, regrouped; "benefits and limitations in practice" is split into 1.6 and 5.1. The earlier combined theme "Challenges / Limitations" is split into T5 Limitations (5.1 and 5.2, problems observed in the studies) and T6 Challenges (6.1, formerly 5.3: open problems and future work the authors state); no meaning unit was recoded. T1. LLMs Application / Usage for Architecture Design (RQ1) 1.1 Architecture generation and synthesis from requirements 1.2 Design decision support: pattern, tactic and technology recommendation 1.3 Architecture documentation, decision records and rationale capture 1.4 Architecture analysis, recovery, conformance and smell detection 1.5 The role assigned to the model: assistant, co-designer or autonomous agent 1.6 Reported benefits in practice T2. Techniques for Optimization (RQ2) 2.1 Prompting strategies: chain-of-thought, few-shot, role and self-refinement 2.2 Knowledge grounding: RAG, knowledge graphs and architecture repositories 2.3 Fine-tuning, model adaptation and multi-agent orchestration T3. Techniques for Evaluation (RQ2) 3.1 Evaluation designs: benchmarks, case studies, expert judgement, experiments 3.2 Metrics and quality criteria used to judge generated architectures 3.3 Cost, latency and reproducibility of the reported setups T4. Emerging Trends (RQ3) 4.1 From single-prompt assistance towards agentic and multi-agent architecting 4.2 Integration with model-driven engineering and formal artefact generation 4.3 Human-AI collaboration and the changing role of the architect 4.4 Movement from design-time assistance towards runtime and continuous architecting 4.5 Trust, governance and responsible adoption in industrial settings T5. Limitations (RQ3) 5.1 Reported limitations in practice 5.2 Reported reliability problems: hallucination, inconsistency, non-determinism T6. Challenges (RQ3) 6.1 Open challenges and stated future work
B5: Snowballing procedure | C5: Wohlin (2014), forward direction. The start set is S1-S23. For each seed, the citing records listed by Google Scholar are retrieved and each is logged on the Citing studies sheet with its decision. A record already in the main corpus, or already logged, is recorded as a duplicate on the Citing studies sheet, with the record it duplicates and where that original is (this sheet, or Final-TA for main-corpus studies). For each record we confirm that it cites the seed, then screen on title and abstract and, unless it is clearly excluded, on the full text; the full text decides. A record whose full text cannot be obtained (for example, a Google Scholar citation-only entry) is excluded as not retrievable, with what its record shows. Whether to run further iterations is still to be decided.
B6: Scope criterion | C6: A source is in scope when a model performs, or in a proposal paper is specified to perform, a task whose object is a software architecture. (1) Object of the task: the object of the model's task decides scope; a model acting as a component of an architecture is not doing architectural work. (2) Metadata: title, keywords and venue can support a decision but never decide it. (3) Proposed task: a paper that runs no model is in scope if it specifies a model performing an architectural task. (4) Knowledge artefact: a model producing an ontology, knowledge graph or domain taxonomy is not doing architectural work.
B7: Approach | C7: Thematic synthesis following Cruzes & Dybå (2011), with the six phases of Braun & Clarke (2006) organising the analytic work. Deductive at theme level (the six themes are fixed by the research questions) and inductive below it; a new sub-theme is added only when coded material fits none of the existing ones.
B8: Meaning units and row types | C8: A meaning unit is a short paraphrase from a study carrying one idea, with its section or page. Evidenced: the study reports or does what the sub-theme describes. Coded silence: the study is silent on something the review asks about and the silence matters; the code starts with "Absence:". Related activity: the study does something next to the sub-theme. Only Evidenced rows count as evidence. One unit carries one idea; several instances of the same idea are one unit. Coverage (decided 4 October 2026): unlike the main synthesis, which has a row for every study and sub-theme, a snowballed study has a row only where it addresses the sub-theme or where its silence matters (most often no grounding, no settings, runs or cost, or design-time use only). An empty study/sub-theme pair therefore means that the study does not address the sub-theme and that the silence was not judged analytically relevant; it does not mean the question was not asked.
B9: Trend signal | C9: Every row under T4, and under 6.1, records how the trend is evidenced: Explicit (the authors state it) or No signal. Rows under T1-T3 and T5 carry no signal. A distributional reading of a trend (inferred from the spread of publication years) is a judgement for the synthesis across studies and is not recorded on individual rows (decided 4 October 2026).
B10: Study families | C10: Studies that are not independent (same authors, subjects, data or transcripts) form a family. A snowballed study that belongs to a line of work in the main corpus takes that family's ID (F1-F20); a new line of work gets a new ID (SF1, SF2 ...). Counts of supporting studies are reported with the number of independent families.
B11: RQ4: extension to self-adaptive systems | C11: Answered on StudyWise_SAS_Extension (per study) and SAS extension (per sub-theme). Following supervisor feedback, each is read against MAPE-K, Rainbow and Models@run.time and, where one fits better, another framework (below). Per study: evidence, locus of the architectural work, what breaks for a self-adaptive system (a named property), the framework reading with a link grade, the best fit and why, and a testable extension with preconditions, risks and grounding. Link grades: Direct (the study does it), Partial (it does part of it), Inferred (our mapping), Not applicable. Only Direct and Partial count as evidence from the corpus. A framework not named in a row has nothing to say about it. Frameworks: - MAPE-K feedback loop: Kephart, J.O. & Chess, D.M. (2003). The Vision of Autonomic Computing. Computer, 36(1), 41-50. DOI 10.1109/MC.2003.1160055 - Rainbow (architecture-based self-adaptation): Garlan, D., Cheng, S.-W., Huang, A.-C., Schmerl, B. & Steenkiste, P. (2004). Rainbow: Architecture-Based Self-Adaptation with Reusable Infrastructure. Computer, 37(10), 46-54. DOI 10.1109/MC.2004.175 - Models@run.time: Blair, G., Bencomo, N. & France, R.B. (2009). Models@run.time. Computer, 42(10), 22-27. DOI 10.1109/MC.2009.326 - Three-layer architecture for self-managed systems: Kramer, J. & Magee, J. (2007). Self-Managed Systems: an Architectural Challenge. Future of Software Engineering (FOSE ’07), 259-268. DOI 10.1109/FOSE.2007.19 - FORMS reference model: Weyns, D., Malek, S. & Andersson, J. (2012). FORMS: Unifying Reference Model for Formal Specification of Distributed Self-Adaptive Systems. ACM Transactions on Autonomous and Adaptive Systems, 7(1), 1-61. DOI 10.1145/2168260.2168268 - EUREMA (executable runtime megamodels): Vogel, T. & Giese, H. (2014). Model-Driven Engineering of Self-Adaptive Software with EUREMA. ACM Transactions on Autonomous and Adaptive Systems, 8(4), 1-33. DOI 10.1145/2555612 - ActivFORMS (active formal models): Iftikhar, M.U. & Weyns, D. (2014). ActivFORMS: Active Formal Models for Self-Adaptation. Proceedings of SEAMS 2014, 125-134. DOI 10.1145/2593929.2593944 - Dynamic software product lines: Hallsteinsen, S., Hinchey, M., Park, S. & Schmid, K. (2008). Dynamic Software Product Lines. Computer, 41(4), 93-95. DOI 10.1109/MC.2008.123 - Control-theoretic adaptation: Filieri, A., Maggio, M., et al. (2015). Software Engineering Meets Control Theory. Proceedings of SEAMS 2015, 71-82. DOI 10.1109/SEAMS.2015.12 - Requirements-driven adaptation (awareness requirements): Souza, V.E.S., Lapouchnian, A., Robinson, W.N. & Mylopoulos, J. (2011). Awareness Requirements for Adaptive Systems. Proceedings of SEAMS 2011, 60-69. DOI 10.1145/1988008.1988018
B12: Quality assessment | C12: Same six-item instrument as the main synthesis: Q1 problem definition, Q2 problem context, Q3 research design, Q4 contributions, Q5 insights, Q6 limitations. Each scored 0 (absent), 1 (general or partial) or 2 (explicit), total 0-12. It measures reporting completeness, not methodological soundness. Each score is justified with its location and why the adjacent score was not given. The decision rule is not yet fixed. Scores are the first rater's; the second rater's are pending.
B13: Validation | C13: The supplementary synthesis was initially generated with Claude Opus 5.5 using the shared codebook and researcher-supplied protocol. Authors performed human validation with ChatGPT (GPT-6, High reasoning) as an additional consistency-checking aid. Independent second-rater quality scoring remains pending where not separately documented; source traceability and screening decisions are retained for audit.
B14: References | C14: 1. Cruzes, D.S. & Dybå, T. (2011). Recommended Steps for Thematic Synthesis in Software Engineering. ESEM 2011, 275-284. DOI 10.1109/ESEM.2011.36 2. Braun, V. & Clarke, V. (2006). Using thematic analysis in psychology. Qualitative Research in Psychology, 3(2), 77-101. DOI 10.1191/1478088706qp063oa 3. Wohlin, C. (2014). Guidelines for snowballing in systematic literature studies and a replication in software engineering. EASE 2014, 1-10. DOI 10.1145/2601248.2601268 Framework references are listed under RQ4.

Sheet Seeds
A1: Seed | B1: Authors | C1: Title | D1: Year | E1: Citation source | F1: Records listed | G1: Logged | H1: Included | I1: Excluded | J1: Duplicates | K1: Status
A2: S1 | B2: Maranhão & Guerra | C2: A Prompt Pattern Sequence Approach to Apply Generative AI in Assisting Software Architecture Decision-making | D2: 2024 | E2: Google Scholar | F2: 22 | G2: =COUNTIF(Citing_Studies!$B$2:$B$1000,A2) -> 22 | H2: =COUNTIFS(Citing_Studies!$B$2:$B$1000,A2,Citing_Studies!$G$2:$G$1000,"Included*") -> 7 | I2: =COUNTIFS(Citing_Studies!$B$2:$B$1000,A2,Citing_Studies!$G$2:$G$1000,"Excluded*") -> 12 | J2: =COUNTIFS(Citing_Studies!$B$2:$B$1000,A2,Citing_Studies!$G$2:$G$1000,"Duplicate*") -> 3 | K2: =IF(F2="","Not started",IF(G2=F2,"Complete","To log: "&(F2-G2))) -> Complete
A3: S2 | B3: Maranhão Junior, Melegati & Guerra | C3: Applying a Prompt Pattern Sequence for Decision-Making in Microservices Architectures | D3: 2025 | E3: Google Scholar | F3: 2 | G3: =COUNTIF(Citing_Studies!$B$2:$B$1000,A3) -> 2 | H3: =COUNTIFS(Citing_Studies!$B$2:$B$1000,A3,Citing_Studies!$G$2:$G$1000,"Included*") -> 0 | I3: =COUNTIFS(Citing_Studies!$B$2:$B$1000,A3,Citing_Studies!$G$2:$G$1000,"Excluded*") -> 1 | J3: =COUNTIFS(Citing_Studies!$B$2:$B$1000,A3,Citing_Studies!$G$2:$G$1000,"Duplicate*") -> 1 | K3: =IF(F3="","Not started",IF(G3=F3,"Complete","To log: "&(F3-G3))) -> Complete
A4: S3 | B4: Diaz-Pace, Tommasel, Capilla & Ramírez | C4: Architecture Exploration and Reflection meet LLM-based Agents | D4: 2025 | E4: Google Scholar | F4: 13 | G4: =COUNTIF(Citing_Studies!$B$2:$B$1000,A4) -> 13 | H4: =COUNTIFS(Citing_Studies!$B$2:$B$1000,A4,Citing_Studies!$G$2:$G$1000,"Included*") -> 5 | I4: =COUNTIFS(Citing_Studies!$B$2:$B$1000,A4,Citing_Studies!$G$2:$G$1000,"Excluded*") -> 5 | J4: =COUNTIFS(Citing_Studies!$B$2:$B$1000,A4,Citing_Studies!$G$2:$G$1000,"Duplicate*") -> 3 | K4: =IF(F4="","Not started",IF(G4=F4,"Complete","To log: "&(F4-G4))) -> Complete
A5: S4 | B5: Dhar, Vaidhyanathan & Varma | C5: Can LLMs Generate Architectural Design Decisions? An Exploratory Empirical Study | D5: 2024 | E5: Google Scholar | F5: 119 | G5: =COUNTIF(Citing_Studies!$B$2:$B$1000,A5) -> 119 | H5: =COUNTIFS(Citing_Studies!$B$2:$B$1000,A5,Citing_Studies!$G$2:$G$1000,"Included*") -> 31 | I5: =COUNTIFS(Citing_Studies!$B$2:$B$1000,A5,Citing_Studies!$G$2:$G$1000,"Excluded*") -> 63 | J5: =COUNTIFS(Citing_Studies!$B$2:$B$1000,A5,Citing_Studies!$G$2:$G$1000,"Duplicate*") -> 25 | K5: =IF(F5="","Not started",IF(G5=F5,"Complete","To log: "&(F5-G5))) -> Complete
A6: S5 | B6: Soliman & Keim | C6: Do Large Language Models Contain Software Architectural Knowledge? An Exploratory Case Study with GPT | D6: 2025 | E6: Google Scholar | F6: 31 | G6: =COUNTIF(Citing_Studies!$B$2:$B$1000,A6) -> 31 | H6: =COUNTIFS(Citing_Studies!$B$2:$B$1000,A6,Citing_Studies!$G$2:$G$1000,"Included*") -> 1 | I6: =COUNTIFS(Citing_Studies!$B$2:$B$1000,A6,Citing_Studies!$G$2:$G$1000,"Excluded*") -> 7 | J6: =COUNTIFS(Citing_Studies!$B$2:$B$1000,A6,Citing_Studies!$G$2:$G$1000,"Duplicate*") -> 23 | K6: =IF(F6="","Not started",IF(G6=F6,"Complete","To log: "&(F6-G6))) -> Complete
A7: S6 | B7: Ramachandran | C7: Empowering Software Architects with Artificial Intelligence: Analyzing GitHub Copilot's Role in Modern Architecture Design | D7: 2025 | E7: Google Scholar | F7: 2 | G7: =COUNTIF(Citing_Studies!$B$2:$B$1000,A7) -> 2 | H7: =COUNTIFS(Citing_Studies!$B$2:$B$1000,A7,Citing_Studies!$G$2:$G$1000,"Included*") -> 0 | I7: =COUNTIFS(Citing_Studies!$B$2:$B$1000,A7,Citing_Studies!$G$2:$G$1000,"Excluded*") -> 2 | J7: =COUNTIFS(Citing_Studies!$B$2:$B$1000,A7,Citing_Studies!$G$2:$G$1000,"Duplicate*") -> 0 | K7: =IF(F7="","Not started",IF(G7=F7,"Complete","To log: "&(F7-G7))) -> Complete
A8: S7 | B8: Eisenreich, Speth & Wagner | C8: From Requirements to Architecture: An AI-Based Journey to Semi-Automatically Generate Software Architectures | D8: 2024 | E8: Google Scholar | F8: 56 | G8: =COUNTIF(Citing_Studies!$B$2:$B$1000,A8) -> 56 | H8: =COUNTIFS(Citing_Studies!$B$2:$B$1000,A8,Citing_Studies!$G$2:$G$1000,"Included*") -> 4 | I8: =COUNTIFS(Citing_Studies!$B$2:$B$1000,A8,Citing_Studies!$G$2:$G$1000,"Excluded*") -> 17 | J8: =COUNTIFS(Citing_Studies!$B$2:$B$1000,A8,Citing_Studies!$G$2:$G$1000,"Duplicate*") -> 35 | K8: =IF(F8="","Not started",IF(G8=F8,"Complete","To log: "&(F8-G8))) -> Complete
A9: S8 | B9: Díaz-Pace, Tommasel & Capilla | C9: Helping Novice Architects to Make Quality Design Decisions Using an LLM-Based Assistant | D9: 2024 | E9: Google Scholar | F9: 59 | G9: =COUNTIF(Citing_Studies!$B$2:$B$1000,A9) -> 59 | H9: =COUNTIFS(Citing_Studies!$B$2:$B$1000,A9,Citing_Studies!$G$2:$G$1000,"Included*") -> 4 | I9: =COUNTIFS(Citing_Studies!$B$2:$B$1000,A9,Citing_Studies!$G$2:$G$1000,"Excluded*") -> 15 | J9: =COUNTIFS(Citing_Studies!$B$2:$B$1000,A9,Citing_Studies!$G$2:$G$1000,"Duplicate*") -> 40 | K9: =IF(F9="","Not started",IF(G9=F9,"Complete","To log: "&(F9-G9))) -> Complete
A10: S9 | B10: Dhar, Vaidhyanathan & Varma | C10: Leveraging Generative AI for Architecture Knowledge Management | D10: 2024 | E10: Google Scholar | F10: 24 | G10: =COUNTIF(Citing_Studies!$B$2:$B$1000,A10) -> 24 | H10: =COUNTIFS(Citing_Studies!$B$2:$B$1000,A10,Citing_Studies!$G$2:$G$1000,"Included*") -> 0 | I10: =COUNTIFS(Citing_Studies!$B$2:$B$1000,A10,Citing_Studies!$G$2:$G$1000,"Excluded*") -> 5 | J10: =COUNTIFS(Citing_Studies!$B$2:$B$1000,A10,Citing_Studies!$G$2:$G$1000,"Duplicate*") -> 19 | K10: =IF(F10="","Not started",IF(G10=F10,"Complete","To log: "&(F10-G10))) -> Complete
A11: S10 | B11: Jahić & Sami | C11: State of Practice: LLMs in Software Engineering and Software Architecture | D11: 2024 | E11: Google Scholar | F11: 72 | G11: =COUNTIF(Citing_Studies!$B$2:$B$1000,A11) -> 72 | H11: =COUNTIFS(Citing_Studies!$B$2:$B$1000,A11,Citing_Studies!$G$2:$G$1000,"Included*") -> 4 | I11: =COUNTIFS(Citing_Studies!$B$2:$B$1000,A11,Citing_Studies!$G$2:$G$1000,"Excluded*") -> 33 | J11: =COUNTIFS(Citing_Studies!$B$2:$B$1000,A11,Citing_Studies!$G$2:$G$1000,"Duplicate*") -> 35 | K11: =IF(F11="","Not started",IF(G11=F11,"Complete","To log: "&(F11-G11))) -> Complete
A12: S11 | B12: Ahmad, Waseem, Liang, Fahmideh, Aktar & Mikkonen | C12: Towards Human-Bot Collaborative Software Architecting with ChatGPT | D12: 2023 | E12: Google Scholar | F12: 277 | G12: =COUNTIF(Citing_Studies!$B$2:$B$1000,A12) -> 277 | H12: =COUNTIFS(Citing_Studies!$B$2:$B$1000,A12,Citing_Studies!$G$2:$G$1000,"Included*") -> 11 | I12: =COUNTIFS(Citing_Studies!$B$2:$B$1000,A12,Citing_Studies!$G$2:$G$1000,"Excluded*") -> 227 | J12: =COUNTIFS(Citing_Studies!$B$2:$B$1000,A12,Citing_Studies!$G$2:$G$1000,"Duplicate*") -> 39 | K12: =IF(F12="","Not started",IF(G12=F12,"Complete","To log: "&(F12-G12))) -> Complete
A13: S12 | B13: Keim, Kaplan, Koziolek & Mirakhorli | C13: Does BERT Understand Code?, An Exploratory Study on the Detection of Architectural Tactics in Code | D13: 2020 | E13: Google Scholar | F13: 27 | G13: =COUNTIF(Citing_Studies!$B$2:$B$1000,A13) -> 27 | H13: =COUNTIFS(Citing_Studies!$B$2:$B$1000,A13,Citing_Studies!$G$2:$G$1000,"Included*") -> 0 | I13: =COUNTIFS(Citing_Studies!$B$2:$B$1000,A13,Citing_Studies!$G$2:$G$1000,"Excluded*") -> 23 | J13: =COUNTIFS(Citing_Studies!$B$2:$B$1000,A13,Citing_Studies!$G$2:$G$1000,"Duplicate*") -> 4 | K13: =IF(F13="","Not started",IF(G13=F13,"Complete","To log: "&(F13-G13))) -> Complete
... A24: S23 | B24: Jafari Sarvejahani | C24: Towards Architectural Pen Test Case Generation and Attack Surface Analysis to Support Secure Design | D24: 2025 | E24: Google Scholar | F24: 3 | G24: =COUNTIF(Citing_Studies!$B$2:$B$1000,A24) -> 3 | H24: =COUNTIFS(Citing_Studies!$B$2:$B$1000,A24,Citing_Studies!$G$2:$G$1000,"Included*") -> 0 | I24: =COUNTIFS(Citing_Studies!$B$2:$B$1000,A24,Citing_Studies!$G$2:$G$1000,"Excluded*") -> 3 | J24: =COUNTIFS(Citing_Studies!$B$2:$B$1000,A24,Citing_Studies!$G$2:$G$1000,"Duplicate*") -> 0 | K24: =IF(F24="","Not started",IF(G24=F24,"Complete","To log: "&(F24-G24))) -> Complete
A25: Total | F25: =SUM(F2:F24) -> 781 | G25: =SUM(G2:G24) -> 781 | H25: =SUM(H2:H24) -> 69 | I25: =SUM(I2:I24) -> 477 | J25: =SUM(J2:J24) -> 235

Sheet Citing_Studies
A1: Record | B1: Seed | C1: Authors | D1: Title | E1: Year | F1: Venue | G1: Decision | H1: Ground | I1: Reason | J1: Other seeds cited
A2: S1-F01 | B2: S1 | C2: Narváez, Battaglia, Fernández & Rossi | D2: Designing Microservices Using AI: A Systematic Literature Review | E2: 2025 | F2: Software (MDPI) 4(1), art. 6 | G2: Included as FS01 | I2: Systematic review of 43 studies (2018-2024) on AI in microservices design. Included under our rule for reviews: the model tasks it reports target architecture (service identification and decomposition, decision-making, decision documentation). | J2: S4, S8
A3: S1-F02 | B3: S1 | C3: Abu-Salih, Alotaibi, Alanazi, Abu Khurma, Al-Shboul, Khouri & Aljaafari | D3: Using large language models for semantic interoperability: A systematic literature review | E3: 2025 | F3: ICT Express 11, pp. 819-837 | G3: Excluded | H3: Out of scope (rule 4) | I3: Systematic review of 160 studies on LLMs for semantic interoperability. The model tasks it reports target ontologies, schemas, documents and data, not a software architecture. S1 is cited once, as an example of pattern-based prompting. | J3: None
A4: S1-F03 | B4: S1 | C4: Esposito, Li, Moreschini, Ahmad, Cerny, Vaidhyanathan, Lenarduzzi & Taibi | D4: Generative AI for software architecture. Applications, challenges, and future directions | E4: 2026 | F4: Journal of Systems and Software 231, art. 112607 | G4: Included as FS02 | I4: Multivocal review of 46 sources on generative AI in software architecture. Included under our rule for reviews: its model tasks (decision support, generation, reconstruction, conformance, refactoring) target architecture. S1 is one of its sources. | J4: S3, S4, S5, S7, S8, S9, S10, S11
A5: S1-F04 | B5: S1 | C5: Banitaan, Daoud, Alquran & Akour | D5: Foundation Models in Software Engineering: A Taxonomy, Systematic Review, and In-Depth Analysis of Testing Support | E5: 2026 | F5: Information (MDPI) 17, art. 73 | G5: Excluded | H5: Out of scope (review threshold) | I5: Systematic review of 224 studies across the SE life cycle, with its in-depth analysis on testing. The 12 design/architecture studies are counted in its taxonomy but not synthesised. | J5: None
A6: S1-F05 | B6: S1 | C6: Guimaraes & Nascimento | D6: AI in the Software Development Lifecycle: Insights and Open Research Questions | E6: 2025 | F6: FSE Companion 2025, pp. 1353-1357 | G6: Excluded | H6: Out of scope (rule 3) | I6: Five-page position paper and research roadmap. It runs no model and specifies no architectural model task of its own; its architecture subsection lists other work without synthesis. | J6: S7
A7: S1-F06 | B7: S1 | C7: Zhang, Liu, Sun, Xu, Sun, Li, Jin & Liu | D7: Semantic-Enhanced Automatic Refinement of Architecture Recovery Results Using LLMs | E7: 2026 | F7: ICSE 2026, pp. 1687-1699 | G7: Included as FS03 | I7: Primary study (SemRef): an LLM refines module views recovered from source code, each change checked against dependency structure. The model works on the implemented architecture. | J7: S4, S5, S7, S8
A8: S1-F07 | B8: S1 | C8: Pancher, Melegati & Guerra | D8: Exploratory Test-Driven Development Study with ChatGPT in Different Scenarios | E8: 2025 | F8: XP 2025, LNBIP 545, pp. 145-159 | G8: Excluded | H8: Out of scope (rule 1) | I8: Students used ChatGPT for test-driven development on three programming tasks. The model's task targets unit tests and code, not architecture; S1 is cited only in the background. | J8: S11
A9: S1-F08 | B9: S1 | C9: Alves Pereira, Sousa, Dantas Filho, Albuquerque, Perkusich, Gorgônio & Perkusich | D9: Towards a Characterization of Microservice Architectures Generated by Large Language Models | E9: 2026 | F9: JAWs 2026 (ICSE 2026 workshop); arXiv version read | G9: Included as FS04 | I9: Primary study: LLMs from two providers generate microservice architectures from the documentation of two modular monoliths. Acceptance at JAWs 2026 confirmed on the ICSE 2026 site. | J9: S7, S9
A10: S1-F09 | B10: S1 | C10: Mohamad & Dharam Singh | D10: Prompt Engineering Frameworks and Their Educational Value in Higher Education | E10: 2025 | F10: Innovative Teaching and Learning Journal 9(2), pp. 495-505 | G10: Excluded | H10: Out of scope (review threshold) | I10: Integrative review of five prompt-engineering frameworks for their educational value. S1 is the only architectural study and is summarised as a teaching example, not synthesised. | J10: None
A11: S1-F10 | B11: S1 | C11: Karan, Dhar, Soliman & Vaidhyanathan | D11: Can LLMs Extract Architectural Design Decisions from Source Code Commits? – A Preliminary Exploratory Study | E11: 2026 | F11: IDEA-ARCH 2026 (ECSA 2026 workshop); arXiv version read | G11: Included as FS05 | I11: Primary study: four LLMs extract architectural design decisions from commit messages and diffs. Peer review confirmed on the ECSA 2026 programme; presented 7 Sep 2026, so included after the date window was extended to the retrieval date. | J11: S4, S8, S10
A12: S1-F11 | B12: S1 | C12: Narváez, Battaglia, Fernández & Rossi | D12: Designing Microservices Using AI: A Systematic Literature Review | E12: 2025 | F12: Software (MDPI) 4(1), art. 6 (second listing) | G12: Duplicate of S1-F01 | H12: Duplicate | I12: Same article as S1-F01 (same DOI), listed twice by Google Scholar; the texts were compared and are the same. The original is on this sheet (S1-F01), included and coded as FS01. | J12: As S1-F01
A13: S1-F12 | B13: S1 | C13: Manias, Moulos, Gatzioura, Zdolšek Draksler, Guček & Kyriazis | D13: Architecting Human Oversight in AI-Enabled Software Systems: From Principles to Implementation | E13: 2026 | F13: ICSA 2026 Companion, pp. 127-128 (tutorial abstract) | G13: Excluded | H13: Out of scope (rule 1) | I13: Two-page tutorial abstract on building human oversight into AI-enabled systems. LLMs appear only as system components; no model performs an architectural task. It is also a tutorial abstract, not a research article. | J13: None
A14: S1-F13 | B14: S1 | C14: Copei, Hohlfeld, Kosiol & Ristoski | D14: LLMs Choose the Right Stack: From Patterns to Tools | E14: 2025 | F14: ISE 2025 (ASE 2025 workshop), pp. 276-283 | G14: Included as FS06 | I14: Primary study: six LLMs recommend architectural styles, patterns and tools for four scenarios, directly and through the CAPI decision tree. Workshop uses single-blind review. | J14: S4, S5, S10
A15: S1-F14 | B15: S1 | C15: Mitas & Sachweh | D15: Lifelong Learning in Software Engineering: Towards an AI-driven Tutor for Cloud-Based Software Architectures | E15: 2025 | F15: IEEE E-TEMS 2025, pp. 92-97 | G15: Included as FS07 | I15: Primary study: ChatGPT-4o and Llama 3.1 act as tutors that generate reference architectures from requirements and evaluate students' architectures against them. Six-page full paper, refereed. | J15: S7, S8
A16: S1-F15 | B16: S1 | C16: Zhang, Yiran | D16: Architecture-driven software comprehension across source code and binaries | E16: 2025 | F16: Thesis, Nanyang Technological University (DR-NTU) | G16: Excluded | H16: Not peer reviewed | I16: A thesis, excluded on its record without reading the full text. | J16: Not checked
A17: S1-F16 | B17: S1 | C17: Pancher, Melegati & Guerra | D17: Exploratory Test-Driven Development Study with ChatGPT in Different Scenarios | E17: 2025 | F17: XP 2025, LNBIP 545 (second listing, Google Books) | G17: Duplicate of S1-F07 | H17: Duplicate | I17: Same article as S1-F07 (same DOI), listed twice by Google Scholar; the texts are identical. The original is on this sheet (S1-F07), excluded as out of scope (rule 1). | J17: As S1-F07
A18: S1-F17 | B18: S1 | C18: Rodriguez Sanchez, Vázquez-Santacruz & Cervantes Maceda | D18: A proposal for LLM ensemble learning to achieve consensus in architectural design decisions | E18: 2025 | F18: SSRN preprint 5775315 | G18: Excluded | H18: Not peer reviewed | I18: SSRN preprint, excluded on its record. The full text, received later through S3 (S3-F10), carries the SSRN notice that it has not been peer reviewed on every page and cites S1 in its related work (p. 9). On its content it would be in scope (an ensemble of LLMs generates design decisions guided by ADD); revisit if a peer-reviewed version appears. | J18: S3, S4, S7, S8, S9, S10, S11 (from the full text received as S3-F10)
A19: S1-F18 | B19: S1 | C19: Coelho, Amancio, Paiva Garcia, Vidal Junior, Almeida, Oliveira Leao, Paixao & Freire | D19: More Productive, but at What Cost? Understanding How GenAI Shapes Developers' Work Across the SPACE Dimensions | E19: 2026 | F19: SBES 2026 (CBSoft 2026) | G19: Excluded | H19: Out of scope (rule 1) | I19: Survey of 86 developers on GenAI and productivity (SPACE framework). The activities surveyed are code-level; architecture appears only in one respondent's quote. | J19: None
A20: S1-F19 | B20: S1 | C20: Vardhaman | D20: The Evolution of Cognitive Software Engineering: A Longitudinal Analysis of Large Language Models and Machine Learning in Architectural Synthesis, Fault Prediction, and Code Comprehension | E20: 2024 | F20: The American Journal of Engineering and Technology 6(12), pp. 222-229 | G20: Excluded | H20: Peer review not established | I20: Narrative overview with no method or data. Peer review for this article could not be reliably established, and the main concern is its bibliographic record: it is dated 31 Dec 2024 but cites five papers from ICSA 2025, and the PDF metadata belongs to an unrelated article. Its architecture content would also fail the review threshold. | J20: S7, S10
A21: S1-F20 | B21: S1 | C21: Ribas de Lima & Matos | D21: Prompt Engineering Applied to the Generation of Software Modeling Documents: A Systematic Mapping Study | E21: 2026 | F21: ISE'26 (CBSoft 2026 workshop) | G21: Excluded | H21: Out of scope (review threshold) | I21: Mapping study of 52 studies on prompt engineering for software modelling documents. Architecture and component models (13 of 52) are counted but not synthesised; all findings are pooled across artefact types. Borderline because of the 25% share. | J21: None
A22: S1-F21 | B22: S1 | C22: Jahić | D22: The contextual gap in GenAI for software engineering: Haven't we solved this problem with software architecture? | E22: 2026 | F22: Blog post, Cambridge Advance Online | G22: Excluded | H22: Not peer reviewed | I22: A blog post (15 Jul 2026). The author is the first author of S10. | J22: None
A23: S1-F22 | B23: S1 | C23: Maranhão Junior, Melegati & Guerra | D23: Applying a Prompt Pattern Sequence for Decision-Making in Microservices Architectures | E23: 2025 | F23: ESOCC 2025 (Springer) | G23: Duplicate of S2 | H23: Duplicate (main corpus) | I23: Same study as S2 of the main corpus. The original is in the main workbook (Final-TA, Included studies, S2), where it is included and coded, so it is not screened or coded again here. | J23: Not checked
A24: S2-F01 | B24: S2 | C24: Anghel & Cioara | D24: A systematic review of generative AI usage for IT project management | E24: 2026 | F24: arXiv 2604.21958 (Apr 2026); published in Systems (MDPI) 14(6), art. 722, 22 Jun 2026 (see S2-F02) | G24: Excluded | H24: Out of scope (review threshold) | I24: Systematic review of 30 studies on generative AI in IT project management, organised by PMBOK process group. S2 and S9 are its only architectural studies: each is summarised in the planning section and listed in a table (arXiv pp. 8-9; journal Section 4.2 and Table 2, pp. 10-11), but not synthesised. The authors' own agent vision gives a Technical Lead agent the architectural view in a single sentence, which is not a substantive part either; the journal version calls that section a conceptual perspective beyond the reviewed evidence. The journal version (S2-F02) was read in full and keeps the same treatment. | J24: S9
A25: S2-F02 | B25: S2 | C25: Anghel & Cioara | D25: Generative AI for IT Project Management: A Systematic Review and Future Research Agenda | E25: 2026 | F25: Systems (MDPI) 14(6), art. 722 | G25: Duplicate of S2-F01 | H25: Duplicate | I25: Journal version of the review logged as S2-F01 (its arXiv preprint), listed separately by Google Scholar: same authors, search and 30 studies, with the same text on S2 (Section 4.2, p. 10; Table 2, p. 11). Peer reviewed: received 4 May, revised 18 June, accepted 19 June, published 22 June 2026. The original is on this sheet (S2-F01), excluded under the review threshold; this version was read in full and confirms that decision. | J25: As S2-F01
A26: S3-F01 | B26: S3 | C26: Esposito, Li, Moreschini, Ahmad, Cerny, Vaidhyanathan, Lenarduzzi & Taibi | D26: Generative AI for software architecture. Applications, challenges, and future directions | E26: 2026 | F26: Journal of Systems and Software 231, art. 112607 | G26: Duplicate of S1-F03 | H26: Duplicate | I26: Same article as S1-F03 (same DOI, identical text), reached again through S3, which it reviews as source WL[8] (Section 1, p. 2, and its tables). The original is on this sheet (S1-F03), included and coded as FS02, so it is not screened or coded again. | J26: As S1-F03
A27: S3-F02 | B27: S3 | C27: Meddeb, Batti & Fathallah | D27: BPMN DMN decision table generation based on agentic AI for critical applications | E27: 2026 | F27: Business Process Management Journal (Emerald), online 22 Jan 2026, pp. 1-34 | G27: Excluded | H27: Out of scope (rule 1) | I27: Primary study in which LLM agents (ReAct with retrieval) analyse BPMN process models, extract their decision points and generate DMN decision tables and an optimised process, tested on a supply-chain sales process. The objects of the model's task are a business process and its decision rules, not a software architecture; the architecture described is that of the authors' own agent framework (rule 1). S3 is cited only as an example of ReAct-style reasoning loops (p. 3). | J27: None
A28: S3-F03 | B28: S3 | C28: Cervantes, Kazman & Cai | D28: Better Together: An LLM-assisted approach to designing software architectures using Attribute-Driven Design | E28: 2026 | F28: IEEE Transactions on Software Engineering (early access, 2026); author's version read | G28: Included as FS08 | I28: Primary study: a model with an architect persona follows Attribute-Driven Design to design complete architectures from prioritised drivers, evaluated against a proven solution, by four professional architects and against zero-shot design. Accepted in IEEE TSE (early access). S3 is cited in the related work on design agents (ref. [23], p. 2). | J28: S1 (not in S1's Scholar list), S4, S5, S7, S8, S9, S10
A29: S3-F04 | B29: S3 | C29: Compagnucci, Lu & Trubiani | D29: Agentic Runtime Reconfiguration of Architectural Patterns in Federated Learning | E29: 2026 | F29: Journal of Systems and Software 240, art. 112966 (special issue "AI for SA") | G29: Included as FS09 | I29: Primary study: LLM agents decide after every training round which architectural patterns of a federated-learning system to switch on or off, reasoning over its configuration and metric history, and the system applies the decision. The model is itself a component of the system, but the object of its task is the system's architectural configuration, so it is in scope (rule 1). Peer reviewed (received 2 March, accepted 22 May, online 29 May 2026). S3 is cited in a list of LLM work on architectural decisions (p. 2). | J29: S4, S5, S8, S9
A30: S3-F05 | B30: S3 | C30: Dhar, Vaidhyanathan & Varma | D30: AgenticAKM: Enroute to Agentic Architecture Knowledge Management | E30: 2026 | F30: AGENT 2026 (ICSE 2026 workshop), ACM; arXiv version read | G30: Included as FS10 | I30: Primary study: specialised LLM agents recover architecture knowledge from code repositories and generate Architecture Decision Records, compared with a single prompt in a blind user study on 29 repositories. Accepted at AGENT 2026: listed among the accepted papers on the ICSE 2026 site and presented on 14 April 2026 (lightning talk); the workshop's submission site records 27 of 44 submissions accepted. S3 is cited in the related work on agents in architecture (ref. [15], p. 4). | J30: S4
A31: S3-F06 | B31: S3 | C31: El Outmani, Hatahet, Osterholz, Rausch & Venkataramana Shenoy | D31: Knowledge-Guided Architecture Documentation Recovery with Evidence Grounding and Traceability: A Registered Report (Stage 1) | E31: 2026 | F31: ICSA 2026 Companion (IEEE), pp. 534-541 | G31: Included as FS11 | I31: Stage-1 registered report, a preregistered study design without results: an LLM multi-agent pipeline is specified to recover evidence-grounded architecture documentation (a C4-level component view with traceability links) from repositories under four levels of injected architectural knowledge. In scope under rule 3 (a model is specified to perform an architectural task). Published in the ICSA 2026 Companion proceedings (IEEE, pp. 534-541; Crossref); the track is not named on the paper or found in the conference programme, but it is an eight-page research paper, not an abstract, and a Stage-1 report is reviewed before acceptance. S3 is cited in the related work on agentic systems (ref. [25], p. 536). | J31: S4, S5, S14 (via its arXiv version)
A32: S3-F07 | B32: S3 | C32: Zimmermann & Seiger | D32: AI Assistance for Architectural Decision Making: Domain-Driven Context and Prompt Engineering | E32: 2026 | F32: IDEA-ARCH 2026 (ECSA 2026 workshop), short paper; author version read | G32: Included as FS12 | I32: Short vision paper: from practitioner input and action research it distils eight uses of generative and agentic AI in architectural decision making, proposes decision-assistance tooling that injects modelled project knowledge into prompt templates, and illustrates it with an ADR-review prompt run with several LLMs. Accepted at IDEA-ARCH 2026, like FS05: listed in the ECSA 2026 programme (presented 7 September 2026), and each submission is reviewed by at least three programme committee members. S3 is cited for the option-exploration use case (ref. [9], pp. 3-4). | J32: S4, S11
A33: S3-F08 | B33: S3 | C33: Korvic | D33: Machine Learning and Large Language Model Approaches for Software Code Understanding, Prediction, and Architectural Decision Support | E33: 2024 | F33: Frontiers in Emerging Multidisciplinary Sciences 1(1), pp. 25-34 (irjernet.com); dated 31 Dec 2024, header reads 2026 | G33: Excluded | H33: Out of scope (review threshold) | I33: Narrative overview that draws only on existing literature, mostly machine learning for code (defect prediction, code representation, summarisation). We accept it as peer reviewed; the journal site could not be reached to check the process independently. Its architecture content is five papers (S3, S4, S8, S9 and Arun et al., 2025), each summarised in one or two sentences and repeated across the methodology, results and discussion, without comparison or synthesis, so it falls below the review threshold, as S1-F09 and S2-F01 did. Its bibliographic record is inconsistent: it is dated to volume 1, issue 1, published 31 December 2024, yet its header reads FEMS (2026), the PDF was created in March 2026, and it cites two papers from 2025; six of its 26 references are never cited in the text. S3 is cited as an example of agents for architecture exploration (p. 29). | J33: S4, S8, S9
A34: S3-F09 | B34: S3 | C34: Maia, Bandeira, Oliveira, Mendes & Mendonca | D34: LLM-Native Applications as a Paradigm for AI-Driven Software Architecture: Taxonomy, Application Families, and Architecting Practices | E34: 2026 | F34: SSRN preprint 6799068 (manuscript in the JSS template) | G34: Excluded | H34: Not peer reviewed | I34: SSRN preprint; every page states that it has not been peer reviewed. It extends the authors' ICSE 2026 poster on LLM-native applications. It would also be out of scope under rule 1: it proposes a taxonomy, application families and a conceptual architecture for applications whose runtime behaviour is orchestrated by an LLM, with an example chatbot for literature reviews (SCRIBE), so the model is a component of the system and performs no task on a software architecture; a peer-reviewed version would therefore still be excluded. S3 is cited as an example of agentic AI (p. 3). | J34: S10
A35: S3-F10 | B35: S3 | C35: Rodriguez Sanchez, Vázquez-Santacruz & Cervantes Maceda | D35: A proposal for LLM ensemble learning to achieve consensus in architectural design decisions | E35: 2025 | F35: SSRN preprint 5775315 | G35: Duplicate of S1-F17 | H35: Duplicate | I35: Same SSRN preprint as S1-F17 (abstract 5775315), reached again through S3, which it cites in its related work (p. 9). The original is on this sheet (S1-F17), excluded as not peer reviewed; this full text carries the SSRN notice on every page and confirms that decision. | J35: As S1-F17
A36: S3-F11 | B36: S3 | C36: Compagnucci, Lu & Trubiani | D36: Agentic Runtime Reconfiguration of Architectural Patterns in Federated Learning | E36: 2026 | F36: Journal of Systems and Software 240, art. 112966 (second listing) | G36: Duplicate of S3-F04 | H36: Duplicate | I36: Same article as S3-F04 (same DOI), listed twice by Google Scholar; the two PDFs differ only in file metadata, and their texts are identical. The original is on this sheet (S3-F04), included and coded as FS09. | J36: As S3-F04
A37: S3-F12 | B37: S3 | C37: Miccio Palermo | D37: Agentes basados en LLMs para la derivación de tareas de desarrollo backend a partir de requerimientos textuales | E37: 2026 | F37: CIbSE 2026 (XXIX Congresso Ibero-Americano em Engenharia de Software), Doctoral Symposium (Simpósio de Doutorado), SBC SOL; DOI 10.5753/cibse.2026.42459; published 11 May 2026 (from the SOL page seen through S8-F59); the file read states no venue (8 pages; ISISTAN, CONICET-UNICEN, Argentina) | G37: Excluded | H37: Not in English | I37: Written in Spanish, with an English abstract. It is structured as a research proposal (research questions, objectives, preliminary progress, future work) for a multi-agent LLM workflow that refines requirements, proposes service and component boundaries, defines API contracts and specifies tests for backend development. On its content it would be a candidate for scope; revisit if an English, peer-reviewed version appears. S3 is cited as an example of agents that combine LLMs with planning, reflection and search (ReArch, p. 4). | J37: S4, S8, S11
A38: S3-F13 | B38: S3 | C38: Plokha, V. | D38: Arkitektonisk kontroll i LLM-baserade AI-agenter | E38: 2026 | F38: Not stated (Google Scholar citation-only entry) | G38: Excluded | H38: Not retrievable | I38: Google Scholar lists it only as a [CITATION] entry, with no link to a document (screenshot of the entry kept), and a web search found no copy. The Swedish title ('Architectural control in LLM-based AI agents') suggests that it is not written in English, and no venue is given. Whether and where it cites S3 could not be checked beyond Google Scholar's listing. | J38: Not checked
A39: S4-F01 | B39: S4 | C39: Li, Zhao, Jiang et al. (19 authors) | D39: Large Language Models for manufacturing | E39: 2026 | F39: Journal of Manufacturing Systems 86, pp. 516-545 (review) | G39: Excluded | H39: Out of scope (rule 1) | I39: Review of LLM applications across the manufacturing lifecycle (CAD and CAM, product, chip and aerospace design, supply chains, quality control, education, patents), with some evaluations of GPT-4V. The objects of the model tasks it reports are manufacturing products, processes and documents, not a software architecture, and it synthesises no architectural model task, so it could not meet the review threshold either. S4 is cited once, with two other works, for the claim that AI may turn designers into orchestrators of AI-assisted design (ref. [66], p. 520). | J39: None
A40: S4-F02 | B40: S4 | C40: Ye, Zhang, Ma et al. (29 authors) | D40: LLMs4All: A Review of Large Language Models Across Academic Disciplines | E40: 2025 | F40: arXiv preprint 2509.19580 (v5, Nov 2025; also on Preprints.org) | G40: Excluded | H40: Not peer reviewed | I40: arXiv preprint (v5, 23 Nov 2025), also posted on Preprints.org; no peer-reviewed version was found. It reviews LLM use across academic disciplines, from the arts, letters and law to business, science and engineering. Its only software-architecture content is S4 and the DRAFT preprint by the S4 authors and two others, and both are filed under building architecture (§3.4 Arts and Architecture): S4 gets a few sentences in §3.4.5 and is listed again as the benchmark 'AKM' in §3.4.6 and Table 12, and DRAFT gets a paragraph and a Table 12 row. It would therefore also fail the review threshold. S4 is cited as ref. [283] in Table 11 (p. 45), §3.4.5 (p. 48) and §3.4.6 with Table 12 (pp. 48-49). | J40: None
A41: S4-F03 | B41: S4 | C41: Esposito, Li, Moreschini, Ahmad, Cerny, Vaidhyanathan, Lenarduzzi & Taibi | D41: Generative AI for software architecture. Applications, challenges, and future directions | E41: 2026 | F41: Journal of Systems and Software 231, art. 112607 | G41: Duplicate of S1-F03 | H41: Duplicate | I41: Same article as S1-F03, reached again through S4. Its title, authors and affiliations match S1-F03 exactly, so the full text did not need to be read again. The S1-F03 full text reviews S4 as source WL[5] (Dhar et al., 2024a): in Section 1 (pp. 1-2), in its tables (pp. 8-16) and in the reference list (p. 19). The original is on this sheet (S1-F03), included and coded as FS02, so it is not screened or coded again. | J41: As S1-F03
A42: S4-F04 | B42: S4 | C42: Kalyuzhnaya, Mityagin, Lutsenko et al. (11 authors) | D42: LLM Agents for Smart City Management: Enhancing Decision Support Through Multi-Agent AI Systems | E42: 2025 | F42: Smart Cities (MDPI) 8(1), art. 19 | G42: Excluded | H42: Out of scope (rule 1) | I42: Journal article (received 23 Oct 2024, published 24 Jan 2025) on an LLM-based multi-agent system for smart city management, tested on the Digital Urban Platform of St. Petersburg. Its agents route urban questions to a document pipeline or a city-services API, select functions, retrieve context and summarise answers about city development and service provision, evaluated on 150 question-answer pairs (routing accuracy, G-Eval, Answer Relevancy). The agents are components of a decision-support system whose architecture the authors designed themselves, and the objects of their tasks are urban questions, planning documents and city data, so no model performs a task on a software architecture. S4 is cited once, as ref. 32 (its arXiv version), in a list of fields where LLMs support decision making: "healthcare [31], architecture [32], logistics [33]" (§2.2, p. 5). | J42: None
A43: S4-F05 | B43: S4 | C43: Baltes, Angermeir, Arora et al. (22 authors) | D43: Guidelines for Empirical Studies in Software Engineering involving Large Language Models | E43: 2026 | F43: Empirical Software Engineering (accepted manuscript); arXiv 2508.15503 v8 read | G43: Excluded | H43: Out of scope (rule 3) | I43: Guidelines paper by 22 researchers: a taxonomy of seven study types and eight guidelines for designing and reporting empirical SE studies that involve LLMs, with an applicability matrix and a reporting checklist. It runs no model and specifies no architectural model task, so it is out of scope (rule 3); its many mentions of architecture concern how to report the architecture of LLM-based research tools. The version read is arXiv v8 (18 Sep 2026), marked as the accepted manuscript for Empirical Software Engineering (submitted 26 Aug 2025, last revised 11 Jun 2026; the journal's review is mentioned in Section 3, p. 7); no published journal version was found. S4 is cited once, as ref. 40, as an example of reporting a fine-tuning approach and its datasets (§5.2.3, p. 23); S10 is cited once, as ref. 71, as an example of a study of LLM usage (§4.2.1, p. 12). | J43: S10
A44: S4-F06 | B44: S4 | C44: Płoszaj-Mazurek & Ryńska | D44: Artificial Intelligence and Digital Tools for Assisting Low-Carbon Architectural Design: Merging the Use of Machine Learning, Large Language Models, and Building Information Modeling for Life Cycle Assessment Tool Development | E44: 2024 | F44: Energies (MDPI) 17(12), art. 2997 | G44: Excluded | H44: Out of scope (rule 1) | I44: Journal article (received 11 Apr 2024, published 18 Jun 2024) on low-carbon building design, in three case studies: a neural network in Rhinoceros and Grasshopper that estimates a building's carbon footprint from its form; a web carbon calculator in which ChatGPT (gpt-3.5-turbo-instruct) suggests lower-carbon materials for the building components a designer describes, tested in student workshops; and a web application that loads a BIM (IFC) model, computes its embodied carbon and asks the same model for material suggestions. The object of every model task is a building design, not a software architecture; "architectural design" here means the design of buildings. S4 is cited once, as ref. 45 (its arXiv version), as an application of LLMs to "architectural design", next to BIM (ref. 46) (Section 1, p. 3). | J44: None
... A50: S4-F12 | B50: S4 | C50: Díaz-Pace, Tommasel & Capilla | D50: Helping Novice Architects to Make Quality Design Decisions Using an LLM-Based Assistant | E50: 2024 | F50: ECSA 2024 (Springer LNCS), pp. 324-332 | G50: Duplicate of S8 | H50: Duplicate (main corpus) | I50: Same study as S8 of the main corpus (ECSA 2024, LNCS, pp. 324-332, DOI 10.1007/978-3-031-70797-1_21, first online 1 September 2024); the title, pages and DOI match. The original is in the main workbook (Final-TA, Included studies, S8), where it is included and coded, so it is not screened or coded again here. Its citation of S4 is confirmed by our main-corpus coding of S8, which records that it contrasts its step-wise ADR generation with Dhar et al.'s single-step generation (Sections 3 and 5). | J50: Not checked
A51: S4-F13 | B51: S4 | C51: Zhou, Li, Liang, Zhang, Shahin, Li & Yang | D51: Using LLMs in Generating Design Rationale for Software Architecture Decisions | E51: 2026 | F51: ACM TOSEM 35(8), art. 225 (July 2026); DOI 10.1145/3785010 | G51: Included as FS13 | I51: Primary study: five LLMs generate the design rationale of 100 architecture decisions taken in Stack Overflow posts and GitHub issues and discussions, with zero-shot prompting, chain-of-thought and a five-agent pipeline, evaluated argument by argument against the experts' rationale and in interviews with six practitioners. In scope: the task object is the rationale of an architecture decision, that is, architecture documentation (1.3). Peer reviewed: the journal version was read (received 29 April 2025, revised 17 September 2025, accepted 8 December 2025). S4 is cited as ref. [15] in the related work on design rationale (§7.1, p. 33) and in its summary, together with DRAFT [45] (§7.3, p. 34). It also cites S5 (ref. [53]) and S8 (ref. [16]). | J51: S5, S8
A52: S4-F14 | B52: S4 | C52: Soliman & Keim | D52: Do Large Language Models Contain Software Architectural Knowledge? An Exploratory Case Study with GPT | E52: 2025 | F52: ICSA 2025 (IEEE); IEEE Xplore version read | G52: Duplicate of S5 | H52: Duplicate (main corpus) | I52: Same study as S5 of the main corpus (ICSA 2025): the title and authors match, and the content matches our coding of S5 (GPT-3.5, Hadoop HDFS, 14 engineers, 236 questions). The original is in the main workbook (Final-TA, Included studies, S5), where it is included and coded, so it is not screened or coded again here. The full text (IEEE Xplore version) confirms that it cites S4, as ref. [12]: among the researchers exploring LLMs for architecture (Section I, p. 1), and for using GPT and T5 in zero-shot, few-shot and fine-tuning setups to recommend design decisions (Section VII-2, p. 10). | J52: Not checked
A53: S4-F15 | B53: S4 | C53: Zhang, Li, Liang, Sun & Liu | D53: Knowledge-Based Multi-Agent Framework for Automated Software Architecture Design | E53: 2025 | F53: FSE Companion ’25 (ACM), pp. 530-534; DOI 10.1145/3696630.3728493 | G53: Included as FS14 | I53: Vision paper: four LLM-based agents (Analyst, Modeler, Designer, Evaluator) are specified to design a system's architecture from its software requirements specification, drawing on architectural knowledge extracted from existing designs, authoritative literature and architecture experts. In scope under the proposed-task clause (rule 3): it runs no model, but it specifies models performing architectural tasks: decisions on technology, styles and patterns, conceptual logical and physical views, UML design diagrams, and evaluation of the artefacts against the requirements. Peer reviewed: FSE 2025 companion proceedings, received 17 January 2025 and accepted 13 March 2025; the track is not named on the paper. S4 is cited once, as ref. [3], for zero-shot prompting frequently leading LLMs to generate hallucinatory content (Section 1, p. 530). | J53: None
A54: S4-F16 | B54: S4 | C54: Fuchß, Liu, Hey, Keim & Koziolek | D54: Enabling Architecture Traceability by LLM-based Architecture Component Name Extraction | E54: 2025 | F54: ICSA 2025 (IEEE); DOI 10.1109/ICSA65012.2025.00011 | G54: Included as FS15 | I54: Primary study: LLMs extract architecture component names from architecture documentation, from source-code package structure or from both, as a simple architecture model that lets TransArC recover trace links between documentation and code without a manually created model. In scope (rule 1): the model recovers an architecture model of an existing system (1.4). Peer reviewed: ICSA 2025 (IEEE). It is the conference version of S20 (TAAS 2026), whose coding already covers the same approach and its first evaluation; we include it as a separate study in family F20 rather than as a duplicate of S20. S4 is cited once, as ref. [22], among LLM uses for supporting design decision making (Section II-B, p. 2). | J54: S7, S8, S11
A55: S4-F17 | B55: S4 | C55: Shen, Gao, Lu, Zhang, Zheng & Santamouris | D55: How AI Shapes the Future Landscape of Sustainable Building Design With Climate Change Challenges? | E55: 2026 | F55: Advanced Science 13(13), e23238; DOI 10.1002/advs.202523238 | G55: Excluded | H55: Out of scope (rule 1) | I55: Review (structured narrative, 116 studies from 2010 to October 2024; received 15 November 2025, accepted 20 January 2026) of AI for sustainable, climate-responsive building design: climate data processing, early-stage design generation with LLMs and text-to-image or text-to-3D models, form-finding and multi-objective optimisation, building performance prediction, and integrated design across form, material and systems, with a framework and policy recommendations. The objects of the model tasks it discusses are buildings, their geometry, materials, energy and comfort, not a software architecture, and it synthesises no architectural model task, so it could not meet the review threshold either. S4 is cited twice as ref. [3], each time as work on building design: for LLMs in the introduction (Section 1, p. 1), and in Table 2 under early-stage design generation of buildings, among LLM and text-to-image works (p. 9). | J55: None
A56: S4-F18 | B56: S4 | C56: Vaidhyanathan & Muccini | D56: Software Architecture in the Age of Agentic AI | E56: 2025 | F56: ECSA 2025 tutorials, LNCS 15982, pp. 41-49 (Springer, 2026); DOI 10.1007/978-3-032-04403-7_5 | G56: Excluded | H56: Out of scope (rule 3) | I56: Tutorial summary: the plan of a half-day ECSA 2025 tutorial in three parts (software architecture for ML-enabled systems, LLMs for software architecture, architecting LLM-based multi-agent systems), with learning objectives, a schedule and the presenters' background. It runs no model and reports no study, and it specifies no architectural model task of its own: the LLM part introduces the topic and includes a hands-on session with an existing co-pilot tool (ArchCoPilot) based on S4, so it is out of scope (rule 3). It is also a tutorial description rather than a research article, so it would fail the publication-type criterion as well. S4 is cited as ref. [2] among works on AI supporting architecture practice (Section 1, p. 42) and as the basis of the tool used in the hands-on session (p. 43); S4's second author presents the tutorial. It also cites S9 (ref. [3]), S4-F11 (ref. [1]) and FS02's arXiv preprint (ref. [4]). | J56: S9
A57: S4-F19 | B57: S4 | C57: Su, Bakhtin, Ahmad, Esposito, Lenarduzzi & Taibi | D57: Evaluating Large Language Models for Detecting Architectural Decision Violations | E57: 2026 | F57: ICSA 2026 (IEEE); DOI 10.1109/ICSA66085.2026.00007 | G57: Included as FS16 | I57: Primary study: four open LLMs check whether the code of 109 GitHub projects complies with the decisions in their architecture decision records (980 ADRs, 1,317 accepted decisions), one model detecting violations and three validating its reasoning, with accuracy measured on 305 decisions validated by the authors. In scope (rule 1): the model judges the implementation against recorded architectural decisions, an architecture conformance task (1.4). Peer reviewed: ICSA 2026 (IEEE). S4 is cited once, as ref. [23] ('Rudra et al.'), in the related work on AI in ADR research (Section II, p. 2). It also cites S9 (ref. [10]), FS02 (ref. [16]) and S4-F11 (ref. [17]). | J57: S9
A58: S4-F20 | B58: S4 | C58: Fuchß, Liu, Corallo, Hey, Keim, von Geisau & Koziolek | D58: Who's Who? LLM-assisted Software Traceability with Architecture Entity Recognition | E58: 2026 | F58: ACM Transactions on Autonomous and Adaptive Systems (TAAS), 2026; DOI 10.1145/3807453 | G58: Duplicate of S20 | H58: Duplicate (main corpus) | I58: Same study as S20 of the main corpus (ACM TAAS, 2026, DOI 10.1145/3807453); the title and all seven authors match. The original is in the main workbook (Final-TA, Included studies, S20), where it is included and coded, so it is not screened or coded again here. Its citation of S4 was checked in the arXiv version (2511.02434v2), since the ACM page could not be opened: S4 is ref. [13], cited among LLM uses for supporting design decision making (Section 2.2), the same sentence as in FS15. FS15 (S4-F16), its conference version, is included in family F20. | J58: Not checked
A59: S4-F21 | B59: S4 | C59: Orellana, Cereceda-Balic, Solar & Astudillo | D59: Enabling Design of Secure IoT Systems with Trade-Off-Aware Architectural Tactics | E59: 2024 | F59: Sensors (MDPI) 24(22), art. 7314; DOI 10.3390/s24227314 | G59: Excluded | H59: Out of scope (rule 3) | I59: Primary study: security tactics taxonomies are extended with IoT-specific trade-offs against the ISO 25010:2023 quality characteristics, the catalogue is illustrated on the Nunatak environmental monitoring system, and it is validated in a controlled experiment in which 12 practitioners designed a secure IoT system with catalogues with or without trade-off information. The designers are people; no model performs, or is specified to perform, an architectural task. An LLM-based recommender for secure IoT design is mentioned only as ongoing work in the conclusion, without being specified, so the proposed-task clause (rule 3) is not met. S4 is cited once, as ref. [136], in a group of works [134-137] on LLMs as a topic in the software architecture community (Section 8, p. 28). It also cites S7 (ref. [135]) and S8 (ref. [137]), in the same group. | J59: S7, S8
A60: S4-F22 | B60: S4 | C60: Falcão, Schweitzer, Siebert, Calvet & Elberzhager | D60: Evaluating the effectiveness of LLM-based interoperability | E60: 2026 | F60: ICSE 2026 (IEEE/ACM), pp. 2963-2974; DOI 10.1145/3744916.3773251 | G60: Excluded | H60: Out of scope (rule 1) | I60: Primary study (ICSE 2026): 13 open-source LLMs make a service interoperate at runtime without human intervention, either by converting incoming data into the service's target representation directly (DIRECT) or by generating adapter code that is then tested and deployed (CODEGEN), evaluated with pass@1 over three runs on four versions of an agricultural dataset (field boundaries from John Deere's schema to GeoJSON). The objects of the model's task are data and data-conversion code, and the model works as a component of the service, so it performs no task on a software architecture (rule 1). S4 is cited once, as ref. [10], for a general definition of an LLM as a probabilistic model that generates word sequences (Section 1.2, p. 2964). | J60: None
A61: S4-F23 | B61: S4 | C61: Dhar, Vaidhyanathan & Varma | D61: Leveraging Generative AI for Architecture Knowledge Management | E61: 2024 | F61: ICSA-C 2024 (IEEE), pp. 163-166; DOI 10.1109/ICSA-C63560.2024.00034 | G61: Duplicate of S9 | H61: Duplicate (main corpus) | I61: Same study as S9 of the main corpus (ICSA-C 2024, pp. 163-166, DOI 10.1109/ICSA-C63560.2024.00034, IEEE Xplore 10628192); the title and the three authors match. The original is in the main workbook (Final-TA, Included studies, S9), where it is included and coded in family F3 with S4, so it is not screened or coded again here. Its link to S4 rests on our main-corpus coding of S9, whose empirical content is a restated summary of S4's study (same models, metrics and repository); S4's own reference list cites S9 as companion work. The IEEE page could not be opened to check S9's reference list. | J61: Not checked
A62: S4-F24 | B62: S4 | C62: Zhao, Jin, Zhang, Fan, Wang, Li, Liu & Liu | D62: Software Architecture Recovery Augmented With Semantics | E62: 2026 | F62: IEEE TSE 52(1), pp. 338-359 (January 2026); DOI 10.1109/TSE.2025.3620670 | G62: Included as FS17 | I62: Primary study: SemArc recovers the module architecture of a system from its source code, with an LLM summarising each file and inferring the system's architectural patterns and components from a knowledge base of canonical patterns; the components anchor a clustering that also uses explicit and implicit dependencies. It is evaluated on 15 C/C++, Java and Python projects against seven baselines and on 30 further projects. In scope (rule 1): the model's task object is the architecture of an existing system (recovery, 1.4). Peer reviewed: IEEE TSE (received 8 February 2025, accepted 3 October 2025, online 14 October 2025). S4 is cited once, as ref. [59] (its arXiv version), in the related work on LLMs for architecture-level decisions (Section VI-B, p. 357). It also cites S10 (ref. [60]). | J62: S10
A63: S4-F25 | B63: S4 | C63: Ibáñez, Barrón-Estrada & Zatarain-Cabada | D63: Can Multimodal Large Language Models Grade Like an Expert? A Study on UML Class Diagram Assessment Accuracy | E63: 2025 | F63: Computer Applications in Engineering Education 33(5), e70080; DOI 10.1002/cae.70080 | G63: Excluded | H63: Out of scope (rule 1) | I63: Primary study: four multimodal LLMs (ChatGPT-4, Gemini, Amazon AI, Claude 3.5 Sonnet) grade UML class diagrams drawn by 34 engineering students for an exercise on the Open-Closed Principle, compared with three instructors' consensus scores, with a grounded-theory classification of the models' grading errors. The object of the model's task is a student's class-level object-oriented design in a teaching exercise, graded against SOLID principles, not a software architecture, so it is out of scope (rule 1); it sits in software engineering education and detailed design. S4 is cited once, as ref. [70], in a group of works [70-72] on generative models lacking the depth needed to evaluate complex, structured artefacts (Section 5, p. 12). | J63: None
A64: S4-F26 | B64: S4 | C64: Tian, Sobczak, Patil, Hou, Pang, Ramanathan, Yang, Chen, Golan, Zhai, Sun, Song & Wang | D64: CrossMatAgent: AI-Assisted Design of Manufacturable Metamaterial Patterns via Multi-Agent Generative Framework | E64: 2026 | F64: Advanced Intelligent Discovery 2(4), e202500063; DOI 10.1002/aidi.202500063 | G64: Excluded | H64: Out of scope (rule 1) | I64: Primary study (received 4 April 2025, accepted 2 July 2025): CrossMatAgent, a multi-agent framework in which GPT-4o agents analyse metamaterial patterns, write descriptions and prompts, and supervise image generators (DALL-E 3 and a fine-tuned Stable Diffusion XL) that produce simulation- and 3D-printing-ready metamaterial patterns, evaluated with CLIP alignment, SHAP and finite-element simulations. The objects of the model tasks are metamaterial patterns and their descriptions; 'architectural synthesis' and the agent named Architect refer to the geometry of the material, not to a software architecture, and the agent framework is the system that runs the task (rule 1). S4 is cited once, as ref. [44] (with arXiv in the entry), in a group of works [42-46] on fine-tuning pre-trained models (Section 1, p. 2). | J64: None
A65: S4-F27 | B65: S4 | C65: Dhar, Kakran, Karan, Vaidhyanathan & Varma | D65: DRAFT-ing Architectural Design Decisions using LLMs | E65: 2025 | F65: arXiv 2504.08207 (v1, April 2025); submitted to JSS; no published version found | G65: Excluded | H65: Not peer reviewed | I65: arXiv preprint (v1, 11 April 2025, the only version; marked 'Preprint submitted to JSS', and also posted on SSRN); no peer-reviewed version was found. Karthik Vaidhyanathan's publication page lists it under CoRR only, while his published papers carry their venues (checked 28 September 2026), and DBLP records it under CoRR as an informal publication. It is therefore excluded on its record. On its content it would be in scope and would belong to family F3: DRAFT, by the S4 authors and two others, fine-tunes an LLM with retrieved ADR examples to generate the decision of an ADR from its context, and compares few-shot, RAG and fine-tuning on 4,911 ADRs with automated metrics and human evaluation; revisit if a peer-reviewed version appears. S4 is its authors' previous work, ref. [12], cited in the introduction, the approach, the results and the related work. It also cites S7 (ref. [48]), as a vision of generating architecture candidates from requirements (Section 8, p. 20). It also cites S8 (ref. [50]), as an AI assistant among the approaches to reducing ADR effort (Section 8, p. 20). | J65: S7, S8
A66: S4-F28 | B66: S4 | C66: Li, Zhang, Zhou, Liang, Sun, Xuan, Jin & Liu | D66: MAAD: Automate Software Architecture Design through Knowledge-Driven Multi-Agent Collaboration | E66: 2025 | F66: arXiv 2507.21382 (v1, July 2025), TOSEM template; no published version found | G66: Excluded | H66: Not peer reviewed | I66: arXiv preprint (v1, 28 July 2025) in the ACM TOSEM template with placeholder volume, article number and DOI, that is, a manuscript under review; no published version was found in a web search on 28 September 2026 (the arXiv page itself could not be opened for its version history). It is therefore excluded on its record. On its content it would be in scope and would join family SF13 as the full paper of the MAAD framework in FS14 (its ref. [12]): four agents (Analyst, Modeler, Designer, Evaluator) produce architecture designs and evaluation reports from requirements specifications, compared with MetaGPT, with feedback from industrial architects on 11 specifications and three LLMs; revisit if a peer-reviewed version appears. S4 is cited once, as ref. [24], in the related work on LLMs for architecture (Section 2, p. 5). It also cites S5 (ref. [36]), S7 (ref. [23]) and S11 (ref. [20]), and FS02, S4-F10 (excluded study) and FS14. | J66: S5, S7, S11
A67: S4-F29 | B67: S4 | C67: Soliman, Ashraf, Abdelsalam, Keim & Venkatesh | D67: LLMs for Software Architecture Knowledge: A Comparative Analysis Among Seven LLMs | E67: 2025 | F67: ECSA 2025, LNCS 15929, pp. 99-115 (Springer, 2026); DOI 10.1007/978-3-032-02138-0_7 | G67: Included as FS18 | I67: Primary study: seven LLMs (Qwen2, DeepSeek-R1-Distill-Llama, GPT-4o, GPT-4o mini, Llama 3.3, TinyLlama, Mistral Large) answer 229 questions written by software engineers about the architectural knowledge of Hadoop HDFS (components and connectors, quality attribute solutions, rationale of decisions); answers are scored against ground truth and the models' responses compared with each other. In scope (rule 1): the model's task object is the architecture of an existing system, as in S5, whose questions and ground truth it reuses. Peer reviewed: ECSA 2025 (LNCS 15929). S4 is cited once, as ref. [13], together with S9, for using GPT and T5 to recommend design decisions (Section 7.2, p. 111). It also cites S5 (ref. [37]), S8 (ref. [15]), S9 (ref. [14]) and FS15 (ref. [19]). | J67: S5, S8, S9
A68: S4-F30 | B68: S4 | C68: Bialek, Groenboom & Andrikopoulos | D68: Software architecture for machine learning to aid sustainable digital transformation: A systematic mapping study | E68: 2026 | F68: Information and Software Technology 190, art. 107931 (systematic mapping study) | G68: Excluded | H68: Out of scope (rule 1) | I68: Systematic mapping study (received 10 March 2025, revised 8 October 2025, accepted 13 October 2025, online 27 October 2025) of 150 studies found with a search on sustainability and digital transformation together with software architecture or machine learning. It maps how the three fields intersect, which sustainability dimensions are addressed, which application domains are covered (GICS sectors and industry groups) and which MLOps architecture components the studies mention. Its topic is software architecture for ML-based systems, so the models it maps are components of the systems being architected and perform no task on a software architecture (rule 1); the other research area, ML that supports the architecting of software, is only named in the background. It synthesises no architectural model task, so it could not meet the review threshold either. S4 is cited once, as ref. [21], together with S8 (ref. [22]), as an example of that other area (Section 2.2, p. 3). | J68: S8
A69: S4-F31 | B69: S4 | C69: Diaz-Pace, Tommasel, Capilla & Ramírez | D69: Architecture Exploration and Reflection meet LLM-based Agents | E69: 2025 | F69: ICSA-C 2025 (IEEE); DOI 10.1109/ICSA-C65153.2025.00015; IEEE Xplore version read | G69: Duplicate of S3 | H69: Duplicate (main corpus) | I69: Same study as S3 of the main corpus (ICSA-C 2025); the title and all four authors match, and the content matches our coding of S3 (the ReArch design agents, adapted from ReAct and LATS, searching for patterns and tactics for textual requirements, applied to the mobility case study of ref. [6]). The original is in the main workbook (Final-TA, Included studies, S3), where it is included and coded in family F2, so it is not screened or coded again here. The full text (IEEE Xplore version) confirms that it cites S4 once, as ref. [14] (its arXiv version), together with Eisenreich et al., for using simple LLM prompting strategies to suggest, evaluate and document design alternatives (Section V, Related Work, p. 5 of the PDF). | J69: Not checked
A70: S4-F32 | B70: S4 | C70: de Oliveira & Mendonça | D70: LLM-Based Quality Assessment of Software Architecture Diagrams: A Preliminary Study with Four Open-Source Projects | E70: 2025 | F70: ECSA 2025, LNCS 15929, pp. 116-123 (Springer, 2026); DOI 10.1007/978-3-032-02138-0_8 | G70: Included as FS19 | I70: Primary study (short paper): ChatGPT-4o rates one architecture diagram and its textual description from each of four open-source projects on clarity, consistency, completeness, accuracy and level of detail, with justifications and suggestions, and one software architecture expert reviews its assessments. In scope (rule 1): the model's task object is the architecture documentation of existing systems, which it assesses against the architecture the text describes (1.3, 1.4). Peer reviewed: ECSA 2025 (LNCS 15929). S4 is cited once, as ref. [4] (its arXiv version), for LLMs in architectural decision support (Section 2, p. 117). It also cites S11 (ref. [1]) and FS02's arXiv preprint (ref. [6]). | J70: S11
A71: S4-F33 | B71: S4 | C71: Rubei, Di Salle & Bucaioni | D71: LLM-Based Recommender Systems for Violation Resolutions in Continuous Architectural Conformance | E71: 2025 | F71: ICSA-C 2025 (IEEE), pp. 404-409; DOI 10.1109/ICSA-C65153.2025.00063 | G71: Included as FS20 | I71: Primary study (six pages): an LLM-based recommender added to the authors' model-driven conformance tool proposes resolutions for violations of a reference architecture; Gemini 1.5 and ChatGPT-4o are evaluated on 16 IoT architectures mutated by the authors. In scope (rule 1): the model's task object is a software architecture, which it corrects to conform to a reference architecture (1.4). Peer reviewed: ICSA-C 2025 (IEEE); the companion track is not named on the paper, and FS19 cites it as a paper of the MDE4SA 2025 workshop. S4 is cited once, as ref. [14], for a tool that helps architects write ADRs with GPT and T5 models, zero- and one-shot prompting and fine-tuning (Section V, p. 408). It also cites S8 (ref. [13]). | J71: S8
A72: S4-F34 | B72: S4 | C72: Sathvika, Dhar & Vaidhyanathan | D72: LLM-based Automated Architecture View Generation: Where Are We Now? | E72: 2026 | F72: ICSA 2026 (IEEE), pp. 245-256; DOI 10.1109/ICSA66085.2026.00031 | G72: Included as FS21 | I72: Primary study: three LLMs with zero-, one- and few-shot prompts, a general-purpose coding agent and a custom multi-agent approach (ArchView) generate architecture views from hierarchical summaries of the source code of 340 open-source repositories, evaluated against manually coded ground-truth views by an LLM judge, image similarity and a blinded human evaluation (4,137 views, 13 configurations). In scope (rule 1): the model's task object is the architecture of an existing system, recovered from its code and documented as views (1.3, 1.4). Peer reviewed: ICSA 2026 (IEEE). S4 is cited once, as ref. [59] (its arXiv version, dated 03 2024), for prior work on automated generation of ADRs (Section VII, p. 254). It also cites S9 (ref. [60]), S10 (ref. [56]), FS02 (ref. [10]), FS19 (ref. [14]) and S4-F11 (ref. [58]). | J72: S9, S10
A73: S4-F35 | B73: S4 | C73: Taherkhani, Sepidband, Pham, Wang & Hemmati | D73: Automated Prompt Engineering for Cost-Effective Code Generation Using Evolutionary Algorithms | E73: 2026 | F73: ACM Transactions on Software Engineering and Methodology (TOSEM), 2026; DOI 10.1145/3805704 | G73: Excluded | H73: Out of scope (rule 1) | I73: Primary study (ACM TOSEM, 2026, online with DOI; volume and article number not yet assigned on the version read): EPiC evolves the prompts given to an LLM for code generation with a lightweight evolutionary algorithm whose fitness is the pass rate of generated tests, and compares it with agent-based code generators (Reflexion, LATS, LDB, Self-Collaboration) and Self-Consistency on HumanEval+, MBPP+ and BigCodeBench with o3-mini, DeepSeek-V3 and Claude 3.7 Sonnet, for pass@k and for the extra tokens and cost per solved problem. The object of the model's task is the code of single functions and the prompts that produce it, not a software architecture (rule 1). S4 is cited once, as ref. [7], together with a work on GUI prototyping, as an example of LLMs used in software design (Section 1, p. 1). | J73: None
A74: S4-F36 | B74: S4 | C74: Adnan, Gupta, Akshathala & Vaidhyanathan | D74: ArchBench: Benchmarking Generative-AI for Software Architecture Tasks | E74: 2026 | F74: ICSA 2026 Software Architecture Showcase track (accepted, per arXiv comment); arXiv 2603.17833v1 read | G74: Included as FS22 | I74: Tool and benchmark paper (five pages): ArchBench, a platform for benchmarking LLMs and agents on software architecture tasks, with a command-line pipeline (dataset download, logged inference, automated evaluation), a public leaderboard and five tasks from published studies, two of them architectural (ADR generation, trace-link recovery between architecture documentation and code) and three code generation. It runs no model and reports no results. Included by the user's decision under the proposed-task clause (rule 3): it specifies benchmark tasks whose object is a software architecture. Peer review accepted on our judgement: the version read is arXiv v1 (18 March 2026), whose comment states acceptance in the ICSA 2026 Software Architecture Showcase track, where the programme lists it; no published version was found, and the track's review process could not be checked. S4 is cited three times, as ref. [7]: with a survey, for optional LLM-as-judge assessment (Section II, p. 2); as the source of the ADR generation task and its dataset (Section II, p. 3); and for the difficulty of comparing studies that use their own datasets and metrics (Section IV, p. 4). It also cites FS15 (ref. [9]), FS02 (ref. [1]) and S4-F11 (ref. [5]). | J74: None
A75: S4-F37 | B75: S4 | C75: Garg, Shaik, Bandyopadhyay & Caragea | D75: Towards AI-Assisted Research Writing: Benchmarking LLMs for AI/ML Introduction Generation | E75: 2026 | F75: arXiv preprint 2508.14273 (v3, 31 Aug 2026) | G75: Excluded | H75: Out of scope (rule 1) | I75: Benchmark study: five LLMs (DeepSeek-V3, Gemma-3-12B, LLaMA 4 Maverick, Mistral Small 3.1, GPT-4o) generate the introductions of machine-learning papers from their titles, abstracts and related work, on new datasets from NAACL 2025 and ICLR 2025, scored by automated metrics, LLM-as-a-judge and a human evaluation of 80 outputs. The object of the model's task is the introduction of a research paper, not a software architecture (rule 1). The version read is arXiv 2508.14273v3 (31 August 2026); its project page is labelled for EMNLP 2026, but a peer-reviewed version was not checked, since the scope decision does not depend on it. S4 is cited once, as Dhar et al. (2024), as a recent benchmarking study in which each output was annotated by a single annotator (Section 7, p. 8). | J75: None
A76: S4-F38 | B76: S4 | C76: Duits, El Moutaouakil & Malavolta | D76: Can Large Language Models Assist the Comprehension of ROS2 Software Architectures? | E76: 2026 | F76: EASE 2026 (ACM); arXiv 2604.21699v1 read | G76: Included as FS23 | I76: Primary study: nine commercial LLMs answer 1,230 generated questions each about the architecture of three ROS2 systems (entities, publish and subscribe relations, services, communication paths, interface types), given the computation graph extracted from each running system as JSON, checked against a ground truth derived from the graph. In scope (rule 1): the model's task object is the architecture of existing systems, their nodes and connectors (1.4). Peer reviewed: EASE 2026 (ACM); the version read is arXiv v1 (23 April 2026) with the EASE 2026 reference block and a placeholder DOI. S4 is cited as ref. [12]: with FS02, for LLMs assisting architects in design decision making (Section 1, p. 1), and in the related work and its Table 1 (Section 3, pp. 2-3). It also cites S5 (ref. [39]), S8 (ref. [13]), FS18 (ref. [38]), S4-F10 (excluded study)'s arXiv version (ref. [37]), FS02 (ref. [17]) and S4-F18 (ref. [40]). | J76: S5, S8
A77: S4-F39 | B77: S4 | C77: Cervantes, Kazman & Cai | D77: Improving LLM-assisted code generation through the use of architectural documents and implementation plans | E77: 2026 | F77: Designing '26 (3rd International Workshop on Designing Software, ACM), pp. 23-30; DOI 10.1145/3786152.3788588 | G77: Excluded | H77: Out of scope (rule 1) | I77: Primary study (workshop paper): an LLM-based coding agent (Cursor, automatic model selection) first writes an implementation plan from a requirements document and an architecture document produced with the authors' ADD approach (FS08), and then generates the code phase by phase; three experiments on a ReAct-style agent (with document and plan, with the document only, from requirements only) are compared by the authors for conformance of the code to the design, functional correctness of the main use case, and size and modularity measured with DV8; Kiro's workflow is tried as well. The architecture is an input and the model's task object is the implementation plan and the code, so it is out of scope (rule 1), as S4-F11 was; the conformance of the code to the architecture is assessed by the authors, not by the model. Had it been in scope it would join FS08 in SF7 (same three authors, and its architecture document comes from FS08's approach). Peer reviewed: Designing '26, 3rd International Workshop on Designing Software (ACM), pp. 23-30. S4 is cited once, as ref. [9], with S10, among studies of LLMs making architecture decisions (Section 2, p. 24). It also cites S10 (ref. [10]), S4-F11 (ref. [11]) and, as ref. [2], an arXiv preprint (2506.22688) by the same authors whose title matches FS08's subtitle. | J77: S10
A78: S4-F40 | B78: S4 | C78: Gürtl, Scharf, Thrainer, Gütl & Steinmaurer | D78: Design and Evaluation of an LLM-Based Mentor for Software Architecture in Higher Education Project Management Classes | E78: 2024 | F78: ICL 2024, LNNS 1280, pp. 375-386 (Springer, 2025); DOI 10.1007/978-3-031-83523-0_35 | G78: Included as FS24 | I78: Primary study: a Socratic LLM mentor (Mistral 7B), whose dialogue follows seven design steps derived from 18 software engineers, guides first-year students in designing a system architecture from a project description and requirements; 39 students, with and without the mentor, and their architectures rated on a rubric. In scope (rule 1): the model's task object is the architecture the student is designing, whose components and relationships it identifies and suggests (1.1, 1.2), as with FS07's tutor. Peer reviewed: ICL 2024 (Springer LNNS 1280, pp. 375-386, 2025), as the Springer page confirms; the author's version was read. S4 is cited twice, as ref. [15] (its arXiv version): in the related work, for LLMs proposing design choices by generating ADRs from a decision context (Section 2, p. 3), and for LLMs' limited ability to raise high-level design quality without considerable human input (Section 6.1, p. 9). It also cites S7 (ref. [14], its arXiv version). | J78: S7
A79: S4-F41 | B79: S4 | C79: Zhang, Liu, Sun, Xu, Sun, Li, Jin & Liu | D79: Semantic-Enhanced Automatic Refinement of Architecture Recovery Results Using LLMs | E79: 2026 | F79: ICSE '26, pp. 1687-1699; DOI 10.1145/3744916.3773114 (details pasted from the ACM page) | G79: Duplicate of S1-F06 | H79: Duplicate | I79: Same article as S1-F06, reached again through S4; the details sent (title, all eight authors, ICSE '26, pp. 1687-1699, DOI 10.1145/3744916.3773114) match S1-F06, so the full text did not need to be read again. The S1-F06 full text cites S4 once, as ref. [14] (its arXiv version), among works in which LLMs assist architects with design decisions and knowledge access (Section 2, p. 1689). The original is on this sheet (S1-F06), included and coded as FS03, so it is not screened or coded again. | J79: As S1-F06
A80: S4-F42 | B80: S4 | C80: Compagnucci, Lu & Trubiani | D80: Agentic Runtime Reconfiguration of Architectural Patterns in Federated Learning | E80: 2026 | F80: Journal of Systems and Software 240, art. 112966 (details pasted from ScienceDirect) | G80: Duplicate of S3-F04 | H80: Duplicate | I80: Same article as S3-F04, reached again through S4; the details sent (title, the three authors Compagnucci, Lu and Trubiani, ScienceDirect article S0164121226001998 in the Journal of Systems and Software) match S3-F04, so the full text did not need to be read again. The S3-F04 full text cites S4 as Dhar et al. (2024a): with S9 (2024b) among works in which LLMs support architectural decisions (Section 1, p. 2), and for its empirical study of LLMs generating design decisions as ADRs (Section 3.1, p. 3); in Section 3.1 (p. 4) S4's study is also described under the label 2024b, which the reference list assigns to S9. The original is on this sheet (S3-F04), included and coded as FS09, so it is not screened or coded again. | J80: As S3-F04
A81: S4-F43 | B81: S4 | C81: Li, Zhang, Yan, Liu, Li, Liu & Lian | D81: Benchmarking Requirement-to-Architecture Generation with Hybrid Evaluation | E81: 2026 | F81: arXiv preprint 2604.06683 (v3, 9 Sep 2026) | G81: Excluded | H81: Not peer reviewed | I81: arXiv preprint (v3, 9 September 2026) in an IEEE conference template without a venue, copyright notice or DOI; the arXiv page could not be read, and a web search found no peer-reviewed version (only arXiv, ResearchGate and aggregator listings). It would be in scope (rule 1, 1.1): R2ABench pairs 68 structured requirements specifications with human-validated reference architecture views in PlantUML, and LLMs (among them GPT-5, Claude Sonnet 4.6, DeepSeek V3.2, Qwen3-Coder) are run directly and inside agent frameworks (MetaGPT, Mini-SWE, OpenHands) to generate views from the requirements, scored by syntax checks, graph metrics and LLM judges; revisit if it is published. S4 is cited once, as ref. [33], for studies of whether LLMs can generate architectural design decisions or ADR-like artefacts (Section VII, p. 10). It also cites FS21 (ref. [12]), FS02 (ref. [8]) and S4-F10 (excluded study)'s arXiv version (ref. [32]). | J81: None
A82: S4-F44 | B82: S4 | C82: Falcão, Elberzhager & Vaidhyanathan | D82: Toward architecting self-coding information systems | E82: 2026 | F82: ICSE-Companion '26 (ACM), pp. 510-512; DOI 10.1145/3774748.3795876 | G82: Excluded | H82: Out of scope (rule 3) | I82: Extended abstract (three pages) proposing self-coding information systems as a research topic: systems that implement functional requirements or address quality requirements by generating, testing and (re)deploying the source code of at least one subsystem at runtime, assumed to use LLM-based coding agents; it gives a definition, expected impacts (architectural trade-offs, roles, social and organisational aspects) and research directions. It runs no model, and the model task it specifies is the generation of source code at runtime, not a task whose object is a software architecture; self-architecting systems that document their design decisions and review their architectures are named only as a possible later evolution, without being specified. Out of scope (rule 3); the object of the specified task is also code (rule 1). Peer reviewed: ICSE-Companion '26 (ACM), pp. 510-512; DOI 10.1145/3774748.3795876. S4 is cited once, as ref. [6], as an example of generative AI supporting architects at development time, by generating architectural design decisions (Section 1, p. 510). It also cites S10 (ref. [10]), FS19 (ref. [5]), FS02 (ref. [7]) and S4-F22 (ref. [8]). | J82: S10
A83: S4-F45 | B83: S4 | C83: Fokaefs, Khan & Ahmadzadeh | D83: Can AI Build Systems? An Exploratory Study on Generating Software Architecture with LLMs | E83: 2025 | F83: CASCON 2025 (IEEE), pp. 399-408; DOI 10.1109/CASCON66301.2025.00069 | G83: Included as FS25 | I83: Primary study: o3, Gemini 2.0 Flash and Llama 4 Maverick, with three prompting strategies, generate high-level UML component architectures from the natural-language descriptions of two open-source systems, alone and in 81 two-model drafter-refiner chains, compared with the documented architectures. In scope (rule 1): the model's task object is the architecture of the system to be built, generated from its requirements (1.1). Peer reviewed: CASCON 2025 (IEEE), pp. 399-408. S4 is cited once, as ref. [10] (its arXiv version), for LLMs producing plausible design decisions from structured context but sometimes lacking comprehensive rationales (Section II, p. 400). It also cites S7 (ref. [12]) and S11 (ref. [11]). | J83: S7, S11
A84: S4-F46 | B84: S4 | C84: Kim, Kwon, Bae & Lee | D84: Integrating IS success and open innovation in enterprise LLM adoption: a dual-path model of net benefits and usage growth | E84: 2026 | F84: Behaviour & Information Technology (Taylor & Francis), online 3 Aug 2026; DOI 10.1080/0144929X.2026.2711036 | G84: Excluded | H84: Out of scope (rule 1) | I84: Primary study in information systems (received 10 March 2026, accepted 18 July 2026, online 3 August 2026): a survey of 261 firm representatives, analysed with PLS-SEM, tests how firms' evaluations of LLM quality (IS success model) and their learning and open-innovation capabilities shape perceived net benefits and growth in LLM usage, with a post-hoc experiment on 148 employees about information quality and user satisfaction. No model performs a task in the study; its object is organisational adoption of LLMs and its financial outcomes, not a software architecture (rule 1). S4 is cited once, among studies reporting positive outcomes of LLM use, for improved decision making (Section 2.1, p. 3). | J84: None
A85: S4-F47 | B85: S4 | C85: Jackson, Cha, Prikladnicki & van der Hoek | D85: The Role of LLMs in Collaborative Software Design | E85: 2026 | F85: FSE Companion '26 (ACM), pp. 1783-1792; DOI 10.1145/3803437.3806702 | G85: Included as FS26 | I85: Primary study (exploratory lab study): 18 pairs of software professionals design a campus bicycle-parking app from a requirements document with optional access to GPT-3.5 Turbo; the paper reports how pairs share the model, the roles they give it (none, information source, generator, producer) and how they interpret its output. In scope (rule 1): the design includes the system's architecture, and the model is used on it: pairs had it produce whole designs as overviews of the core architectural components and their interactions, draft deployment diagrams and a C4 model, and lay out backend architecture options with their trade-offs; it is a human-centred study of design with a model, as S11 is of architecting with ChatGPT. Peer reviewed: FSE Companion '26 (ACM), pp. 1783-1792. S4 is cited once, as ref. [13], for LLM-generated ADRs that cannot be relied on without human review (Section 2.2, p. 1784). It also cites S8 (ref. [14]). | J85: S8
A86: S4-F48 | B86: S4 | C86: Pegado, Camarinha-Matos & Rocha | D86: A Brief Survey on Human-AI Collaboration for Architecture Design of Industrial Systems | E86: 2025 | F86: PRO-VE 2025, IFIP AICT 770 (Springer, 2026); DOI 10.1007/978-3-032-05673-3_4; authors' preprint read | G86: Excluded | H86: Out of scope (review threshold) | I86: Brief survey, combining conceptual modelling, literature synthesis and project experience, of architecture design for industrial (manufacturing) systems: most of it reviews architecture description languages and tools and their limits for manufacturing (Tables 1-3), followed by a one-page section on human-AI collaborative design and a conceptual table of human and AI roles across systems engineering (Table 4), and directions on multi-agent systems and Asset Administration Shells. Model tasks with an architectural object are not a synthesised part of it: the AI section consists of prospective statements (AI could suggest adjustments, generate and refactor architecture as code, explain design artefacts), each resting on a single citation, with no studies compared or synthesised, so it falls below the review threshold. Peer reviewed: PRO-VE 2025, Hybrid Human-AI Collaborative Networks, IFIP AICT 770 (Springer, 2026); the authors' preprint was read. S4 is cited once, as ref. [71], for AI technologies that could play a transformative role in future collaborative architectural design environments (Section 5, p. 10). | J86: None
A87: S4-F49 | B87: S4 | C87: Feng, Yang, Chen, Luo, Wang, Zhou, Xu & Leung | D87: E2LLM: Structure-Guided Efficient Inference for LLMs in Distributed Edge-IoT Environments | E87: 2026 | F87: IEEE Transactions on Mobile Computing 25(9), pp. 14239-14253 (September 2026); DOI 10.1109/TMC.2026.3676689 | G87: Excluded | H87: Out of scope (rule 1) | I87: Primary study (received 12 December 2025, accepted 18 March 2026): E2LLM, a framework for distributed LLM inference in edge-IoT environments, in which edge devices plan the structure of a response and lightweight auxiliary models generate segment-specific key-value caches so that IoT devices decode segments in parallel, evaluated on edge testbeds for latency, communication, energy and generation quality. The object of the work is the deployment and inference of LLMs; the models generate text and are components of the system, and no model performs a task on a software architecture (rule 1). S4 is cited once, as ref. [11], for 'architectural simplification' of models among techniques for deploying LLMs on constrained devices (Section I, p. 14239), a topic S4 does not address. | J87: None
A88: S4-F50 | B88: S4 | C88: Cao, Zhang, Li, Zhong, Li, Fan, Zhang & Zdun | D88: Leveraging Large Language Models for Event Storming in Domain-Driven Design: A Controlled Experiment | E88: 2026 | F88: ICSA 2026 (IEEE), pp. 323-334; DOI 10.1109/ICSA66085.2026.00039 | G88: Excluded | H88: Out of scope (rule 4) | I88: Primary study (controlled experiment): 240 postgraduate students in 60 teams build Big Picture Event Storming models of a library management system from a requirements document, manually and then with one of six LLMs (GPT-4o, o4-mini, two DeepSeek models, Qwen3-235B, Qwen3-32B) under basic and optimised prompts; models are scored for accuracy, completeness and consistency against a reference model provided by domain experts. The model's task object is a business domain model (domain events, commands, actors, policies and hotspots of a business process), not a software architecture: the study deliberately stays at the Big Picture level and leaves the design-level work of defining aggregates and bounded contexts to future work, so it is out of scope under the knowledge-artefact rule (rule 4); the authors frame domain modelling as the early phase of architecture design, but framing does not decide scope (rule 2). Peer reviewed: ICSA 2026 (IEEE), pp. 323-334. S4 is cited as ref. [10], among work on LLMs for software architecture design (Section I, p. 323) and for supporting architectural design decisions (Section III, p. 325). It also cites S8 (ref. [11]), S10 (ref. [33]), FS14 (ref. [12]), FS02 (ref. [32]), S4-F10 (excluded study)'s arXiv version (ref. [31]) and S4-F11 (ref. [13]). | J88: S8, S10
A89: S4-F51 | B89: S4 | C89: Cervantes, Kazman & Cai | D89: Better Together: An LLM-assisted approach to designing software architectures using Attribute-Driven Design | E89: 2026 | F89: IEEE Transactions on Software Engineering (early access, 2026); DOI 10.1109/TSE.2026.3706446 | G89: Duplicate of S3-F03 | H89: Duplicate | I89: Same article as S3-F03, reached again through S4: the PDF sent is the same IEEE Xplore early-access version (DOI 10.1109/TSE.2026.3706446), and its text is identical to the S3-F03 file apart from the download stamps. It cites S4 once, as ref. [18] (its arXiv version), for an exploratory empirical study of whether LLMs can generate architectural design decisions (Section II-A, p. 2); it also cites S9 (ref. [27]) and S4-F27, the DRAFT preprint (ref. [21]). The original is on this sheet (S3-F03), included and coded as FS08, so it is not screened or coded again. | J89: As S3-F03
A90: S4-F52 | B90: S4 | C90: Cervantes, Cai & Kazman | D90: Large Language Models as Assistants in Software Architecture Design | E90: 2026 | F90: IEEE Software 43(4), pp. 87-95 (July/August 2026); DOI 10.1109/MS.2026.3663353 | G90: Included as FS27 | I90: Primary study (magazine feature): GPT-4o generates 14 design problems with quality-attribute requirements, each with four design-concept alternatives and their pros and cons; four LLMs choose among the alternatives, and 23 participants of the Designing 2025 workshop choose for five of the problems. In scope (rule 1): the model's task object is architectural design, the selection of design concepts (patterns, tactics, technologies) for quality-attribute problems (1.2). Peer reviewed: IEEE Software 43(4), pp. 87-95. S4 is cited once, as ref. 8, for LLMs generating relevant design decisions that do not yet reach human level (Related Work, p. 89). It also cites S5 (ref. 9) and S8 (ref. 7). | J90: S5, S8
A91: S4-F53 | B91: S4 | C91: Töpfer, Khalyeyev, Bureš, Hnětynka & Plášil | D91: How Well Do LLMs Understand DEECo Ensemble-Based Component Architectures | E91: 2024 | F91: ISoLA 2024, LNCS 15220, pp. 208-223 (Springer, 2025); DOI 10.1007/978-3-031-75107-3_13 | G91: Included as FS28 | I91: Primary study (exploratory): GPT-4 Turbo, with file-system access to the specifications and code of three DEECo applications written in three DSLs, answers questions about their ensemble-based component architectures (components, ensembles, roles, membership conditions, and which ensembles form in a given state). In scope (rule 1): the model's task object is the architecture of existing collective adaptive systems (1.4). Peer reviewed: ISoLA 2024, LNCS 15220, pp. 208-223 (Springer, 2025). S4 is cited once, as ref. [8] (its arXiv version, 'accepted to ICSA 2024'), for LLMs generating design decisions from a decision context without yet reaching human-level correctness (Section 5, p. 221). It also cites S11 (ref. [1]). | J91: S11
A92: S4-F54 | B92: S4 | C92: Sambu, Capuano, O'Dea, Vaidhyanathan & Muccini | D92: LLMs for Architectural Refactoring: An Exploratory Study on Monoliths to Microservices | E92: 2026 | F92: ICSA 2026, 23rd IEEE International Conference on Software Architecture, pp. 268-279; DOI 10.1109/ICSA66085.2026.00033 | G92: Included as FS29 | I92: Primary study (exploratory): four LLMs (GPT-5, Gemini 2.5 Pro, GLM-4.6, DeepSeek 3.2 Terminus) decompose four monolithic Java systems into microservices through a three-phase pipeline (repository summarisation, generation of five architectural views, single-shot service decomposition with a static dependency graph), evaluated against reference decompositions and published tool results from an established benchmark. In scope (rule 1): the model's task object is the architecture of existing systems, their decomposition into services (1.4). Peer reviewed: ICSA 2026 (IEEE), pp. 268-279. S4 is cited once, as ref. [13], together with S10 (ref. [14]) and S5 (ref. [15]), for the limited empirical work on LLMs supporting architectural reasoning and system-level design decisions (Section I, p. 268). | J92: S5, S10
A93: S4-F55 | B93: S4 | C93: Adil, Fronza, Mikkonen, Ihantola & Iaccarino | D93: GenAI as an Instant, Readily Available Co-Developer: Redefining Software Design Process for AI Native Hybrid Work | E93: 2026 | F93: Automated Software Engineering 33, article 94 (Springer, 2026), 16 pp.; DOI 10.1007/s10515-026-00648-3 | G93: Excluded | H93: Out of scope (rule 3) | I93: Vision paper with a research agenda: challenges of hybrid software design found in the authors' earlier study (missed in-room discussions, undocumented rationale, early splitting of work, unclear architectural decisions, interrupted designs) are mapped to roles GenAI could play as a co-developer, with a conceptual interaction model, three research questions and a discussion of limitations. It runs no model and presents no technical artefact, as the authors state (Section 7, p. 13). The model tasks it outlines, given as illustrative examples in Table 1 (p. 7), are summarising design discussions for remote members, logging rationale from chat messages, prompting alignment checks and retrieving earlier discussions; their object is the team's communication and collaboration, with architecture only as the topic of some stored discussions, and no architectural model task is specified beyond one example row. Out of scope (rule 3); the object of the outlined tasks is also the collaboration process rather than an architecture (rule 1). Peer reviewed: Automated Software Engineering (Springer), received 18 July 2025, accepted 18 July 2026. S4 is cited three times, as Dhar et al. 2024, among work on GenAI supporting architectural reasoning and design activities (Sections 1, 4 and 5, pp. 2, 8, 9). It also cites S8 (Díaz-Pace et al. 2024) and S11 (Ahmad et al. 2023). | J93: S8, S11
A94: S4-F56 | B94: S4 | C94: Cao, Li, Fan, Li & Zhong | D94: A Grey Literature Review of AI-Native Applications | E94: 2026 | F94: arXiv preprint 2509.13144 (v2, 21 Jul 2026), marked 'Preprint submitted to Elsevier' | G94: Excluded | H94: Out of scope (rule 1) | I94: Grey literature review of 106 sources (web searches and GitHub open-source project documentation) on AI-native applications, systems built around generative AI as their core engine: it synthesises their defining characteristics, quality attributes (such as maintainability, scalability, adaptability and observability), technical implementation elements (core models, agentic systems, RAG) and opportunities and challenges, and proposes a dual-layered engineering blueprint. Its topic is the architecture of LLM-based systems, so the models it reviews are components of the systems being architected and perform no task on a software architecture (rule 1); it synthesises no architectural model task, so it could not meet the review threshold either. The version read is arXiv 2509.13144v2 (21 July 2026), a preprint submitted to an Elsevier journal; no peer-reviewed version was found in a web search on 28 Sep 2026, so it would also fail the peer-review criterion. S4 is cited once, as ref. [10], together with ref. [47] and S8 (ref. [11]), for generative AI applied to software architecture design (Section 2.2, p. 3). | J94: S8
A95: S4-F57 | B95: S4 | C95: Codabux & Galster | D95: Reframing Software Architecture and Design Skills in the Era of Generative Artificial Intelligence | E95: 2026 | F95: ICSE-Companion '26 (ACM), pp. 478-480; DOI 10.1145/3774748.3795868 | G95: Excluded | H95: Out of scope (rule 3) | I95: Three-page position paper proposing a research direction on how GenAI changes the skills architects need (understanding and analysing context, including prompt and context engineering, critical thinking, communication, collaboration, the skill level at which to use GenAI) and how architects develop skills when work is delegated to GenAI, with the risk of de-skilling. It runs no model, and the object of its argument is the skills of human architects; the architectural uses of GenAI it mentions (scenarios, components, ADRs, diagrams, erosion analysis) are cited from other work as background, without an architectural model task of its own being specified. Out of scope (rule 3). Peer reviewed: ICSE-Companion '26 (ACM), pp. 478-480. S4 is cited once, as ref. [9], as an example of GenAI producing documentation such as ADRs (Section 1, p. 478). It also cites S7 (ref. [11]). | J95: S7
A96: S4-F58 | B96: S4 | C96: Li, Zhang, Zhou, Cai, Liang, Sun, Xuan, Jin & Liu | D96: Bridging Requirements and Architecture: Multi-Agent Orchestration with External Knowledge and Hierarchical Memory | E96: 2026 | F96: arXiv 2606.01385 (v1, 31 May 2026), TOSEM template; no published version found | G96: Excluded | H96: Not peer reviewed | I96: arXiv preprint (v1, 31 May 2026) in the ACM TOSEM template with placeholder volume, article number and DOI, that is, a manuscript under review; no published version was found in a web search on 28 September 2026. It is therefore excluded on its record. It is a revised manuscript of the MAAD framework, under a new arXiv entry and title, of the preprint we logged as S4-F28 (arXiv 2507.21382), with one author added (Cai), and it states that it extends the authors' FSE 2025 vision paper (FS14, its ref. [47]). On its content it would be in scope and would join family SF13: four agents (Analyst, Modeler, Designer, Evaluator), with retrieval of architectural standards and patterns and a hierarchical design memory, turn requirements specifications into multi-view architectures with quality-attribute evaluation reports, compared with MetaGPT on 10 case studies with four LLMs (GPT-5.2, Qwen 3.5, Llama 3.3, DeepSeek-R1) and reviewed by six industry architects on 10 real-world specifications; revisit if a peer-reviewed version appears. S4 is cited once, as ref. [8], for GPT-4 generating relevant design decisions zero-shot without reaching human level, and GPT-3.5 becoming competitive few-shot (Section 2.2, p. 5). It also cites S7 (ref. [11]) and S11 (ref. [3]). | J96: S7, S11
A97: S4-F59 | B97: S4 | C97: Pereira, Albuquerque, Perkusich, Rodríguez, Díaz-Pace, Gorgônio & Perkusich | D97: Toward Generating Microservice Architectures from Textual Requirements with Large Language Models | E97: 2025 | F97: SBCARS 2025 (19th Brazilian Symposium on Software Components, Architectures, and Reuse), pp. 79-89; DOI 10.5753/sbcars.2025.14591 | G97: Included as FS30 | I97: Primary study (initial, exploratory): an OpenAI reasoning model (called 'GPT-4 o3') generates microservice architectures (services, responsibilities, inter-service links) from the textual requirements of two systems, Bookstore and PetClinic, under zero-shot and one-shot prompting; outputs are compared with reference decompositions extracted from the implemented systems and reviewed blind by experienced architects. In scope (rule 1): the model's task object is the architecture of the systems to be built (1.1). Peer reviewed: SBCARS 2025, pp. 79-89 (SBC Open Library, DOI 10.5753/sbcars.2025.14591). S4 is cited three times, as ref. [10]: with S10 (ref. [17]) for LLMs suggesting architectural structures (Section 1, p. 79), in related work for generating design alternatives in context (Section 2.2, p. 80), and for GPT-4's competitive performance in design tasks (Section 3, p. 82). | J97: S10
A98: S4-F60 | B98: S4 | C98: Vieira | D98: Leveraging LLMs for Trustworthy Software Engineering: Insights and Challenges | E98: 2025 | F98: IEEE Computer (cover feature), July 2025, pp. 79-90; DOI 10.1109/MC.2025.3546204 | G98: Excluded | H98: Out of scope (rule 3) | I98: Vision article: how LLMs could be integrated across the software life cycle (requirements, architectural design, code generation, analysis and testing, program repair and migration, deployment of infrastructure as code, issue management, continuous trustworthiness assessment) to support trustworthy software, and the challenges and research directions this raises. It runs no model. Architecture appears in one paragraph on design (p. 83), which the author calls 'presently only a hypothesis': LLMs might recommend patterns that fit trustworthiness requirements (for example, microservices with isolated data processing for a health-care system) and help weigh trade-offs such as scalability against security; and in one sentence on continuous assessment (pp. 84-85), where LLMs might analyse architectural choices and recommend adjustments for resilience. These are illustrative possibilities, not a specified architectural model task, so the article is out of scope (rule 3), as S4-F55 was. Peer reviewed: IEEE Computer cover feature (IEEE Computer Society). S4 is cited once, as ref. 4, for LLMs having been studied for supporting architectural decisions (p. 80). | J98: None
A99: S4-F61 | B99: S4 | C99: Warnett & Zdun | D99: AI-Powered Architecting for Industry 4.0 Cyber-Physical Production Systems: A Novel Approach, Research Problems and Challenges | E99: 2025 | F99: Software Architecture. ECSA 2025 Tracks and Workshops, LNCS 15982, pp. 155-168 (Springer; first online 5 September 2025, volume dated 2026); DOI 10.1007/978-3-032-04403-7_15 | G99: Included as FS31 | I99: Overview of the authors' research programme on architecting ML- and RL-based systems for Industry 4.0 cyber-physical production systems: six contributions (design-decision catalogues, an RLOps case study, a modelling method, automatic conformance checks, an LLM-based check of RL practices, LLM-based pipeline generation) placed in a CI/CD pipeline, proposals for further AI support, and four open challenges. It runs no model. Included by our decision under the proposed-task clause (rule 3): Section 5 (pp. 164-165) specifies two architectural model tasks, an LLM writing Python code against the authors' CodeableModels metamodel to generate the formal architecture model of a system from its code and schematics, and an LLM checking such models for conformance to catalogued architectural design decisions; both name their input, output and place in the pipeline, and their object is an architecture model. Peer reviewed: ECSA 2025 Tracks and Workshops (LNCS 15982, Springer); the track is not named on the paper or the Springer page. S4 is cited once, as ref. [22], for involving LLMs in architectural generation to automate synthesis, documentation and adaptation to changing needs (Section 2, p. 157). | J99: None
A100: S4-F62 | B100: S4 | C100: Wang, Li, Liang, Cai, Li, Shahin, Khan & Feng | D100: Using LLMs in Software Design: An Empirical Study of GitHub and A Practitioner Survey | E100: 2026 | F100: arXiv preprint 2605.01392 (v2, 19 Sep 2026), marked 'Preprint submitted to Elsevier'; no published version found | G100: Excluded | H100: Not peer reviewed | I100: arXiv preprint (v2, 19 September 2026) marked as submitted to an Elsevier journal; no published version was found in a web search on 29 September 2026 (only arXiv, its replication package on GitHub and aggregator pages). It is therefore excluded on its record. Mixed-methods study: 291 developer-ChatGPT conversations shared on GitHub, mined for design tasks, coded into nine categories (Architecture Design among them, with 52 tasks) and characterised by interaction type and design level, and a survey of 65 practitioners on benefits and limitations. On its content it would be in scope (rule 1): in the Architecture Design conversations the model works on the architecture of the developers' systems (decomposition, messaging, integration), as in the human-centred studies S11 and FS26; revisit if a peer-reviewed version appears. S4 is cited three times, as Dhar et al. (2024), in the related work on LLMs for architecture (Section 2.2, p. 3) and in the discussion (Section 5, p. 21). It also cites S8 (Díaz-Pace et al., 2024) and S10 (Jahic and Sami, 2024). | J100: S8, S10
A101: S4-F63 | B101: S4 | C101: Vo, Tran, Vo, Tran-Truong & Ha | D101: Exploring the Reasoning Depth of Small Language Models in Software Architecture: A Multidimensional Evaluation Framework Towards Software Engineering 2.0 | E101: 2026 | F101: arXiv preprint 2603.07091 (v1, 7 Mar 2026); no published version found | G101: Excluded | H101: Not peer reviewed | I101: arXiv preprint (v1, 7 March 2026) with no venue, acceptance note or copyright line; no published version was found in a web search on 29 September 2026 (only arXiv and aggregator pages). It is therefore excluded on its record. Benchmark study: ten open-weight small language models (under 7B parameters) generate architecture decision records from decision contexts, zero-shot, few-shot and after LoRA fine-tuning, on S4's dataset of 95 ADRs from five GitHub repositories, scored for technical compliance and semantic diversity (SLM-ArchBench). On its content it would be in scope (rule 1): the model's task object is architectural design decisions, as in S4 (1.3); revisit if a peer-reviewed version appears. S4 is cited as ref. [7] throughout (Sections I-III, pp. 1-4, and the conclusion, p. 9), as the prior ADR-generation study whose dataset and baseline it adopts. It cites no other seed. | J101: None
A102: S4-F64 | B102: S4 | C102: Vieira | D102: Engineering Trustworthy Software: A Mission for LLMs | E102: 2024 | F102: arXiv preprint 2411.17981 (v1, 27 Nov 2024) | G102: Duplicate of S4-F60 | H102: Duplicate | I102: Earlier arXiv version (27 November 2024) of the IEEE Computer article logged as S4-F60 (July 2025, DOI 10.1109/MC.2025.3546204): same single author and the same vision of LLMs across the software life cycle for trustworthy software, with the same architecture passages (recommending patterns such as microservices with isolated data processing, weighing trade-offs, analysing architectural choices during continuous assessment); its note says that an improved and extended version was submitted to the IEEE, which is S4-F60. It is not screened again: S4-F60 is the peer-reviewed version and is excluded under rule 3, and this preprint would fail on both scope (rule 3) and peer review. S4 is cited once, as ref. 4, for LLMs helping to define secure and scalable designs during architecture design (p. 1). | J102: As S4-F60
A103: S4-F65 | B103: S4 | C103: Albuquerque, Renan, Rodríguez, Díaz-Pace, Dantas, França, Perkusich, Gorgônio & Perkusich | D103: From Textual Requirements to Microservice Architectures: A Comprehensive Evaluation of LLM-Based Design Synthesis | E103: 2026 | F103: arXiv preprint 2607.28307 (v1, 30 Jul 2026), ACM template with placeholder venue ('Conference'17'); also posted on SSRN; no published version found | G103: Excluded | H103: Not peer reviewed | I103: arXiv preprint (v1, 30 July 2026) in the ACM template with the placeholder venue 'Conference'17, July 2017, Washington, DC'; it is also posted on SSRN, with supplementary material on Zenodo, and no peer-reviewed version was found in a web search on 29 September 2026. It is therefore excluded on its record. It extends the authors' SBCARS 2025 study, FS30 (its ref. [31]), with a refined method, an added research question (RQ4, a descriptive synthesis of the experts' open feedback) and an expanded analysis: OpenAI o3 generates microservice architectures from the textual requirements of Bookstore and PetClinic under zero-shot and few-shot prompting, one execution per condition, compared with implemented reference architectures and rated blind by experts. On its content it would be in scope (rule 1, 1.1) and would join family SF4 with FS04 and FS30; revisit if a peer-reviewed version appears. S4 is cited as ref. [13], among work on LLM-supported architecture design (Sections 2-3, p. 3) and in the related work for LLM generation of architectural design decisions (Section 3, p. 4). It cites no other seed. | J103: None
A104: S4-F66 | B104: S4 | C104: Gupta, Dhar, Feitosa & Vaidhyanathan | D104: Context Matters: Evaluating Context Strategies for Automated ADR Generation Using LLMs | E104: 2026 | F104: EASE 2026 (ACM), Research Papers track; arXiv 2604.03826v2 read | G104: Included as FS32 | I104: Primary study: four LLMs (Gemini-2.5-Pro, Qwen3-235B, GLM-4.6, Gemma-3-4B) generate the next architecture decision record of a repository from its title and a selection of earlier records (none, all, first K, last K, K retrieved by similarity), on over 4,500 ADRs from 750 open-source repositories, scored by text similarity against the human records. In scope (rule 1): the model's task object is architectural design decisions and their documentation (1.3). Peer reviewed: EASE 2026, Research Papers track, as listed on the conference site (researchr profile of Vaidhyanathan, checked 29 September 2026); the version read is arXiv v2 (15 April 2026) with the EASE 2026 reference block and a placeholder DOI. S4 is cited four times, as ref. [8] and again as its arXiv version, ref. [9]: for GPT-4 generating plausible decisions and for ADR generation treated as an isolated task (Section 1, p. 1), and in the related work (Section 6, p. 10). It also cites S9 (ref. [25]), S8 (ref. [26]), S5 (ref. [27]), S7 (ref. [28]) and S10 (ref. [29]). | J104: S5, S7, S8, S9, S10
A105: S4-F67 | B105: S4 | C105: Eisenreich | D105: From Requirements to Architecture: Semi-Automatically Generating Software Architectures | E105: 2025 | F105: EMISA 2025, PhD Research Proposal category (GI LNI P-362, pp. 59-63; DOI 10.18420/EMISA2025_08); arXiv preprint 2504.12192 (v1, 16 Apr 2025) read | G105: Excluded | H105: Peer review not established | I105: Five-page PhD research proposal, read in its arXiv version (v1, 16 April 2025, GI Lecture Notes in Informatics layout, no venue stated). A web search on 29 September 2026 found no published version, but S7-F20 cites it (ref. [4]) as EMISA 2025, GI LNI P-362, pp. 59-63, DOI 10.18420/EMISA2025_08, and the EMISA 2025 programme lists it as a PhD Research Proposal. The call describes that category as proposals (up to five pages) for talks on ongoing PhD theses and does not describe how submissions are reviewed, so peer review is not established; excluded by our decision (29 September 2026). It proposes LLM-based tools, evaluated by design science, for an assisted architecture creation process (domain models and use cases from requirements, architecture candidates using patterns retrieved with RAG, and qualitative evaluation against requirements), with brief preliminary results, among them that an LLM automating ATAM found a considerable overlap with participants' trade-offs. On its content it would likely be in scope (rule 3 met by the specified architecture generation and evaluation tools) and would join family F6 with S7, the author's earlier vision paper; revisit if the review process for EMISA's PhD research proposals can be established. S4 is cited once, as [DVV24], for LLMs generating relevant decisions, not yet at human quality (Section 2, p. 2). It also cites S7 ([ESW24]) and S10 ([JS24]), and FS24 ([Gü25]). | J105: S7, S10
...

Sheet Included_Studies
A1: Sr | B1: ID | C1: Found via | D1: Authors | E1: Title | F1: Year | G1: Venue | H1: Contribution type | I1: LLM / Gen AI used | J1: Architectural task addressed | K1: Evaluation type | L1: Family | M1: Coverage and independence
A2: 1 | B2: FS01 | C2: S1-F01, S1-F11, S4-F09, S4-F73, S8-F01, S8-F36; cites S1, S4, S8 | D2: Narváez, Battaglia, Fernández & Rossi | E2: Designing Microservices Using AI: A Systematic Literature Review | F2: 2025 | G2: Software (MDPI), vol. 4, article 6; DOI 10.3390/software4010006 | H2: Secondary study: systematic literature review following PRISMA, 43 studies published 2018-2024 on AI techniques in microservices design. Five research questions: techniques used, challenges, benefits, emerging trends, and the artefacts used as input. | I2: None run. The reviewed studies use machine learning (53.5%; clustering such as k-Means and word embeddings), NLP (32.6%), BERT-based models, deep and reinforcement learning and LSTM networks. Language models and generative AI appear as an emerging trend, supported by a few cited works (refs. [27], [38]-[41]). | J2: Microservice design: service identification from requirements in greenfield projects, decomposition of existing monoliths, architectural decision-making and decision documentation. Runtime autoscaling, fault tolerance and monitoring are also covered, which the authors include for completeness. | K2: Systematic literature review: IEEE Xplore, ACM Digital Library and Google Scholar; 2018-2024; 97 full texts read (20 more not accessible), 43 included; screening by two authors; no formal quality assessment of the included studies. | L2: SF1 | M2: 28 meaning units (7 / 4 / 4 / 6 / 5 / 2 across T1-T6). Secondary study (systematic review). New family SF1 (UAI and LIFIA, Argentina). It reports on S1, S4 and S8, so its units about them are not independent evidence; its content on language models is thin and rests on single citations.
A3: 2 | B3: FS02 | C3: S1-F03, S3-F01, S4-F03, S5-F02, S7-F01, S8-F03, S9-F01, S10-F02, S11-F11; cites S1, S3, S4, S5, S7, S8, S9, S10, S11 | D3: Esposito, Li, Moreschini, Ahmad, Cerny, Vaidhyanathan, Lenarduzzi & Taibi | E3: Generative AI for software architecture. Applications, challenges, and future directions | F3: 2026 | G3: The Journal of Systems and Software, vol. 231, article 112607 (online 17 Sep 2025); DOI 10.1016/j.jss.2025.112607 | H3: Secondary study: multivocal literature review of 36 peer-reviewed and 10 grey sources (search February 2025) on generative AI in software architecture. Research questions on purposes, models and techniques (RQ1), life-cycle phases, architectural styles, quality tasks, validation methods and use cases (RQ2), and challenges (RQ3); themes extracted by open coding. | I3: None run. Reports model use across its sources: OpenAI GPT models 62% of the model uses counted in Table 12, Google models 9%, LLaMA 8%, with DeepSeek and Qwen appearing in 2024-2025; cloud-hosted models preferred over on-premises ones. | J3: As reported across its sources: architectural decision support (38%), reverse engineering and reconstruction (19%), architecture generation (19%), quality assessment (9%), comprehension, requirements, migration and traceability. Life-cycle transitions: requirements to architecture 40%, architecture to code 32%, code to architecture 13%, requirements to architecture to code 12%, architecture to architecture 3%. | K3: Multivocal literature review following Garousi et al.: four digital libraries and five search engines, 1053 unique records screened to 46; two authors per decision with a third for disagreements and Cohen’s kappa reported; snowballing; quality assessment (Dybå and Dingsøyr checklist for peer-reviewed sources, Garousi criteria for grey); replication package on Zenodo. | L3: SF2 | M3: 34 meaning units (8 / 4 / 6 / 8 / 4 / 4 across T1-T6). Secondary study (multivocal review). New family SF2 (Oulu with Tampere, Arizona and IIIT Hyderabad); Vaidhyanathan co-authored S4 and S9 (F3), but this is a review, so it is kept separate. It reports on nine seeds (S1, S3-S5, S7-S11). Reliability: three statements about S1 conflict with our coding of S1; the snowballing yield and sources searched are reported inconsistently; three grey sources are cited but not listed.
A4: 3 | B4: FS03 | C4: S1-F06, S4-F41, S5-F10, S7-F17, S8-F21; cites S1, S4, S5, S7, S8 | D4: Zhang, Liu, Sun, Xu, Sun, Li, Jin & Liu | E4: Semantic-Enhanced Automatic Refinement of Architecture Recovery Results Using LLMs | F4: 2026 | G4: ICSE ’26, pp. 1687-1699; DOI 10.1145/3744916.3773114 | H4: Technique with quantitative evaluation. SemRef refines the output of existing architecture recovery tools by combining dependency analysis with a language model’s semantic judgement, in four stages: resizing modules (split and merge), file-level regrouping, hierarchy construction and iterative top-down refinement with module summaries. | I4: GPT-4o-mini (gpt-4o-mini-2024-07-18) by default, temperature 0, seed 1. Compared with GPT-4o (2024-08-06), Gemini-2.0-flash-001, Llama 3.3 (70B) and DeepSeek-V3-0324. All off the shelf; no fine-tuning. | J4: Architecture recovery, module view: correcting the file-to-module grouping recovered from source code and turning it into a named module hierarchy with a summary per module. The direction is from code to architecture. | K4: Quantitative evaluation on 9 open-source projects with published ground-truth architectures (25.7K to 11.7M lines), 10 recovery-tool implementations giving 90 inputs, five similarity metrics plus reduction in distance to perfect, ANOVA across tools and projects, an ablation of the five stages, token-cost analysis, a comparison of five models, and a case study on Bash. | L4: SF3 | M4: 37 meaning units (9 / 7 / 8 / 5 / 5 / 3 across T1-T6). Primary study. New family SF3 (Nanyang Technological University with Imperial, HUST and Xi'an Jiaotong). The recommended input tool, SARIF, is the authors' own earlier work. FS17 (SemArc) belongs to the same family. Reliability: the abstract says 'trillions of lines of code' (largest project 11.7M); text figures in Section 4.2.1 differ from Table 3, and units use the table values.
A5: 4 | B5: FS04 | C5: S1-F08, S7-F25, S9-F17; cites S1, S7, S9 | D5: Alves Pereira, Sousa, Dantas Filho, Albuquerque, Perkusich, Gorgônio & Perkusich | E5: Towards a Characterization of Microservice Architectures Generated by Large Language Models | F5: 2026 | G5: JAWs 2026, Journal Ahead Workshop at ICSE 2026 (13-14 April 2026); version read: arXiv:2609.20308v1 | H5: Exploratory empirical study. Characterises, rather than judges, the microservice architectures language models produce when asked to decompose a modular monolith from its textual architecture documentation, adapting the M2MDF decomposition framework so that model inference replaces clustering. Framed as a baseline for a research agenda on architecture-to-architecture transformation. | I5: "GPT-based models from OpenAI" and "models from DeepSeek"; no model name, version, temperature or other setting is reported. Zero-shot and few-shot prompting. No fine-tuning. | J5: Architecture-to-architecture transformation: deriving a microservice architecture (service boundaries, responsibilities, communications) from the architecture documentation of an existing modular monolith, for early-stage modernisation. | K5: Two systems (MediaStore, TeaStore), two providers, two prompting strategies, one run per configuration. No ground truth; outputs in CSV are characterised by eight structural and textual metrics (service count, communications, density, isolated services, responsibility length, vocabulary, redundancy). | L5: SF4 | M5: 25 meaning units (6 / 4 / 5 / 3 / 4 / 3 across T1-T6). Primary study. New family SF4 (VIRTUS, Federal University of Campina Grande); extends the authors' SBCARS 2025 study. arXiv version of the JAWs 2026 paper read. Its inputs are the documentation prepared in Fuchs et al. (ICSA 2025, FS15), the predecessor of S20. Cites FS02.
A6: 5 | B6: FS05 | C6: S1-F10, S4-F71, S4-F108, S10-F52, S10-F69; cites S1, S4, S8, S10 | D6: Karan, Dhar, Soliman & Vaidhyanathan | E6: Can LLMs Extract Architectural Design Decisions from Source Code Commits? – A Preliminary Exploratory Study | F6: 2026 | G6: IDEA-ARCH 2026, Intelligent & Data-driven Engineering for Software Architecture workshop at ECSA 2026 (Bolzano), full paper, presented 7 Sep 2026; published in ECSA 2026, LNCS 16991, pp. 208-215 (Springer, 2027), DOI 10.1007/978-3-032-39143-8_19; arXiv:2609.03721v1 read and checked against the published chapter (S4-F108) | H6: Exploratory empirical study (eight-page workshop paper). Tests whether language models can recover architectural design decisions from source code commits alone, comparing zero-shot and few-shot prompting across four models. | I6: Gemini 3 Pro (parameters not disclosed), DeepSeek R1 (685B), Kimi K2 Thinking (1T, 32B active), Qwen3 (32B), chosen from the Arena leaderboard. Zero-shot prompting, and few-shot prompting with examples retrieved by embedding similarity. No fine-tuning. Temperature, runs, embedding model and number of examples not reported. | J6: Architectural knowledge recovery: extracting the architectural design decision behind a single commit from its message and git diff, for architectural knowledge management. | K6: 30 developer-written decisions from Apache Cassandra, Hadoop and Tajo (Maestro dataset, linked to commits by Jira ID); four models by two prompting strategies. Automated comparison with the documented decision (ROUGE-L, BLEU, METEOR, BERTScore) and single-author inspection of the 60 Gemini outputs on a rubric fixed in advance (abstraction level, verbosity, rationale). | L6: F3 | M6: 26 meaning units (6 / 4 / 6 / 2 / 5 / 3 across T1-T6). Primary study. Family F3 with S4 and S9 (shared authors Dhar and Vaidhyanathan; continues S4's work on design decisions), overlapping F4 through Soliman; not independent of S4. arXiv version of the IDEA-ARCH 2026 paper read. The published chapter (ECSA 2026, LNCS 16991, pp. 208-215, Springer, dated 2027) was reached through S4 (S4-F108), and its text matches the arXiv version apart from typesetting.
A7: 6 | B7: FS06 | C7: S1-F13, S4-F83, S5-F24, S10-F58; cites S1, S4, S5, S10 | D7: Copei, Hohlfeld, Kosiol & Ristoski | E7: LLMs Choose the Right Stack: From Patterns to Tools | F7: 2025 | G7: ISE 2025, International Workshop on Intelligent Software Engineering at ASE 2025 (Seoul, 16 Nov 2025); ASE 2025 Workshops proceedings (IEEE), pp. 276-283; DOI 10.1109/ASEW67777.2025.00057 | H7: Empirical evaluation in three experiments of off-the-shelf models on architectural pattern recommendation: direct prompting (naive and improved prompts), decision-tree-guided recommendation through the authors’ CAPI method, and mapping patterns to implementation tools. | I7: Six models through the GWDG Chat AI service: ChatGPT-4o (closed; "ChatGPT-o4" in the text), DeepSeek-R1, Meta-Llama-3.1-8B-Instruct, Mistral-Large-Instruct, Codestral-22B, Qwen2.5-VL-72B-Instruct; temperature 0.5, top-p 0.5. Naive and improved prompts, decision-tree-guided prompting, JSON-structured output. No fine-tuning. | J7: Design decision support: choosing an architectural style (monolithic, client-server, microservices) and recommending architectural patterns for a described system, then mapping the patterns to implementation tools chosen from a supplied list (CNCF Landscape). | K7: Four scenarios from the authors’ CAPI user study. Exp. 1: 480 prompts (6 models, 2 prompts, 4 scenarios, 10 runs) rated on three-point ordinal scales (reasonable, variance, patterns). Exp. 2: one CAPI traversal per model and scenario, compared with 10 human participants by number of patterns and a penalty-based distance to the authors’ must/could/must-not lists. Exp. 3: JSON compliance and reasonableness of the tools. | L7: SF5 | M7: 23 meaning units (4 / 4 / 6 / 2 / 5 / 2 across T1-T6). Primary study. New family SF5 (Kassel, Fraunhofer IEE, Marburg); builds on the authors' own CAPI method. Scenarios, reference lists and human comparison data come from the authors' earlier CAPI study, so the benchmark is not independent of the method.
A8: 7 | B8: FS07 | C8: S1-F14, S7-F45, S8-F48; cites S1, S7, S8 | D8: Mitas & Sachweh | E8: Lifelong Learning in Software Engineering: Towards an AI-driven Tutor for Cloud-Based Software Architectures | F8: 2025 | G8: E-TEMS 2025, IEEE European Technology and Engineering Management Summit (Bruges, 26-28 May 2025), pp. 92-97; DOI 10.1109/E-TEMS64751.2025.11239087 | H8: Method proposal with an exploratory test: a four-step prompting method that makes a language model act as a tutor for novice architects, tried out with simulated student questions on one dataset. | I8: ChatGPT-4o (cloud) and Llama 3.1 Tulu 3 70B (AllenAI community model, run locally). Role prompting in four steps, with a relevance check and a self-check against the role instructions. No model fine-tuning ("fine-tune the prompts" in the paper means revising the prompts). | J8: Generating several reference architectures with decision records from requirements, and evaluating students’ architectures (component diagrams, a domain model) and requirement summaries against them, as a tutor for novice architects. | K8: Exploratory test on the MobSTr dataset (requirements, assumptions, hazards and a component diagram of an automotive driver assistance system): the authors send example student questions to both models and report their behaviour qualitatively. No students, metrics, number of questions or runs reported. | L8: SF6 | M8: 20 meaning units (6 / 4 / 5 / 1 / 3 / 1 across T1-T6). Primary study, exploratory. New family SF6 (IDiAL, Dortmund University of Applied Sciences and Arts). Evidence is the authors' qualitative observation; the test case is an automotive embedded system despite the 'cloud-based' title. A domain model produced with S7's approach is one of its inputs.
A9: 8 | B9: FS08 | C9: S3-F03, S4-F51, S5-F08, S7-F12, S7-F15, S8-F26, S9-F15, S10-F36; cites S1, S3, S4, S5, S7, S8, S9, S10 | D9: Cervantes, Kazman & Cai | E9: Better Together: An LLM-assisted approach to designing software architectures using Attribute-Driven Design | F9: 2026 | G9: IEEE Transactions on Software Engineering (early access, 2026); DOI 10.1109/TSE.2026.3706446; author's version read | H9: Method with empirical evaluation: a model follows Attribute-Driven Design (ADD) with an architect persona, an iteration plan and a single architecture document refined across iterations; evaluated on two case studies and against zero-shot design. | I9: Claude Sonnet 3.7 (first experiment, May 2025); Claude Opus 4.5 Thinking, GPT-5.2 High and Gemini 3 Pro (second experiment, January 2026), run in the Cursor and Antigravity IDEs with privacy mode enabled; a style-stability check with Grok Code, Gemini 3 Pro, Opus 4.5 and ChatGPT 5.1-Codex. No fine-tuning; model settings such as temperature are not reported. | J9: Architecture design from prioritised drivers: iteration planning, selection and instantiation of design concepts (patterns, tactics, frameworks), and documentation of the resulting architecture (views, interfaces, design decisions). | K9: Hotel Pricing System (book case with a proven, deployed solution): the authors compared the LLM design across eleven aspects. Warehouse Management System (unpublished): three models designed it, and Claude Opus 4.5's design was rated by four professional architects on seven drivers (1-5 scale). Completeness compared with zero-shot designs and the Kiro agentic IDE; style stability over eight rounds with four models. | L9: SF7 | M9: 27 meaning units (7 / 4 / 4 / 5 / 4 / 3 across T1-T6). Primary study. New family SF7 (UAM Iztapalapa, University of Hawaii, Drexel University); no author in common with F1-F20 or SF1-SF6. The hotel case and its reference solution come from the first two authors' own book, and the authors compared the LLM design with it themselves; the warehouse design was rated by four professional architects who are not authors. Author's version (TSE early access) read. It cites S1 (ref. [4], with S1's title and DOI but S2's author list), although Google Scholar did not list it among S1's citing records, and the SSRN preprint of FS02 (ref. [9]). Related work by the same authors (IEEE Software 2026, ref. [11]; Designing '26, ref. [47]) belongs to SF7 if it is reached; the IEEE Software article was reached as S4-F52 and included as FS27 in SF7, and the Designing '26 paper as S4-F39, excluded as code generation. Cervantes (Humberto Cervantes Maceda) is also a co-author of S1-F17, an excluded SSRN preprint.
A10: 9 | B10: FS09 | C10: S3-F04, S3-F11, S4-F42, S4-F106, S5-F11, S5-F29, S8-F23, S8-F54, S9-F13, S9-F23; cites S3, S4, S5, S8, S9 | D10: Compagnucci, Lu & Trubiani | E10: Agentic Runtime Reconfiguration of Architectural Patterns in Federated Learning | F10: 2026 | G10: Journal of Systems and Software 240 (2026), art. 112966, special issue "AI for SA"; DOI 10.1016/j.jss.2026.112966; open access | H10: Approach with controlled experiment: a layer of LLM agents added to the FLRA reference architecture switches architectural patterns on and off at runtime; three coordination strategies compared with three baselines. | I10: Llama 3.2 (3B), DeepSeek-r1 (8B) and gpt-oss (20B), open models at temperature 1.0, zero-shot and few-shot; DeepSeek-r1 with few-shot prompting used for the coordination experiments. Retrieval over a system configuration file and a metrics report; no fine-tuning. | J10: Runtime architectural decision-making: after every training round of a federated-learning system, deciding which of three architectural patterns (Client Selector, Heterogeneous Data Handler, Message Compressor) to activate or deactivate, with a rationale, from the system configuration and the metric history. | K10: Emulated federation (Docker Compose; five clients with two hardware profiles, IID and non-IID data, one-shot and batched data inflow, stable and unstable network), image (CNN, FashionMNIST) and text (MLP, AG_NEWS) classification, 10 rounds, 10 repetitions; voting, role-based and debate coordination against Never, Random and rule-based Expert-Driven baselines; Mann-Whitney U and Vargha-Delaney A12. | L10: SF8 | M10: 30 meaning units (7 / 6 / 4 / 6 / 5 / 2 across T1-T6). Primary study, the first included study whose model works on a running system's architecture. New family SF8 (Gran Sasso Science Institute; CSIRO Data61); no author in common with F1-F20 or SF1-SF7. Not independent of its own inputs: the reference architecture (FLRA), the pattern catalogue, the agent coordination patterns and the prompt structure all come from work co-authored by Lu, and the Expert-Driven rules from the pattern catalogue and Compagnucci and Trubiani's earlier performance studies (ICSA 2025; JSS 2026). A predecessor on AI agents for selecting FL patterns (Compagnucci & Trubiani, QualITA 2025) belongs to SF8 if it is reached. Reliability: its account of S5 (seven LLMs; the Llama, DeepSeek and OpenAI families effective), which it uses to choose its models, does not match S5, which studied GPT-3.5 only.
A11: 10 | B11: FS10 | C11: S3-F05; cites S3, S4 | D11: Dhar, Vaidhyanathan & Varma | E11: AgenticAKM: Enroute to Agentic Architecture Knowledge Management | F11: 2026 | G11: AGENT 2026, International Workshop on Agentic Engineering (ICSE 2026), ACM; DOI 10.1145/3786167.3788416 as printed on the paper; arXiv version (2602.04445) read | H11: Approach (a multi-agent architecture for architecture knowledge management) with an initial instantiation for ADR generation, evaluated in a blind user study; short workshop paper. | I11: GPT-5 and Gemini 2.5 Pro (top of the LMArena leaderboard on 5 October 2025), each in the agentic workflow and in a single-prompt baseline; no fine-tuning; prompts and settings not given in the paper. | J11: Architecture knowledge recovery and documentation: summarising a code repository and generating Architecture Decision Records (title, context, decision, consequences) for its significant decisions. Diagram and specification generation and retrieval of existing knowledge are proposed, not implemented. | K11: Blind comparative user study: 13 participants (students and professionals, 0-6 years of industry experience) rated four anonymised ADR sets (single prompt and agentic, each with two models) for 29 repositories they knew (17 Python, 12 JavaScript; 1,000-350,000 lines), 1-5 on relevance, coherence, completeness, conciseness and overall quality, with written comments; averages reported. | L11: F3 | M11: 24 meaning units (6 / 5 / 3 / 5 / 3 / 2 across T1-T6). Primary study (short workshop paper). Family F3 with S4 and S9 (same three authors) and FS05 (Dhar and Vaidhyanathan); not independent of them. arXiv version of the AGENT 2026 paper read, with the ACM rights block of the workshop proceedings; the DOI printed on it did not yet resolve in Crossref. Most agents in its design are proposals: the evaluated instantiation uses a repository summariser, a summary validator, an ADR generator and an ADR validator under an orchestrator. It cites S3, S4 and FS02 (as Esposito et al., 2025), but not S9, its authors' own earlier paper on architecture knowledge management. The evidence is subjective ratings by 13 participants (0-6 years of experience) of repositories they had submitted themselves.
A12: 11 | B12: FS11 | C12: S3-F06, S4-F72, S5-F20; cites S3, S4, S5, S14 | D12: El Outmani, Hatahet, Osterholz, Rausch & Venkataramana Shenoy | E12: Knowledge-Guided Architecture Documentation Recovery with Evidence Grounding and Traceability: A Registered Report (Stage 1) | F12: 2026 | G12: ICSA 2026 Companion (IEEE), pp. 534-541; DOI 10.1109/ICSA-C68850.2026.00097; Stage-1 registered report | H12: Study protocol (Stage-1 registered report, no results): a preregistered staged experiment and an industrial expert study, with a specified multi-agent recovery pipeline. | I12: LLM agents (Architecture Reasoner, Component Assembler, Architectural Validator) and LLM-based semantic similarity, plus an LLM-as-a-judge proxy; no model is named. | J12: Architecture documentation recovery from repositories: a hierarchical component view (C4 level 3) with responsibilities, arc42-aligned sections and traceability links to evidence, under four levels of injected architectural knowledge. | K12: Planned: reproduction of SARIF and SemArc baselines on seven benchmark projects, pipeline comparability check, tests of project-specific facts and bounded architect interaction on four arc42-by-Example projects (paired tests, effect sizes), and an industrial expert assessment; results omitted by design. | L12: SF9 | M12: 20 meaning units (4 / 3 / 4 / 5 / 2 / 2 across T1-T6). Study protocol: a Stage-1 registered report, so its units describe a specified pipeline and a planned study, not results. New family SF9 (TU Clausthal); no author in common with F1-F20 or SF1-SF8. Published in the ICSA 2026 Companion proceedings; the track is not named on the paper or found in the conference programme. It builds on SemArc (FS17) and SARIF as baselines and on the authors' own recovery work (MODELS-C 2025; a ROS 2 workshop study, arXiv 2602.18644), which belongs to SF9 if it is reached. It cites S3, S4, S5, FS02's SSRN preprint and ArchAgent (S14) through its arXiv version, with an author list that differs from S14's.
A13: 12 | B13: FS12 | C13: S3-F07, S4-F95, S11-F150, S11-F223; cites S3, S4, S11 | D13: Zimmermann & Seiger | E13: AI Assistance for Architectural Decision Making: Domain-Driven Context and Prompt Engineering | F13: 2026 | G13: IDEA-ARCH 2026, Intelligent and Data-driven Engineering for Software Architecture (ECSA 2026 workshop), short paper; published in ECSA 2026, LNCS 16991, pp. 143-151 (Springer, 2027), DOI 10.1007/978-3-032-39143-8_14; author version read and checked against the published chapter (S4-F95) | H13: Vision paper: use cases and architecturally significant requirements for AI decision assistance, a Domain-Driven Design context map and component architecture, and an example ADR-review prompt. | I13: An ADR-review prompt was run with six LLMs whose responses are published (Zenodo record: Claude Sonnet, Gemini Flash, ChatGPT, DeepSeek, Llama, Qwen); the paper names no model versions or settings. | J13: Architectural decision making: identifying and elaborating decision drivers, exploring options, and creating, reviewing and recovering ADRs; the worked example reviews an existing ADR against five criteria. | K13: Design-science vision: requirements from practicing architects (number not stated) and action research; one example ADR (Apache James) reviewed by six LLMs, with early results described as mostly positive; systematic evaluation in progress. | L13: SF10 | M13: 20 meaning units (5 / 4 / 3 / 5 / 2 / 1 across T1-T6). Short vision paper. New family SF10 (University of St.Gallen, RWTH Aachen); no author in common with F1-F20 or SF1-SF9. Author version of the IDEA-ARCH 2026 paper read; acceptance confirmed on the ECSA 2026 programme and in the companion dataset on Zenodo. The evidence is practitioner input of unstated size and one example ADR reviewed by six LLMs, whose responses are published; the systematic evaluation is still in progress. It builds on Zimmermann's earlier work on architectural decision models and cites S3, S4, S11 and the arXiv preprint of FS08. The published chapter (ECSA 2026, LNCS 16991, pp. 143-151, Springer, dated 2027) was reached through S4 (S4-F95) and matches the author version in text; its reference list omits the Zenodo dataset still cited in the text as ref. [19].
... A70: 69 | B70: FS69 | C70: S20-F06; cites S20 | D70: Milev & Kanagala | E70: Sentinel: Autonomous Architectural Governance Through Commit Intelligence Across Multi-Repository Systems | F70: 2026 | G70: CAIS '26, ACM Conference on AI and Agentic Systems (San Jose, 26-29 May 2026), four-page paper with a demonstration scenario, pp. 1332-1335; DOI 10.1145/3786335.3813195 | H70: Primary study: system (Sentinel) with a production deployment evaluation and a demonstration scenario; four-page paper | I70: Not named: two agents built on the AWS Strands agent framework with AWS AgentCore two-tier memory and MCP tool servers for GitHub, Confluence and Jira; a Claude Code skill provides the conversational query interface; no settings or fine-tuning reported | J70: Architecture conformance checking and drift detection: grouping commits across repositories into development initiatives, matching them to technical design documents and epics, and judging whether they conform to the TDDs and to ADR-prescribed patterns (for example event-bus communication or extracting a service), with violations flagged on pull requests before merge | K70: Production deployment over eight weeks (120+ microservices, 20 teams, 2,400+ commits): counts of initiatives and drift flags, the true-positive rate of 18 flags judged by automated trace-rule checks and architects, and average time to flag; no recall; demonstration on six LangChain repositories with 100 pull requests and synthetic TDDs and ADRs | L70: SF43 | M70: 17 meaning units (4 / 3 / 4 / 4 / 2 / 0 across T1-T6). Primary study, industrial (Navan). New family SF43: no author is shared with a seed or an included study. It cites S20, S4-F10 (excluded study), FS16 and FS44 as related work and positions itself against FS16's evaluation of ADR-violation detection, so its evidence is independent of theirs. Evidence strength is weak: a four-page paper whose evaluation is 18 drift flags in eight weeks of one company's production use, 83% judged true by automated trace rules and architects (consistent with 15 of 18), with no recall, no baseline and the model behind the agents not named; the demonstration uses synthetic TDDs and ADRs on open-source repositories. Reliability checks: we checked the 83% against 18 flags (15 of 18 is 83.3%), and noted that the average of 12 minutes from commit to drift flag is not reconciled with a synthesis agent said to run two to three times a week. Its reference list gives author lists for S20, S4-F10 (excluded study) and FS16 that differ from the published papers, although the titles and arXiv numbers are right.

Sheet Thematic_Map
A1: Study | B1: Year | C1: Meaning unit | D1: Code | E1: Sub-theme | F1: Theme | G1: Trend signal | H1: Source | I1: Row type | J1: Approach/Type
A2: FS01 | B2: 2025 | C2: For greenfield projects the review reports tools that derive microservice boundaries from requirements artefacts: SEMGROMI groups user stories by NLP semantic similarity, GTMicro clusters use cases with a BERT-based model, and GreenMicro clusters use cases with their database entities, which the review notes is not itself an AI technique. | D2: Service identification from user stories and use cases in greenfield design | E2: 1.1 Architecture generation and synthesis from requirements | F2: T1. LLMs Application / Usage for Architecture Design | H2: Sections 1, 2 and 5.2 (Q1, Q5), pp. 2, 4-5, 11, 13 | I2: Evidenced | J2: T1: design production (1.1-1.3)
A3: FS02 | B3: 2026 | C3: Architecture generation is the purpose of 19% (9) of the sources, and requirements to architecture is the most targeted life-cycle transition (40%, 24), with models mapping textual specifications into architectural representations, for example microservice names from functional requirements, UML component diagrams from informal specifications and SysML system architectures in model-based systems engineering. | D3: Requirements-to-architecture is the most targeted transition | E3: 1.1 Architecture generation and synthesis from requirements | F3: T1. LLMs Application / Usage for Architecture Design | H3: Sections 4.2.1, 4.3.1 and 4.3.4; Tables 11 and 14, pp. 7, 9, 11, 13 | I3: Evidenced | J3: T1: design production (1.1-1.3)
A4: FS03 | B4: 2026 | C4: The model helps produce an architecture, a named module hierarchy, but from source code and the output of recovery tools, not from requirements; it reconstructs what is implemented rather than synthesising a design. | D4: Architecture produced from code, not from requirements | E4: 1.1 Architecture generation and synthesis from requirements | F4: T1. LLMs Application / Usage for Architecture Design | H4: Abstract; Sections 1 and 3, pp. 1687-1690 | I4: Related activity | J4: T1: design production (1.1-1.3)
A5: FS04 | B5: 2026 | C5: Models generate a microservice architecture (services, their responsibilities and the communications between them, as CSV) from natural-language documentation of a modular monolith, aimed at early modernisation when source code and runtime traces are unavailable. | D5: Microservice architecture generated from textual documentation | E5: 1.1 Architecture generation and synthesis from requirements | F5: T1. LLMs Application / Usage for Architecture Design | H5: Abstract; Sections 1 and 3, pp. 1-4 | I5: Evidenced | J5: T1: design production (1.1-1.3)
A6: FS07 | B6: 2025 | C6: Taking the role of an expert architect, the model generates several software architectures that meet the supplied requirements, to serve as references against which students' proposals are compared; teachers can inspect and refine them. | D6: Reference architectures generated from requirements | E6: 1.1 Architecture generation and synthesis from requirements | F6: T1. LLMs Application / Usage for Architecture Design | H6: Section III-C, p. 94; Section IV, pp. 95-96 | I6: Evidenced | J6: T1: design production (1.1-1.3)
A7: FS08 | B7: 2026 | C7: Following Attribute-Driven Design, the model turns prioritised architectural drivers (primary functional requirements, quality attribute scenarios, concerns, constraints) into an iteration plan and a complete architecture: domain model, container, component and sequence diagrams, interfaces and design decisions. | D7: Complete architecture designed from prioritised drivers | E7: 1.1 Architecture generation and synthesis from requirements | F7: T1. LLMs Application / Usage for Architecture Design | H7: Abstract; Sections III-IV, pp. 1, 3-7 | I7: Evidenced | J7: T1: design production (1.1-1.3)
A8: FS08 | B8: 2026 | C8: On a published case (hotel pricing) the generated design resembled the book's proven, deployed solution (CQRS, microservices behind an API gateway, event-driven communication) while being more detailed; on an unpublished warehouse management system, four professional architects gave average ratings of 4 or above (1-5 scale) for four of seven drivers and at least 3.25 for the rest. | D8: Designs comparable to a proven solution and rated as satisfying drivers | E8: 1.1 Architecture generation and synthesis from requirements | F8: T1. LLMs Application / Usage for Architecture Design | H8: Section VI-A; Tables IV-V, pp. 10-12 | I8: Evidenced | J8: T1: design production (1.1-1.3)
A9: FS09 | B9: 2026 | C9: The model does not produce an architecture: the reference architecture (FLRA) and its three patterns are fixed in advance, and the model only chooses which combination of them is active in the next round. | D9: Configuration chosen, no architecture produced | E9: 1.1 Architecture generation and synthesis from requirements | F9: T1. LLMs Application / Usage for Architecture Design | H9: Sections 4.2-4.4, pp. 5-7 | I9: Related activity | J9: T1: design production (1.1-1.3)
A10: FS11 | B10: 2026 | C10: The pipeline recovers an architecture from a repository rather than designing one from requirements; the authors set forward-design agent systems (MASC4, ReArch) apart from recovery. | D10: Architecture recovered from code, not designed | E10: 1.1 Architecture generation and synthesis from requirements | F10: T1. LLMs Application / Usage for Architecture Design | H10: Section II-D, p. 536 | I10: Related activity | J10: T1: design production (1.1-1.3)
A11: FS14 | B11: 2025 | C11: Four LLM-based agents are specified to design a system's architecture from its software requirements specification: an Analyst extracts, filters and classifies the architecturally significant requirements, a Modeler makes the high-level decisions and produces conceptual logical and physical views, a Designer refines them into class, sequence and deployment diagrams, and an Evaluator checks the artefacts against the specification; the design ends when the Evaluator confirms them. | D11: Agents specified to design an architecture from requirements | E11: 1.1 Architecture generation and synthesis from requirements | F11: T1. LLMs Application / Usage for Architecture Design | H11: Abstract; Sections 1 and 2.1, pp. 530-531; Figs. 1-2 | I11: Evidenced | J11: T1: design production (1.1-1.3)
A12: FS22 | B12: 2026 | C12: Three of the five benchmark tasks generate implementations from specifications, requirements or runtime context (serverless functions, IoT services, microservices with controllers, services, data models and configuration), next to architecture rather than architecture itself, although the selection follows a taxonomy that includes requirements-to-architecture transformation. | D12: Code-generation tasks beside the architectural ones | E12: 1.1 Architecture generation and synthesis from requirements | F12: T1. LLMs Application / Usage for Architecture Design | H12: Section II; Table I, pp. 2-3 | I12: Related activity | J12: T1: design production (1.1-1.3)
A13: FS24 | B13: 2024 | C13: From a textual project description and requirements, the mentor leads a student through seven steps distilled from 18 software engineers: project idea, user needs and requirements, a basic conceptual architecture, essential components, their relationships, additional components and a textual summary of the architecture. | D13: Guided design from description and requirements in seven steps | E13: 1.1 Architecture generation and synthesis from requirements | F13: T1. LLMs Application / Usage for Architecture Design | H13: Sections 3.3 and 4, pp. 4-5 | I13: Evidenced | J13: T1: design production (1.1-1.3)
... A816: FS69 | B816: 2026 | C816: Absence: the model, its settings, token use and the cost of running the agents are not reported. | D816: Absence: model, settings and cost | E816: 3.3 Cost, latency and reproducibility of the reported setups | F816: T3. Techniques for Evaluation | H816: Sections 2.2 and 5, pp. 1333-1335, are where they would appear | I816: Coded silence | J816: T3: evaluation technique
A817: FS01 | B817: 2025 | C817: Absence: no agent-based or multi-agent language-model approach appears. Language models are described only as assisting architects from textual input, and none of the trends the review names involves agents. | D817: Absence: no agentic or multi-agent approaches | E817: 4.1 From single-prompt assistance towards agentic and multi-agent architecting | F817: T4. Emerging Trends | G817: No signal | H817: whole paper | I817: Coded silence | J817: T4: emerging trend
A818: FS02 | B818: 2026 | C818: Multi-agent frameworks, together with more advanced retrieval, are presented as inevitable for supporting complex architectural styles such as microservices within token limits; one source already builds LLM-based architecture agents that improve decision-making starting from code. | D818: Multi-agent frameworks seen as necessary for complex architectures | E818: 4.1 From single-prompt assistance towards agentic and multi-agent architecting | F818: T4. Emerging Trends | G818: Explicit | H818: Sections 4.3.1, 5.1 and 5.3, pp. 12, 16-17 | I818: Evidenced | J818: T4: emerging trend
A819: FS03 | B819: 2026 | C819: The pipeline is a fixed sequence of prompts with iterative loops, not an agent; the authors note that related work has shifted toward agent-based automation of architecture tasks, including multi-agent design frameworks. | D819: Fixed prompt pipeline while the field moves to agents | E819: 4.1 From single-prompt assistance towards agentic and multi-agent architecting | F819: T4. Emerging Trends | G819: Explicit | H819: Section 2, p. 1689 | I819: Related activity | J819: T4: emerging trend
A820: FS08 | B820: 2026 | C820: Migrating the approach to an agentic architecture, packaged as a reusable skill, is already under development; the authors contrast their human-in-the-loop process with the multi-agent MAAD, in which humans only validate the result. | D820: Towards an agentic, reusable design skill | E820: 4.1 From single-prompt assistance towards agentic and multi-agent architecting | F820: T4. Emerging Trends | G820: Explicit | H820: Sections II-F and VIII, pp. 3, 14 | I820: Evidenced | J820: T4: emerging trend
A821: FS09 | B821: 2026 | C821: The authors see LLM-based agents moving beyond decision support into software systems, where they monitor runtime behaviour, learn from past outcomes and intervene in real time, and they use them not merely as advisory tools but as decision-making components. | D821: From decision support to agents inside running systems | E821: 4.1 From single-prompt assistance towards agentic and multi-agent architecting | F821: T4. Emerging Trends | G821: Explicit | H821: Sections 1 and 3.4, pp. 2, 4 | I821: Evidenced | J821: T4: emerging trend
A822: FS10 | B822: 2026 | C822: Agentic approaches are presented as a paradigm gaining traction for complex tasks, in software engineering and in architecture (ReArch, MAAD), and the authors move architecture knowledge management from a single prompt to cooperating agents. | D822: From a single prompt to cooperating agents | E822: 4.1 From single-prompt assistance towards agentic and multi-agent architecting | F822: T4. Emerging Trends | G822: Explicit | H822: Sections 1 and 5, pp. 1, 4 | I822: Evidenced | J822: T4: emerging trend
A823: FS11 | B823: 2026 | C823: Agentic systems are presented as extending LLM-based recovery with multi-step workflows, specialised roles and tools (MAAD, ArchAgent, MASC4, ReArch), although it remains difficult to attribute their gains to specific injected architectural knowledge. | D823: Agentic recovery, gains hard to attribute | E823: 4.1 From single-prompt assistance towards agentic and multi-agent architecting | F823: T4. Emerging Trends | G823: Explicit | H823: Sections I and II-D, pp. 534, 536 | I823: Evidenced | J823: T4: emerging trend
A824: FS12 | B824: 2026 | C824: Generative and agentic AI are to be integrated into preparing, making and recording decisions: skills for agentic tools sit beside chat prompts, practitioners already share ADR-writing skills and agents, and the authors expect the AI space to keep changing fast. | D824: Skills for agentic tools beside chat prompts | E824: 4.1 From single-prompt assistance towards agentic and multi-agent architecting | F824: T4. Emerging Trends | G824: Explicit | H824: Sections 1, 3 and 5, pp. 2, 6-7 | I824: Evidenced | J824: T4: emerging trend
A825: FS13 | B825: 2026 | C825: The authors move from prompting to a multi-agent system because rationale is complex and no agent system for it existed, and they divide the work as an architect would (identify aspects, gather information, analyse, review, weigh trade-offs); they plan to extend the agents with context extraction from the project, tracing of external knowledge, code examples and visual output. | D825: From prompts to a multi-agent pipeline | E825: 4.1 From single-prompt assistance towards agentic and multi-agent architecting | F825: T4. Emerging Trends | G825: Explicit | H825: Sections 2.3, 3.4.3 and 8, pp. 4-5, 12, 35 | I825: Evidenced | J825: T4: emerging trend
A826: FS14 | B826: 2025 | C826: Multi-agent systems are presented as the answer to hallucination under zero-shot prompting and as unexplored for architecture design; the authors envision agents that simulate the roles of the design process, and dynamic agent configurations whose roles evolve with task complexity as future research. | D826: Agents simulating the architecture design roles | E826: 4.1 From single-prompt assistance towards agentic and multi-agent architecting | F826: T4. Emerging Trends | G826: Explicit | H826: Sections 1 and 4, pp. 530, 533 | I826: Evidenced | J826: T4: emerging trend
A827: FS15 | B827: 2025 | C827: The pipeline is a fixed sequence of prompts (elaborate, list, merge) with rule-based parsing, not an agent; the only forward look is to models with built-in chain-of-thought reasoning such as OpenAI o1, and agents are not mentioned. | D827: Fixed prompt pipeline; reasoning models as next step | E827: 4.1 From single-prompt assistance towards agentic and multi-agent architecting | F827: T4. Emerging Trends | G827: No signal | H827: Sections III-B and VI, pp. 3-4, 10 | I827: Related activity | J827: T4: emerging trend
A828: FS16 | B828: 2026 | C828: Four models work in fixed roles, a reasoning model detecting violations and three models validating its reasoning as 'experts', and the authors propose cross-model ensembles to combine the models' complementary strengths; no agents are used. | D828: Multi-model pipeline and ensembles | E828: 4.1 From single-prompt assistance towards agentic and multi-agent architecting | F828: T4. Emerging Trends | G828: Explicit | H828: Sections I, III-D and V, pp. 1, 3, 10 | I828: Evidenced | J828: T4: emerging trend
... A1042: FS69 | B1042: 2026 | C1042: A drift flag was counted as a true positive when an automated trace-rule check and a review by architects agreed, and the demonstration uses an open-source project with synthetic design documents to avoid exposing proprietary data. | D1042: Two-signal evaluation of flags; synthetic documents for the demo | E1042: 4.5 Trust, governance and responsible adoption in industrial settings | F1042: T4. Emerging Trends | G1042: Explicit | H1042: Sections 4 and 5, pp. 1334-1335 | I1042: Evidenced | J1042: T4: emerging trend
A1043: FS01 | B1043: 2025 | C1043: The precision of AI-driven decomposition depends on the clarity and quality of the input: ambiguous or overlapping user stories and use cases lead to imprecise service boundaries, and clustering needs a careful choice of the number of clusters. | D1043: Output quality bounded by ambiguous input artefacts | E1043: 5.1 Reported limitations in practice | F1043: T5. Limitations | H1043: Sections 1, 2, 5.2 (Q2) and 7, pp. 2, 4-5, 11, 16 | I1043: Evidenced | J1043: T5: limitation
A1044: FS01 | B1044: 2025 | C1044: Data consistency and distributed transactions are the main unresolved challenge: decomposition tools such as PF4MD leave consistency across services to the architect, and data consistency or distributed transactions are mentioned in 95.3% of the reviewed studies. | D1044: Data consistency and distributed transactions left to the architect | E1044: 5.1 Reported limitations in practice | F1044: T5. Limitations | H1044: Sections 5 and 5.2 (Q2), pp. 9, 11 | I1044: Evidenced | J1044: T5: limitation
A1045: FS01 | B1045: 2025 | C1045: Current tools concentrate on functional decomposition; non-functional requirements such as security, fault tolerance and compliance are handled poorly. | D1045: Non-functional requirements neglected by decomposition tools | E1045: 5.1 Reported limitations in practice | F1045: T5. Limitations | H1045: Section 5.3, p. 14 | I1045: Evidenced | J1045: T5: limitation
A1046: FS02 | B1046: 2026 | C1046: Architectural degradation is a risk when AI recommendations are overused or trusted blindly, and practitioners may accept suggestions as if from an oracle; results on complex tasks were less usable and need checking. | D1046: Blind trust risks architectural degradation | E1046: 5.1 Reported limitations in practice | F1046: T5. Limitations | H1046: Sections 4.4 and 5.1, pp. 15, 17 | I1046: Evidenced | J1046: T5: limitation
A1047: FS02 | B1047: 2026 | C1047: Generative AI may overlook team dynamics and organisational culture, proposing solutions that work technically but ignore the team’s skills or the organisation’s objectives, and over-reliance may reduce human creativity. | D1047: Socio-technical context ignored by generated designs | E1047: 5.1 Reported limitations in practice | F1047: T5. Limitations | H1047: Sections 4.4 and 5.1; Table 21, pp. 16-17 | I1047: Evidenced | J1047: T5: limitation
A1048: FS02 | B1048: 2026 | C1048: Models struggle with long-context reasoning and with fragmented or inconsistent input, which limits their context-awareness, and outputs are hard to adjust afterwards. | D1048: Limited context-awareness and long-context reasoning | E1048: 5.1 Reported limitations in practice | F1048: T5. Limitations | H1048: Section 4.4, p. 15 | I1048: Evidenced | J1048: T5: limitation
A1049: FS03 | B1049: 2026 | C1049: The refinement depends on its input: gains are similar across input tools, so the result is bounded by the best recovery tool available, which the authors recommend choosing. | D1049: Result bounded by the input recovery tool | E1049: 5.1 Reported limitations in practice | F1049: T5. Limitations | H1049: Section 5.1, p. 1697 | I1049: Evidenced | J1049: T5: limitation
A1050: FS03 | B1050: 2026 | C1050: Some recovered modules still differ from the ground truth; in Bash the general module is split into several parts, which the authors argue is a reasonable alternative division. | D1050: Residual divergence from the ground truth | E1050: 5.1 Reported limitations in practice | F1050: T5. Limitations | H1050: Section 4.2.2, p. 1695 | I1050: Evidenced | J1050: T5: limitation
A1051: FS03 | B1051: 2026 | C1051: Only nine projects with human-labelled ground truth could be collected, which the authors list as a threat while arguing that their spread of size, language and domain makes them representative. | D1051: Small evaluation set, limited by available ground truth | E1051: 5.1 Reported limitations in practice | F1051: T5. Limitations | H1051: Section 5.2, p. 1697 | I1051: Evidenced | J1051: T5: limitation
A1052: FS04 | B1052: 2026 | C1052: The metrics give only a partial view: granularity and density are context-dependent, so a higher service count may mean better separation of concerns or over-decomposition, and lower density may mean looser coupling or under-specified interactions. | D1052: Metrics are ambiguous without context | E1052: 5.1 Reported limitations in practice | F1052: T5. Limitations | H1052: Section 4.6; Section 5, pp. 6-7 | I1052: Evidenced | J1052: T5: limitation
A1053: FS04 | B1053: 2026 | C1053: Few-shot outputs include isolated services with no declared interactions, especially from DeepSeek, which may be utility components or over-decomposition. | D1053: Isolated services suggest over-decomposition | E1053: 5.1 Reported limitations in practice | F1053: T5. Limitations | H1053: Sections 4.2 and 4.4, pp. 5-6 | I1053: Evidenced | J1053: T5: limitation
A1054: FS04 | B1054: 2026 | C1054: Only two modular monoliths and two providers were studied, and text-only input may not transfer to settings where code or runtime data is available. | D1054: Two systems, two providers, text-only input | E1054: 5.1 Reported limitations in practice | F1054: T5. Limitations | H1054: Section 6, p. 7 | I1054: Evidenced | J1054: T5: limitation
... A1209: FS69 | B1209: 2026 | C1209: Absence: whether the agents judge the same initiative consistently across runs, and why the false flags arose, are not examined. | D1209: Absence: consistency and false flags not analysed | E1209: 5.2 Reported reliability problems: hallucination, inconsistency, non-determinism | F1209: T5. Limitations | H1209: Section 5, p. 1335, is where they would appear | I1209: Coded silence | J1209: T5: limitation
A1210: FS01 | B1210: 2025 | C1210: Further empirical validation is called for: the practical impact of AI-driven decomposition lacks empirical study, and the use of language models in real-world design remains limited and unvalidated. | D1210: Empirical validation of AI design tools called for | E1210: 6.1 Open challenges and stated future work | F1210: T6. Challenges | G1210: Explicit | H1210: Sections 3, 5.3 and 7, pp. 6, 14-16 | I1210: Evidenced | J1210: T6: challenge
A1211: FS01 | B1211: 2025 | C1211: Future work is to build non-functional requirements such as resilience, fault tolerance, security and compliance into AI-based design tools, and to address distributed data management. | D1211: Non-functional requirements and data management as future work | E1211: 6.1 Open challenges and stated future work | F1211: T6. Challenges | G1211: Explicit | H1211: Sections 5.3 and 7, pp. 14-16 | I1211: Evidenced | J1211: T6: challenge
A1212: FS02 | B1212: 2026 | C1212: The authors call for general evaluation methodologies, architecture-specific datasets and benchmarks, and clearer semantic traceability between architectural artefacts so that model effectiveness can be tested and compared. | D1212: Evaluation methods, datasets and benchmarks needed | E1212: 6.1 Open challenges and stated future work | F1212: T6. Challenges | G1212: Explicit | H1212: Abstract; Sections 4.4 and 5.3, pp. 1, 15, 17 | I1212: Evidenced | J1212: T6: challenge
A1213: FS02 | B1213: 2026 | C1213: A single generative-AI framework that engages all life-cycle phases is named as the advance still missing; current tools are pieces of the puzzle, not related to the phases before them. | D1213: Integration across the architecture life cycle missing | E1213: 6.1 Open challenges and stated future work | F1213: T6. Challenges | G1213: Explicit | H1213: Section 5.1, p. 16 | I1213: Evidenced | J1213: T6: challenge
A1214: FS02 | B1214: 2026 | C1214: Formal verification and AI-driven compliance checking of generated output are proposed as a research direction, and the authors ask who will manage generated content as systems evolve, recalling the same problem in model-driven development. | D1214: Formal verification and ownership of generated artefacts | E1214: 6.1 Open challenges and stated future work | F1214: T6. Challenges | G1214: Explicit | H1214: Sections 4.4 and 5.1, pp. 16-17 | I1214: Evidenced | J1214: T6: challenge
A1215: FS02 | B1215: 2026 | C1215: Experimental comparisons of productivity and quality between human-written and AI-generated code in realistic settings are called for, together with architectural metrics to prevent degradation. | D1215: Controlled human-versus-AI comparisons needed | E1215: 6.1 Open challenges and stated future work | F1215: T6. Challenges | G1215: Explicit | H1215: Section 5.1, p. 16 | I1215: Evidenced | J1215: T6: challenge
A1216: FS03 | B1216: 2026 | C1216: Further prompt optimisation, for example few-shot prompting, is named as future work. | D1216: Prompt optimisation as future work | E1216: 6.1 Open challenges and stated future work | F1216: T6. Challenges | G1216: Explicit | H1216: Section 5.2, p. 1697 | I1216: Evidenced | J1216: T6: challenge
A1217: FS03 | B1217: 2026 | C1217: The authors expect results to improve as stronger models become available, since performance tracked general model capability. | D1217: Gains expected from stronger models | E1217: 6.1 Open challenges and stated future work | F1217: T6. Challenges | G1217: Explicit | H1217: Sections 5.1 and 6, p. 1697 | I1217: Evidenced | J1217: T6: challenge
A1218: FS03 | B1218: 2026 | C1218: The use of language models for architecture recovery is described as still rarely explored. | D1218: LLM-based architecture recovery under-explored | E1218: 6.1 Open challenges and stated future work | F1218: T6. Challenges | G1218: Explicit | H1218: Section 2, p. 1689 | I1218: Evidenced | J1218: T6: challenge
A1219: FS04 | B1219: 2026 | C1219: Future work is to test the stability of generated architectures under repeated runs, different temperatures and alternative prompt formulations. | D1219: Stability under repetition as future work | E1219: 6.1 Open challenges and stated future work | F1219: T6. Challenges | G1219: Explicit | H1219: Section 5 (research agenda), p. 7 | I1219: Evidenced | J1219: T6: challenge
A1220: FS04 | B1220: 2026 | C1220: Hybrid workflows that combine text-driven generation with static dependencies, runtime information or architectural constraints are named as an open challenge. | D1220: Hybrid evidence sources as an open challenge | E1220: 6.1 Open challenges and stated future work | F1220: T6. Challenges | G1220: Explicit | H1220: Section 5 (research agenda), p. 7 | I1220: Evidenced | J1220: T6: challenge
A1221: FS04 | B1221: 2026 | C1221: Models could support exploration by generating several alternatives, highlighting trade-offs and supporting what-if analysis, rather than producing one target architecture. | D1221: Generating alternatives for what-if analysis | E1221: 6.1 Open challenges and stated future work | F1221: T6. Challenges | G1221: Explicit | H1221: Section 5 (research agenda), p. 7 | I1221: Evidenced | J1221: T6: challenge
... A1293: FS68 | B1293: 2026 | C1293: Future work: improve traceability coverage with link inference from commits, test more varied cross-project settings, analyse what distinguishes smell-inducing issues, combine models in ensembles, separate intentional trade-offs, try prompt engineering with retrieval or chain-of-thought, and extend the pipeline to GitHub and other smell types. | D1293: Better links, ensembles, prompt engineering, more platforms | E1293: 6.1 Open challenges and stated future work | F1293: T6. Challenges | G1293: Explicit | H1293: Sections VII-A and VII-C, pp. 52-53 | I1293: Evidenced | J1293: T6: challenge

Sheet Themes_Overview
A1: Theme (and RQ answered) | B1: Sub-themes | C1: Meaning units | D1: Evidenced | E1: Coded silences | F1: Related activity | G1: Studies (evidentiary) | H1: Independent families | I1: Study | J1: Units in T1 | K1: Units in T2 | L1: Units in T3 | M1: Units in T4 | N1: Units in T5 | O1: Units in T6 | P1: Total
A2: T1. LLMs Application / Usage for Architecture Design (RQ1) | B2: • 1.1 Architecture generation and synthesis from requirements • 1.2 Design decision support: pattern, tactic and technology recommendation • 1.3 Architecture documentation, decision records and rationale capture • 1.4 Architecture analysis, recovery, conformance and smell detection • 1.5 The role assigned to the model: assistant, co-designer or autonomous agent • 1.6 Reported benefits in practice | C2: =COUNTIF(Thematic_Map!$F$2:$F$1319,"T1. LLMs Application / Usage for Architecture Design") -> 326 | D2: =COUNTIFS(Thematic_Map!$F$2:$F$1319,"T1. LLMs Application / Usage for Architecture Design",Thematic_Map!$I$2:$I$1319,"Evidenced") -> 297 | E2: =COUNTIFS(Thematic_Map!$F$2:$F$1319,"T1. LLMs Application / Usage for Architecture Design",Thematic_Map!$I$2:$I$1319,"Coded silence") -> 4 | F2: =COUNTIFS(Thematic_Map!$F$2:$F$1319,"T1. LLMs Application / Usage for Architecture Design",Thematic_Map!$I$2:$I$1319,"Related activity") -> 25 | G2: =SUMPRODUCT(--(COUNTIFS(Thematic_Map!$F$2:$F$1319,"T1. LLMs Application / Usage for Architecture Design",Thematic_Map!$I$2:$I$1319,"Evidenced",Thematic_Map!$A$2:$A$1319,$I$2:$I$71)>0)) -> 69 | H2: 49 | I2: FS01 | J2: =COUNTIFS(Thematic_Map!$A$2:$A$1319,$I2,Thematic_Map!$F$2:$F$1319,"T1. LLMs Application / Usage for Architecture Design") -> 7 | K2: =COUNTIFS(Thematic_Map!$A$2:$A$1319,$I2,Thematic_Map!$F$2:$F$1319,"T2. Techniques for Optimization") -> 4 | L2: =COUNTIFS(Thematic_Map!$A$2:$A$1319,$I2,Thematic_Map!$F$2:$F$1319,"T3. Techniques for Evaluation") -> 4 | M2: =COUNTIFS(Thematic_Map!$A$2:$A$1319,$I2,Thematic_Map!$F$2:$F$1319,"T4. Emerging Trends") -> 6 | N2: =COUNTIFS(Thematic_Map!$A$2:$A$1319,$I2,Thematic_Map!$F$2:$F$1319,"T5. Limitations") -> 5 | O2: =COUNTIFS(Thematic_Map!$A$2:$A$1319,$I2,Thematic_Map!$F$2:$F$1319,"T6. Challenges") -> 2 | P2: =SUM(J2:O2) -> 28
A3: T2. Techniques for Optimization (RQ2) | B3: • 2.1 Prompting strategies: chain-of-thought, few-shot, role and self-refinement • 2.2 Knowledge grounding: RAG, knowledge graphs and architecture repositories • 2.3 Fine-tuning, model adaptation and multi-agent orchestration | C3: =COUNTIF(Thematic_Map!$F$2:$F$1319,"T2. Techniques for Optimization") -> 223 | D3: =COUNTIFS(Thematic_Map!$F$2:$F$1319,"T2. Techniques for Optimization",Thematic_Map!$I$2:$I$1319,"Evidenced") -> 194 | E3: =COUNTIFS(Thematic_Map!$F$2:$F$1319,"T2. Techniques for Optimization",Thematic_Map!$I$2:$I$1319,"Coded silence") -> 27 | F3: =COUNTIFS(Thematic_Map!$F$2:$F$1319,"T2. Techniques for Optimization",Thematic_Map!$I$2:$I$1319,"Related activity") -> 2 | G3: =SUMPRODUCT(--(COUNTIFS(Thematic_Map!$F$2:$F$1319,"T2. Techniques for Optimization",Thematic_Map!$I$2:$I$1319,"Evidenced",Thematic_Map!$A$2:$A$1319,$I$2:$I$71)>0)) -> 69 | H3: 49 | I3: FS02 | J3: =COUNTIFS(Thematic_Map!$A$2:$A$1319,$I3,Thematic_Map!$F$2:$F$1319,"T1. LLMs Application / Usage for Architecture Design") -> 8 | K3: =COUNTIFS(Thematic_Map!$A$2:$A$1319,$I3,Thematic_Map!$F$2:$F$1319,"T2. Techniques for Optimization") -> 4 | L3: =COUNTIFS(Thematic_Map!$A$2:$A$1319,$I3,Thematic_Map!$F$2:$F$1319,"T3. Techniques for Evaluation") -> 6 | M3: =COUNTIFS(Thematic_Map!$A$2:$A$1319,$I3,Thematic_Map!$F$2:$F$1319,"T4. Emerging Trends") -> 8 | N3: =COUNTIFS(Thematic_Map!$A$2:$A$1319,$I3,Thematic_Map!$F$2:$F$1319,"T5. Limitations") -> 4 | O3: =COUNTIFS(Thematic_Map!$A$2:$A$1319,$I3,Thematic_Map!$F$2:$F$1319,"T6. Challenges") -> 4 | P3: =SUM(J3:O3) -> 34
A4: T3. Techniques for Evaluation (RQ2) | B4: • 3.1 Evaluation designs: benchmarks, case studies, expert judgement, experiments • 3.2 Metrics and quality criteria used to judge generated architectures • 3.3 Cost, latency and reproducibility of the reported setups | C4: =COUNTIF(Thematic_Map!$F$2:$F$1319,"T3. Techniques for Evaluation") -> 266 | D4: =COUNTIFS(Thematic_Map!$F$2:$F$1319,"T3. Techniques for Evaluation",Thematic_Map!$I$2:$I$1319,"Evidenced") -> 210 | E4: =COUNTIFS(Thematic_Map!$F$2:$F$1319,"T3. Techniques for Evaluation",Thematic_Map!$I$2:$I$1319,"Coded silence") -> 54 | F4: =COUNTIFS(Thematic_Map!$F$2:$F$1319,"T3. Techniques for Evaluation",Thematic_Map!$I$2:$I$1319,"Related activity") -> 2 | G4: =SUMPRODUCT(--(COUNTIFS(Thematic_Map!$F$2:$F$1319,"T3. Techniques for Evaluation",Thematic_Map!$I$2:$I$1319,"Evidenced",Thematic_Map!$A$2:$A$1319,$I$2:$I$71)>0)) -> 67 | H4: 47 | I4: FS03 | J4: =COUNTIFS(Thematic_Map!$A$2:$A$1319,$I4,Thematic_Map!$F$2:$F$1319,"T1. LLMs Application / Usage for Architecture Design") -> 9 | K4: =COUNTIFS(Thematic_Map!$A$2:$A$1319,$I4,Thematic_Map!$F$2:$F$1319,"T2. Techniques for Optimization") -> 7 | L4: =COUNTIFS(Thematic_Map!$A$2:$A$1319,$I4,Thematic_Map!$F$2:$F$1319,"T3. Techniques for Evaluation") -> 8 | M4: =COUNTIFS(Thematic_Map!$A$2:$A$1319,$I4,Thematic_Map!$F$2:$F$1319,"T4. Emerging Trends") -> 5 | N4: =COUNTIFS(Thematic_Map!$A$2:$A$1319,$I4,Thematic_Map!$F$2:$F$1319,"T5. Limitations") -> 5 | O4: =COUNTIFS(Thematic_Map!$A$2:$A$1319,$I4,Thematic_Map!$F$2:$F$1319,"T6. Challenges") -> 3 | P4: =SUM(J4:O4) -> 37
A5: T4. Emerging Trends (RQ3) | B5: • 4.1 From single-prompt assistance towards agentic and multi-agent architecting • 4.2 Integration with model-driven engineering and formal artefact generation • 4.3 Human-AI collaboration and the changing role of the architect • 4.4 Movement from design-time assistance towards runtime and continuous architecting • 4.5 Trust, governance and responsible adoption in industrial settings | C5: =COUNTIF(Thematic_Map!$F$2:$F$1319,"T4. Emerging Trends") -> 226 | D5: =COUNTIFS(Thematic_Map!$F$2:$F$1319,"T4. Emerging Trends",Thematic_Map!$I$2:$I$1319,"Evidenced") -> 146 | E5: =COUNTIFS(Thematic_Map!$F$2:$F$1319,"T4. Emerging Trends",Thematic_Map!$I$2:$I$1319,"Coded silence") -> 31 | F5: =COUNTIFS(Thematic_Map!$F$2:$F$1319,"T4. Emerging Trends",Thematic_Map!$I$2:$I$1319,"Related activity") -> 49 | G5: =SUMPRODUCT(--(COUNTIFS(Thematic_Map!$F$2:$F$1319,"T4. Emerging Trends",Thematic_Map!$I$2:$I$1319,"Evidenced",Thematic_Map!$A$2:$A$1319,$I$2:$I$71)>0)) -> 66 | H5: 47 | I5: FS04 | J5: =COUNTIFS(Thematic_Map!$A$2:$A$1319,$I5,Thematic_Map!$F$2:$F$1319,"T1. LLMs Application / Usage for Architecture Design") -> 6 | K5: =COUNTIFS(Thematic_Map!$A$2:$A$1319,$I5,Thematic_Map!$F$2:$F$1319,"T2. Techniques for Optimization") -> 4 | L5: =COUNTIFS(Thematic_Map!$A$2:$A$1319,$I5,Thematic_Map!$F$2:$F$1319,"T3. Techniques for Evaluation") -> 5 | M5: =COUNTIFS(Thematic_Map!$A$2:$A$1319,$I5,Thematic_Map!$F$2:$F$1319,"T4. Emerging Trends") -> 3 | N5: =COUNTIFS(Thematic_Map!$A$2:$A$1319,$I5,Thematic_Map!$F$2:$F$1319,"T5. Limitations") -> 4 | O5: =COUNTIFS(Thematic_Map!$A$2:$A$1319,$I5,Thematic_Map!$F$2:$F$1319,"T6. Challenges") -> 3 | P5: =SUM(J5:O5) -> 25
A6: T5. Limitations (RQ3) | B6: • 5.1 Reported limitations in practice • 5.2 Reported reliability problems: hallucination, inconsistency, non-determinism | C6: =COUNTIF(Thematic_Map!$F$2:$F$1319,"T5. Limitations") -> 167 | D6: =COUNTIFS(Thematic_Map!$F$2:$F$1319,"T5. Limitations",Thematic_Map!$I$2:$I$1319,"Evidenced") -> 156 | E6: =COUNTIFS(Thematic_Map!$F$2:$F$1319,"T5. Limitations",Thematic_Map!$I$2:$I$1319,"Coded silence") -> 11 | F6: =COUNTIFS(Thematic_Map!$F$2:$F$1319,"T5. Limitations",Thematic_Map!$I$2:$I$1319,"Related activity") -> 0 | G6: =SUMPRODUCT(--(COUNTIFS(Thematic_Map!$F$2:$F$1319,"T5. Limitations",Thematic_Map!$I$2:$I$1319,"Evidenced",Thematic_Map!$A$2:$A$1319,$I$2:$I$71)>0)) -> 68 | H6: 48 | I6: FS05 | J6: =COUNTIFS(Thematic_Map!$A$2:$A$1319,$I6,Thematic_Map!$F$2:$F$1319,"T1. LLMs Application / Usage for Architecture Design") -> 6 | K6: =COUNTIFS(Thematic_Map!$A$2:$A$1319,$I6,Thematic_Map!$F$2:$F$1319,"T2. Techniques for Optimization") -> 4 | L6: =COUNTIFS(Thematic_Map!$A$2:$A$1319,$I6,Thematic_Map!$F$2:$F$1319,"T3. Techniques for Evaluation") -> 6 | M6: =COUNTIFS(Thematic_Map!$A$2:$A$1319,$I6,Thematic_Map!$F$2:$F$1319,"T4. Emerging Trends") -> 2 | N6: =COUNTIFS(Thematic_Map!$A$2:$A$1319,$I6,Thematic_Map!$F$2:$F$1319,"T5. Limitations") -> 5 | O6: =COUNTIFS(Thematic_Map!$A$2:$A$1319,$I6,Thematic_Map!$F$2:$F$1319,"T6. Challenges") -> 3 | P6: =SUM(J6:O6) -> 26
A7: T6. Challenges (RQ3) | B7: • 6.1 Open challenges and stated future work | C7: =COUNTIF(Thematic_Map!$F$2:$F$1319,"T6. Challenges") -> 84 | D7: =COUNTIFS(Thematic_Map!$F$2:$F$1319,"T6. Challenges",Thematic_Map!$I$2:$I$1319,"Evidenced") -> 84 | E7: =COUNTIFS(Thematic_Map!$F$2:$F$1319,"T6. Challenges",Thematic_Map!$I$2:$I$1319,"Coded silence") -> 0 | F7: =COUNTIFS(Thematic_Map!$F$2:$F$1319,"T6. Challenges",Thematic_Map!$I$2:$I$1319,"Related activity") -> 0 | G7: =SUMPRODUCT(--(COUNTIFS(Thematic_Map!$F$2:$F$1319,"T6. Challenges",Thematic_Map!$I$2:$I$1319,"Evidenced",Thematic_Map!$A$2:$A$1319,$I$2:$I$71)>0)) -> 68 | H7: 48 | I7: FS06 | J7: =COUNTIFS(Thematic_Map!$A$2:$A$1319,$I7,Thematic_Map!$F$2:$F$1319,"T1. LLMs Application / Usage for Architecture Design") -> 4 | K7: =COUNTIFS(Thematic_Map!$A$2:$A$1319,$I7,Thematic_Map!$F$2:$F$1319,"T2. Techniques for Optimization") -> 4 | L7: =COUNTIFS(Thematic_Map!$A$2:$A$1319,$I7,Thematic_Map!$F$2:$F$1319,"T3. Techniques for Evaluation") -> 6 | M7: =COUNTIFS(Thematic_Map!$A$2:$A$1319,$I7,Thematic_Map!$F$2:$F$1319,"T4. Emerging Trends") -> 2 | N7: =COUNTIFS(Thematic_Map!$A$2:$A$1319,$I7,Thematic_Map!$F$2:$F$1319,"T5. Limitations") -> 5 | O7: =COUNTIFS(Thematic_Map!$A$2:$A$1319,$I7,Thematic_Map!$F$2:$F$1319,"T6. Challenges") -> 2 | P7: =SUM(J7:O7) -> 23
A8: All themes | C8: =SUM(C2:C7) -> 1292 | D8: =SUM(D2:D7) -> 1087 | E8: =SUM(E2:E7) -> 127 | F8: =SUM(F2:F7) -> 78 | G8: =COUNTA(I2:I71) -> 69 | H8: 49 | I8: FS07 | J8: =COUNTIFS(Thematic_Map!$A$2:$A$1319,$I8,Thematic_Map!$F$2:$F$1319,"T1. LLMs Application / Usage for Architecture Design") -> 6 | K8: =COUNTIFS(Thematic_Map!$A$2:$A$1319,$I8,Thematic_Map!$F$2:$F$1319,"T2. Techniques for Optimization") -> 4 | L8: =COUNTIFS(Thematic_Map!$A$2:$A$1319,$I8,Thematic_Map!$F$2:$F$1319,"T3. Techniques for Evaluation") -> 5 | M8: =COUNTIFS(Thematic_Map!$A$2:$A$1319,$I8,Thematic_Map!$F$2:$F$1319,"T4. Emerging Trends") -> 1 | N8: =COUNTIFS(Thematic_Map!$A$2:$A$1319,$I8,Thematic_Map!$F$2:$F$1319,"T5. Limitations") -> 3 | O8: =COUNTIFS(Thematic_Map!$A$2:$A$1319,$I8,Thematic_Map!$F$2:$F$1319,"T6. Challenges") -> 1 | P8: =SUM(J8:O8) -> 20
I9: FS08 | J9: =COUNTIFS(Thematic_Map!$A$2:$A$1319,$I9,Thematic_Map!$F$2:$F$1319,"T1. LLMs Application / Usage for Architecture Design") -> 7 | K9: =COUNTIFS(Thematic_Map!$A$2:$A$1319,$I9,Thematic_Map!$F$2:$F$1319,"T2. Techniques for Optimization") -> 4 | L9: =COUNTIFS(Thematic_Map!$A$2:$A$1319,$I9,Thematic_Map!$F$2:$F$1319,"T3. Techniques for Evaluation") -> 4 | M9: =COUNTIFS(Thematic_Map!$A$2:$A$1319,$I9,Thematic_Map!$F$2:$F$1319,"T4. Emerging Trends") -> 5 | N9: =COUNTIFS(Thematic_Map!$A$2:$A$1319,$I9,Thematic_Map!$F$2:$F$1319,"T5. Limitations") -> 4 | O9: =COUNTIFS(Thematic_Map!$A$2:$A$1319,$I9,Thematic_Map!$F$2:$F$1319,"T6. Challenges") -> 3 | P9: =SUM(J9:O9) -> 27
I10: FS09 | J10: =COUNTIFS(Thematic_Map!$A$2:$A$1319,$I10,Thematic_Map!$F$2:$F$1319,"T1. LLMs Application / Usage for Architecture Design") -> 7 | K10: =COUNTIFS(Thematic_Map!$A$2:$A$1319,$I10,Thematic_Map!$F$2:$F$1319,"T2. Techniques for Optimization") -> 6 | L10: =COUNTIFS(Thematic_Map!$A$2:$A$1319,$I10,Thematic_Map!$F$2:$F$1319,"T3. Techniques for Evaluation") -> 4 | M10: =COUNTIFS(Thematic_Map!$A$2:$A$1319,$I10,Thematic_Map!$F$2:$F$1319,"T4. Emerging Trends") -> 6 | N10: =COUNTIFS(Thematic_Map!$A$2:$A$1319,$I10,Thematic_Map!$F$2:$F$1319,"T5. Limitations") -> 5 | O10: =COUNTIFS(Thematic_Map!$A$2:$A$1319,$I10,Thematic_Map!$F$2:$F$1319,"T6. Challenges") -> 2 | P10: =SUM(J10:O10) -> 30
I11: FS10 | J11: =COUNTIFS(Thematic_Map!$A$2:$A$1319,$I11,Thematic_Map!$F$2:$F$1319,"T1. LLMs Application / Usage for Architecture Design") -> 6 | K11: =COUNTIFS(Thematic_Map!$A$2:$A$1319,$I11,Thematic_Map!$F$2:$F$1319,"T2. Techniques for Optimization") -> 5 | L11: =COUNTIFS(Thematic_Map!$A$2:$A$1319,$I11,Thematic_Map!$F$2:$F$1319,"T3. Techniques for Evaluation") -> 3 | M11: =COUNTIFS(Thematic_Map!$A$2:$A$1319,$I11,Thematic_Map!$F$2:$F$1319,"T4. Emerging Trends") -> 5 | N11: =COUNTIFS(Thematic_Map!$A$2:$A$1319,$I11,Thematic_Map!$F$2:$F$1319,"T5. Limitations") -> 3 | O11: =COUNTIFS(Thematic_Map!$A$2:$A$1319,$I11,Thematic_Map!$F$2:$F$1319,"T6. Challenges") -> 2 | P11: =SUM(J11:O11) -> 24
I12: FS11 | J12: =COUNTIFS(Thematic_Map!$A$2:$A$1319,$I12,Thematic_Map!$F$2:$F$1319,"T1. LLMs Application / Usage for Architecture Design") -> 4 | K12: =COUNTIFS(Thematic_Map!$A$2:$A$1319,$I12,Thematic_Map!$F$2:$F$1319,"T2. Techniques for Optimization") -> 3 | L12: =COUNTIFS(Thematic_Map!$A$2:$A$1319,$I12,Thematic_Map!$F$2:$F$1319,"T3. Techniques for Evaluation") -> 4 | M12: =COUNTIFS(Thematic_Map!$A$2:$A$1319,$I12,Thematic_Map!$F$2:$F$1319,"T4. Emerging Trends") -> 5 | N12: =COUNTIFS(Thematic_Map!$A$2:$A$1319,$I12,Thematic_Map!$F$2:$F$1319,"T5. Limitations") -> 2 | O12: =COUNTIFS(Thematic_Map!$A$2:$A$1319,$I12,Thematic_Map!$F$2:$F$1319,"T6. Challenges") -> 2 | P12: =SUM(J12:O12) -> 20
I13: FS12 | J13: =COUNTIFS(Thematic_Map!$A$2:$A$1319,$I13,Thematic_Map!$F$2:$F$1319,"T1. LLMs Application / Usage for Architecture Design") -> 5 | K13: =COUNTIFS(Thematic_Map!$A$2:$A$1319,$I13,Thematic_Map!$F$2:$F$1319,"T2. Techniques for Optimization") -> 4 | L13: =COUNTIFS(Thematic_Map!$A$2:$A$1319,$I13,Thematic_Map!$F$2:$F$1319,"T3. Techniques for Evaluation") -> 3 | M13: =COUNTIFS(Thematic_Map!$A$2:$A$1319,$I13,Thematic_Map!$F$2:$F$1319,"T4. Emerging Trends") -> 5 | N13: =COUNTIFS(Thematic_Map!$A$2:$A$1319,$I13,Thematic_Map!$F$2:$F$1319,"T5. Limitations") -> 2 | O13: =COUNTIFS(Thematic_Map!$A$2:$A$1319,$I13,Thematic_Map!$F$2:$F$1319,"T6. Challenges") -> 1 | P13: =SUM(J13:O13) -> 20
I14: FS13 | J14: =COUNTIFS(Thematic_Map!$A$2:$A$1319,$I14,Thematic_Map!$F$2:$F$1319,"T1. LLMs Application / Usage for Architecture Design") -> 6 | K14: =COUNTIFS(Thematic_Map!$A$2:$A$1319,$I14,Thematic_Map!$F$2:$F$1319,"T2. Techniques for Optimization") -> 4 | L14: =COUNTIFS(Thematic_Map!$A$2:$A$1319,$I14,Thematic_Map!$F$2:$F$1319,"T3. Techniques for Evaluation") -> 6 | M14: =COUNTIFS(Thematic_Map!$A$2:$A$1319,$I14,Thematic_Map!$F$2:$F$1319,"T4. Emerging Trends") -> 5 | N14: =COUNTIFS(Thematic_Map!$A$2:$A$1319,$I14,Thematic_Map!$F$2:$F$1319,"T5. Limitations") -> 4 | O14: =COUNTIFS(Thematic_Map!$A$2:$A$1319,$I14,Thematic_Map!$F$2:$F$1319,"T6. Challenges") -> 1 | P14: =SUM(J14:O14) -> 26
I15: FS14 | J15: =COUNTIFS(Thematic_Map!$A$2:$A$1319,$I15,Thematic_Map!$F$2:$F$1319,"T1. LLMs Application / Usage for Architecture Design") -> 6 | K15: =COUNTIFS(Thematic_Map!$A$2:$A$1319,$I15,Thematic_Map!$F$2:$F$1319,"T2. Techniques for Optimization") -> 6 | L15: =COUNTIFS(Thematic_Map!$A$2:$A$1319,$I15,Thematic_Map!$F$2:$F$1319,"T3. Techniques for Evaluation") -> 3 | M15: =COUNTIFS(Thematic_Map!$A$2:$A$1319,$I15,Thematic_Map!$F$2:$F$1319,"T4. Emerging Trends") -> 5 | N15: =COUNTIFS(Thematic_Map!$A$2:$A$1319,$I15,Thematic_Map!$F$2:$F$1319,"T5. Limitations") -> 2 | O15: =COUNTIFS(Thematic_Map!$A$2:$A$1319,$I15,Thematic_Map!$F$2:$F$1319,"T6. Challenges") -> 1 | P15: =SUM(J15:O15) -> 23
I16: FS15 | J16: =COUNTIFS(Thematic_Map!$A$2:$A$1319,$I16,Thematic_Map!$F$2:$F$1319,"T1. LLMs Application / Usage for Architecture Design") -> 4 | K16: =COUNTIFS(Thematic_Map!$A$2:$A$1319,$I16,Thematic_Map!$F$2:$F$1319,"T2. Techniques for Optimization") -> 3 | L16: =COUNTIFS(Thematic_Map!$A$2:$A$1319,$I16,Thematic_Map!$F$2:$F$1319,"T3. Techniques for Evaluation") -> 4 | M16: =COUNTIFS(Thematic_Map!$A$2:$A$1319,$I16,Thematic_Map!$F$2:$F$1319,"T4. Emerging Trends") -> 5 | N16: =COUNTIFS(Thematic_Map!$A$2:$A$1319,$I16,Thematic_Map!$F$2:$F$1319,"T5. Limitations") -> 2 | O16: =COUNTIFS(Thematic_Map!$A$2:$A$1319,$I16,Thematic_Map!$F$2:$F$1319,"T6. Challenges") -> 1 | P16: =SUM(J16:O16) -> 19
I17: FS16 | J17: =COUNTIFS(Thematic_Map!$A$2:$A$1319,$I17,Thematic_Map!$F$2:$F$1319,"T1. LLMs Application / Usage for Architecture Design") -> 3 | K17: =COUNTIFS(Thematic_Map!$A$2:$A$1319,$I17,Thematic_Map!$F$2:$F$1319,"T2. Techniques for Optimization") -> 3 | L17: =COUNTIFS(Thematic_Map!$A$2:$A$1319,$I17,Thematic_Map!$F$2:$F$1319,"T3. Techniques for Evaluation") -> 4 | M17: =COUNTIFS(Thematic_Map!$A$2:$A$1319,$I17,Thematic_Map!$F$2:$F$1319,"T4. Emerging Trends") -> 5 | N17: =COUNTIFS(Thematic_Map!$A$2:$A$1319,$I17,Thematic_Map!$F$2:$F$1319,"T5. Limitations") -> 3 | O17: =COUNTIFS(Thematic_Map!$A$2:$A$1319,$I17,Thematic_Map!$F$2:$F$1319,"T6. Challenges") -> 1 | P17: =SUM(J17:O17) -> 19
I18: FS17 | J18: =COUNTIFS(Thematic_Map!$A$2:$A$1319,$I18,Thematic_Map!$F$2:$F$1319,"T1. LLMs Application / Usage for Architecture Design") -> 4 | K18: =COUNTIFS(Thematic_Map!$A$2:$A$1319,$I18,Thematic_Map!$F$2:$F$1319,"T2. Techniques for Optimization") -> 4 | L18: =COUNTIFS(Thematic_Map!$A$2:$A$1319,$I18,Thematic_Map!$F$2:$F$1319,"T3. Techniques for Evaluation") -> 4 | M18: =COUNTIFS(Thematic_Map!$A$2:$A$1319,$I18,Thematic_Map!$F$2:$F$1319,"T4. Emerging Trends") -> 5 | N18: =COUNTIFS(Thematic_Map!$A$2:$A$1319,$I18,Thematic_Map!$F$2:$F$1319,"T5. Limitations") -> 3 | O18: =COUNTIFS(Thematic_Map!$A$2:$A$1319,$I18,Thematic_Map!$F$2:$F$1319,"T6. Challenges") -> 1 | P18: =SUM(J18:O18) -> 21
I19: FS18 | J19: =COUNTIFS(Thematic_Map!$A$2:$A$1319,$I19,Thematic_Map!$F$2:$F$1319,"T1. LLMs Application / Usage for Architecture Design") -> 5 | K19: =COUNTIFS(Thematic_Map!$A$2:$A$1319,$I19,Thematic_Map!$F$2:$F$1319,"T2. Techniques for Optimization") -> 3 | L19: =COUNTIFS(Thematic_Map!$A$2:$A$1319,$I19,Thematic_Map!$F$2:$F$1319,"T3. Techniques for Evaluation") -> 4 | M19: =COUNTIFS(Thematic_Map!$A$2:$A$1319,$I19,Thematic_Map!$F$2:$F$1319,"T4. Emerging Trends") -> 5 | N19: =COUNTIFS(Thematic_Map!$A$2:$A$1319,$I19,Thematic_Map!$F$2:$F$1319,"T5. Limitations") -> 2 | O19: =COUNTIFS(Thematic_Map!$A$2:$A$1319,$I19,Thematic_Map!$F$2:$F$1319,"T6. Challenges") -> 1 | P19: =SUM(J19:O19) -> 20
I20: FS19 | J20: =COUNTIFS(Thematic_Map!$A$2:$A$1319,$I20,Thematic_Map!$F$2:$F$1319,"T1. LLMs Application / Usage for Architecture Design") -> 4 | K20: =COUNTIFS(Thematic_Map!$A$2:$A$1319,$I20,Thematic_Map!$F$2:$F$1319,"T2. Techniques for Optimization") -> 3 | L20: =COUNTIFS(Thematic_Map!$A$2:$A$1319,$I20,Thematic_Map!$F$2:$F$1319,"T3. Techniques for Evaluation") -> 4 | M20: =COUNTIFS(Thematic_Map!$A$2:$A$1319,$I20,Thematic_Map!$F$2:$F$1319,"T4. Emerging Trends") -> 3 | N20: =COUNTIFS(Thematic_Map!$A$2:$A$1319,$I20,Thematic_Map!$F$2:$F$1319,"T5. Limitations") -> 2 | O20: =COUNTIFS(Thematic_Map!$A$2:$A$1319,$I20,Thematic_Map!$F$2:$F$1319,"T6. Challenges") -> 1 | P20: =SUM(J20:O20) -> 17
... I70: FS69 | J70: =COUNTIFS(Thematic_Map!$A$2:$A$1319,$I70,Thematic_Map!$F$2:$F$1319,"T1. LLMs Application / Usage for Architecture Design") -> 4 | K70: =COUNTIFS(Thematic_Map!$A$2:$A$1319,$I70,Thematic_Map!$F$2:$F$1319,"T2. Techniques for Optimization") -> 3 | L70: =COUNTIFS(Thematic_Map!$A$2:$A$1319,$I70,Thematic_Map!$F$2:$F$1319,"T3. Techniques for Evaluation") -> 4 | M70: =COUNTIFS(Thematic_Map!$A$2:$A$1319,$I70,Thematic_Map!$F$2:$F$1319,"T4. Emerging Trends") -> 4 | N70: =COUNTIFS(Thematic_Map!$A$2:$A$1319,$I70,Thematic_Map!$F$2:$F$1319,"T5. Limitations") -> 2 | O70: =COUNTIFS(Thematic_Map!$A$2:$A$1319,$I70,Thematic_Map!$F$2:$F$1319,"T6. Challenges") -> 0 | P70: =SUM(J70:O70) -> 17

Sheet StudyWise_SAS_Extension
A1: Study | B1: Authors | C1: Core contribution | D1: Locus of the architectural work | E1: What breaks / is missing for SAS | F1: Framework reading (link grade) | G1: Best fit and why | H1: Possible extension for SAS (testable), with preconditions and risks | I1: Grounding
A2: FS01 | B2: Narváez, Battaglia, Fernández & Rossi | C2: Systematic review (43 studies, 2018-2024) of AI in microservices design: service identification, decomposition, decision support and documentation, plus runtime autoscaling and monitoring. | D2: Design time with runtime feedback | E2: (a) Closed loop: traces and metrics inform the architect, but nothing plans or enacts a change of service boundaries (pp. 13-14). (b) Adaptation target: only capacity and resources adapt at runtime; the decomposition is fixed (pp. 11-13). (c) Acceptance: no standard metric for decomposition quality (p. 4), and data consistency is left to the architect (p. 11). (d) The language model works only at design time. | F2: MAPE-K (Partial): Monitor and Analyse over traces exist; Plan and Execute exist only for resources, never for the decomposition. Rainbow (Inferred): decomposition as architecture model, coupling and latency as gauges, thresholds as constraints, split/merge/move as strategies; the review supplies the measures but none of the model, constraint or strategy parts. Models@run.time (Inferred): no model is kept at runtime, and the model-to-system direction is blocked by data consistency (p. 11). Three-layer (Inferred): the runtime work sits in the lower layers; redrawing service boundaries is goal management, which none of it reaches. | G2: Rainbow. The one architectural adaptation the review points to is changing the decomposition from observed coupling and bottlenecks, which is adaptation over an explicit architecture model. MAPE-K fits only for resources; Models@run.time names the missing representation but not the decision logic. | H2: Keep the service decomposition as a runtime architecture model. Monitor coupling and latency, check them against boundary constraints, let a language model propose a split, merge or move with its rationale, and check the proposal against the constraints and a data-consistency precondition before it is applied. Test on an open microservice reference application against architects' decisions, measuring coupling and latency before and after. Preconditions: a machine-readable dependency model; an agreed coupling measure (not standardised, p. 4); a data-migration path (p. 11). Risks: re-partitioning is slow and belongs in an outer loop; the review reports no evaluation of language models in this role. | I2: Partly grounded
A3: FS02 | B3: Esposito, Li, Moreschini, Ahmad, Cerny, Vaidhyanathan, Lenarduzzi & Taibi | C3: Multivocal review of 46 sources on generative AI in software architecture: purposes, models, techniques, life-cycle phases, validation methods and challenges, with future directions. | D3: Design time only | E3: (a) Runtime operation: work concentrates on requirements-to-architecture (40%) and architecture-to-code (32%); runtime appears only as a future direction (p. 16). (b) Autonomy: 85% of sources keep a human in the interaction (p. 10). (c) Acceptance: 93% report no validation of model output (p. 14). (d) Change of an existing architecture, which is what adaptation does, is the least studied transition (3%, p. 11). | F3: MAPE-K (Partial): the catalogued capabilities map onto separate activities, all at design time: recovery and assessment as Analyse, decision support as Plan, architecture-to-code as Execute, retrieval as Knowledge. Monitor is missing. Rainbow (Inferred): the two architecture-to-architecture sources (violation resolution, smell refactoring) are Rainbow-shaped, but 74% of sources have no explicit architecture model (p. 13). Models@run.time (Inferred): models, where present, are design artefacts; there is nothing to connect causally. ActivFORMS (Inferred): answers the review's sharpest gap, assurance (p. 17), but presupposes formal models the corpus lacks. | G3: MAPE-K feedback loop. The activities exist separately, and the review itself names their integration, plus monitoring of usage, as the missing step. Rainbow fits only two sources; Models@run.time and ActivFORMS name the missing representation and assurance but not how the capabilities fit together. | H3: Compose the catalogued capabilities over a shared runtime architecture model: recovery keeps it current, conformance and smell detection analyse it, repair recommendations plan the change, architecture-to-code generation executes it. Test: an LLM conformance-and-repair loop run on every change of an evolving open-source system detects injected violations and proposes fixes that pass static analysis at a rate comparable to an architect's review. Preconditions: an explicit architecture model (absent in 74%); an acceptance check (absent in 93%); architecture-code traceability. Risks: accuracy and hallucination become runtime faults once the human is removed; the adaptation evidence rests on one source. | I3: Partly grounded
A4: FS03 | B4: Zhang, Liu, Sun, Xu, Sun, Li, Jin & Liu | C4: SemRef: a language model refines recovered module views into a named hierarchy with summaries, and each change is kept only if dependency cohesion improves or a second prompt confirms it. | D4: Design time only | E4: (a) Liveness: a one-off offline run on a code snapshot. (b) Source of truth: static dependencies only (pp. 1688, 1693). (c) Timeliness: run time is not reported, and summarisation is repeated on each run (p. 1696). (d) The model changes the architecture model, never the system. | F4: MAPE-K (Partial): Analyse and Knowledge, a checked model of the structure; no Plan or Execute on the system. Rainbow (Inferred): it produces the architecture model Rainbow presupposes, and its acceptance rule works like a constraint check. Models@run.time (Inferred): supplies the system-to-model half, with incremental re-summarisation of changed modules (p. 1692); there is no model-to-system half. FORMS (Inferred): the hierarchy is a reflection model of the base-level structure. | G4: Models@run.time. Its contribution is building, and incrementally maintaining, an architecture model from the system. Rainbow needs such a model but adds logic the paper lacks; MAPE-K fits only through Analyse and Knowledge. | H4: Run the refinement incrementally on change events, with dynamic as well as static dependencies, so that it keeps a runtime architecture model current. Test: after injected changes, incremental refinement restores accuracy against an updated ground truth (MoJoFM, a2a_adj) at a fraction of a full run's token cost and within a stated time budget. Preconditions: change events; dynamic dependency data; ground truth (available for nine projects only). Risks: summarisation dominates cost; hallucination cannot be eliminated, so the cohesion check must stay; run time is unknown. | I4: Partly grounded
A5: FS04 | B5: Alves Pereira, Sousa, Dantas Filho, Albuquerque, Perkusich, Gorgônio & Perkusich | C5: Characterises the microservice architectures language models produce from the documentation of a modular monolith; the prompting strategy shifts granularity and coupling systematically. | D5: Design time only | E5: (a) Liveness: a one-off modernisation step from documents. (b) Acceptance: the metrics describe outputs without thresholds or ground truth. (c) Stability: one run per configuration, so variance is unknown (pp. 6-7). (d) Controllability: the prompt shifts structure and becomes a hidden parameter. | F5: MAPE-K (Inferred): the generated decomposition resembles a Plan for structural change, with no Monitor, Analyse or Execute. Rainbow (Inferred): service count, communication density and isolated services are gauge-like properties of a component-and-connector model; as constraints they could accept or reject an alternative. Models@run.time (Inferred): the CSV output is a machine-readable architecture representation with no connection to a running system. Dynamic product lines (Inferred): open-ended, prompt-sensitive generation argues for bounding adaptation to pre-checked variants. | G5: Rainbow. It supplies an explicit component-and-connector model and architectural metrics usable as constraints, and its task, turning one architecture into another, is what a Rainbow strategy does. MAPE-K adds little; Models@run.time lacks the runtime connection. | H5: Treat LLM-generated alternative decompositions as candidate strategies, each scored with the study's structural metrics against explicit constraints before one is selected. Test: with several candidates per prompting strategy, constraint-based selection picks structurally equivalent architectures across repeated runs even when the raw outputs vary. Preconditions: explicit constraints on granularity and coupling; repeated runs; named models and settings. Risks: stochastic outputs; without ground truth, satisfying a constraint is not correctness; the prompting strategy must be fixed. | I5: Partly grounded
