Workbook

Sheet Method_Used
B1: LLMs for software architecture, thematic synthesis of 23 primary studies
B2: Research Questions (RQs) | C2: RQ1 What has been reported to date for the use of LLMs and Gen AI for architectural design support? RQ2 What techniques are reported to optimize and evaluate LLMs and Gen AI for architectural design support? RQ3 What are the emerging trends in the use of LLMs and Gen AI for architectural design? RQ4 How can the approaches, techniques and trends identified in RQ1-RQ3 be extended to support the architecture design of self-adaptive software systems?
B3: Approach Used | C3: Thematic synthesis of primary research is performed, using the suggested process of Cruzes and Dyb are (2011) thematic synthesis in software engineering: extract data, code the extracted data, translate the codes into themes, develop a model of higher level themes, and evaluate the credibility of the synthesis. The analytic work is organized into the steps in the six-phase structure of Braun and Clarke (2006). The analysis is deductive at the level of theme and inductive at the lower levels. The themes were not discovered and were predetermined in terms of content, thus the structure of the themes is not an option and finding. Three passes (one per descriptive research question) were used in the first pass; the study has six passes (T1 answers RQ1, T2 and T3 answer RQ2, T4, T5 and T6 answer RQ3). Both are deductive on level of themes; the mapping of its themes and sub-themes are discussed in Themes and sub-themes. The data were structured into codes and sub-themes: a code book was created based on a two-study pilot, which was then applied to all other studies, new codes were created and old ones were merged as the corpus was processed, and the sub-themes were then formed by clustering codes instead of defining them at the start. This is a code-book methodology in the three-way typology of thematic analysis established by Braun and Clarke (2021): a structured code book and themes determined early, used by more than a single coder but without measuring inter-coder agreement which is a characteristic of coding-reliability thematic analysis. It is referred to as Braun & Clarke (2006) as having a six-phase sequence, which is merely an organising structure of the analytic work, which that paper is authorized to permit in theoretical and deductive discussions and critique. Under 'Validation' how the code book was implemented and how conflict was solved is documented.
B4: Coding Ladder | C4: The analytic ladder is displayed in each row of the 'Thematic map' sheet. Left-right reading: It progresses in the order of concrete to abstract: Meaning unit, Code, Sub-theme, Theme. Each Theme unreading into right to left sets out its Sub-themes, in which the Codes, founded on the original Meaning units, are found. The two directions are internally consistent, an audit trail in a data-themes and vice versa.
B5: Meaning Unit | C5: A concise, summary description of a primary study containing single idea, an outlined method, methodology, discovery or reported constraint. Both paraphrased and not quoted, in order to both not reproduce licenced copyrighted text, but to place the units, more or less, on equal footing, with respect to granularity. Section or page is noted in a manner that all the units can be traced.
B6: Coding Absences | C6: A study that is silent on an aspect on which the review inquires, and where that silence is analytically significant, is coded as a unit of meaning with the word Absence at the beginning of the code, and the Source column names where such a piece of information would have been found. Absences are reported individually of positive findings and are never stated as a claim that the authors made.
B7: Granularity Rule | C7: Each unit of meaning has one idea. Where a study gives many instances of the same idea given only one is literally counted, and the multiplicity is indicated in it, instead of a series of similar epochs, when a long paper will weigh against a short, that being on a lengthy scale.
B8: Study Families and Independence | C8: The result of some of the studies in the corpus is not independent: one of the authors might report a method in one place and its evaluation in another, with the same subjects, the same companies and even the same transcripts of the model. These kinds of studies compose a family. The sheet included studies records the family in a specific column. To communicate the number of studies supporting a theme, indicate the number of independent families with that number, and state the total number research studies, otherwise a one-line of work is reported twice and evidence appears more extensive than it is. On that test, three families are created. S1 and S2 are F1; same first author, same two companies and the URLs published on S2 in two prompt-transcripts are character by character identical to the URLs published on S1. For instance; S3 and S8 are F2: S3 states ArchMind, we proposed the ArchMind research prototype in earlier work [8], and S8 is the paper on ArchMind. S4 and S9 Are F3: the study S4 reports in full that S9 reports is not a related report, but an overlapping report.
B9: Theme or Sub-theme | C9: Related codes are clustered by sub-themes; themes are the broad structure which will respond to the research question or a single facet of it. Design applies six themes with T1 answering RQ1, T2 and T3 answering RQ2 and T4, T5 and T6 answering RQ3. Six themes: RQ1 is answered by T1, RQ2 by T2 and T3, RQ3 by T4, T5 and T6 with 20 sub-themes. T1. LLMs Application / Usage for Architecture Design (RQ1) 1.1 Architecture generation and synthesis from requirements 1.2 Design decision support: pattern, tactic and technology recommendation 1.3 Architecture documentation, decision records and rationale capture 1.4 Architecture analysis, recovery, conformance and smell detection 1.5 The role assigned to the model: assistant, co-designer or autonomous agent 1.6 Reported benefits in practice T2. Techniques for Optimization (RQ2) 2.1 Prompting strategies: chain-of-thought, few-shot, role and self-refinement 2.2 Knowledge grounding: RAG, knowledge graphs and architecture repositories 2.3 Fine-tuning, model adaptation and multi-agent orchestration T3. Techniques for Evaluation (RQ2) 3.1 Evaluation designs: benchmarks, case studies, expert judgement, experiments 3.2 Metrics and quality criteria used to judge generated architectures 3.3 Cost, latency and reproducibility of the reported setups T4. Emerging Trends (RQ3) 4.1 From single-prompt assistance towards agentic and multi-agent architecting 4.2 Integration with model-driven engineering and formal artefact generation 4.3 Human-AI collaboration and the changing role of the architect 4.4 Movement from design-time assistance towards runtime and continuous architecting 4.5 Trust, governance and responsible adoption in industrial settings T5. Limitations (RQ3) 5.1 Reported limitations in practice 5.2 Reported reliability problems: hallucination, inconsistency, non-determinism T6. Challenges (RQ3) 6.1 Open challenges and stated future work
B10: A Note Related to RQ3 | C10: The trends are not visible on a single piece of paper, as a technique, and therefore each row T4 and under 6.1 represents how the trend was demonstrated. The strongest possible signal is explicit, the authors themselves indicate a change, open challenge or future direction. No signals indicates that they do not. In T1, T 2; T 3 and T 5, there is no signal in the rows. Another value, judgement about the synthesis across studies, and not a property of individual row, was a distributional reading, the spread of the publication years, and is not used (an inferred value in the first pass).
B11: RQ4: The Extension Analysis | C11: In 'SAS extension' sheet, RQ4 is answered. It is not done by coding of the primary studies. Primary studies are about large language models (LLMs) for software architecture design support in general but they are not about self adaptive software systems (SASS). Every sub-theme that is developed based on RQ1 to RQ3 is carried forward and its analysis is done based on the requirements of SASS. Details about our idea of extension of studies towards SASS is also given in 'StudyWise_SAS_Extension'. An answer is not pegged on MAPE-K alone but each study is read off against MAPE-K, Rainbow, and Models@run.time, and on one side a model or the other. According to study: The locus of the architecture object; that breaks down to a SASS, to be expressed as a named property; reading framework with link grade; the best fit and why others do not fit. Where applicable, other models are also suggested in support; for instance self-management systems, as the references are given: - MAPE-K feedback loop: Kephart, J.O. & Chess, D.M. (2003). The Vision of Autonomic Computing. Computer, 36(1), 41-50. DOI 10.1109/MC.2003.1160055 - Rainbow (architecture-based self-adaptation): Garlan, D., Cheng, S.-W., Huang, A.-C., Schmerl, B. & Steenkiste, P. (2004). Rainbow: Architecture-Based Self-Adaptation with Reusable Infrastructure. Computer, 37(10), 46-54. DOI 10.1109/MC.2004.175 - Models@run.time: Blair, G., Bencomo, N. & France, R.B. (2009). Models@run.time. Computer, 42(10), 22-27. DOI 10.1109/MC.2009.326 - Three-layer architecture for self-managed systems: Kramer, J. & Magee, J. (2007). Self-Managed Systems: an Architectural Challenge. Future of Software Engineering (FOSE ’07), 259-268. DOI 10.1109/FOSE.2007.19 - FORMS reference model: Weyns, D., Malek, S. & Andersson, J. (2012). FORMS: Unifying Reference Model for Formal Specification of Distributed Self-Adaptive Systems. ACM Transactions on Autonomous and Adaptive Systems, 7(1), 1-61. DOI 10.1145/2168260.2168268 - EUREMA (executable runtime megamodels): Vogel, T. & Giese, H. (2014). Model-Driven Engineering of Self-Adaptive Software with EUREMA. ACM Transactions on Autonomous and Adaptive Systems, 8(4), 1-33. DOI 10.1145/2555612 - ActivFORMS (active formal models): Iftikhar, M.U. & Weyns, D. (2014). ActivFORMS: Active Formal Models for Self-Adaptation. Proceedings of SEAMS 2014, 125-134. DOI 10.1145/2593929.2593944 - Dynamic software product lines: Hallsteinsen, S., Hinchey, M., Park, S. & Schmid, K. (2008). Dynamic Software Product Lines. Computer, 41(4), 93-95. DOI 10.1109/MC.2008.123 - Control-theoretic adaptation: Filieri, A., Maggio, M., et al. (2015). Software Engineering Meets Control Theory. Proceedings of SEAMS 2015, 71-82. DOI 10.1109/SEAMS.2015.12 - Requirements-driven adaptation (awareness requirements): Souza, V.E.S., Lapouchnian, A., Robinson, W.N. & Mylopoulos, J. (2011). Awareness Requirements for Adaptive Systems. Proceedings of SEAMS 2011, 60-69. DOI 10.1145/1988008.1988018
B12: References | C12: 1- Cruzes, D.S. & Dybå, T. (2011), 'Recommended Steps for Thematic Synthesis in Software Engineering', ESEM 2011, 275-284. DOI 10.1109/ESEM.2011.36. Primary method: the five-step thematic synthesis procedure followed here. 2- Braun, V. & Clarke, V. (2006), 'Using thematic analysis in psychology', Qualitative Research in Psychology, 3(2), 77-101. DOI 10.1191/1478088706qp063oa. Source of the six-phase structure used to organise the analytic work. 3- Braun, V. & Clarke, V. (2021), 'One size fits all? What counts as quality practice in (reflexive) thematic analysis?', Qualitative Research in Psychology, 18(3), 328-352.
B13: Validation | C13: The independent coding was conducted by all authors. Each author used a common code book, which was formulated on the pilot studies, to apply to the same studies without referring to the others, and all disagreement on a code, a sub-theme or a row type was discussed and agreed to an assignment to ensure that none of the code was entered randomly. The coded information in the 'Thematic map' is the consensus outcome of such independent work, not the assigning done by one author. It is a coding-reliability practice per software engineering (SE). One such measure to show consistency between authors is a quantitative agreement statistic; another is independent application of a common code book followed by agreement on the coding completed, which is applied here.
... B18: Scope Criterion and its Supporting Rules | C18: The operational test used at full-text reassessment: A model is in scope when a model executes or in a proposal paper is said to execute a task the object of which is a software architecture. The borderline cases were decided by four supporting rules which are mentioned below since it is on them that the reasons used on the Withdrawn studies sheet are based. (1) The scope is determined by the object of the work of the model: its position within a system is irrelevant. The model as a part of an architecture is not in itself architectural work, and the run-to-run task workflow is not the architecture of the system in which it is instantiated. (2) Metadata can only support a scope decision, and never determines one. Title, keywords, venue and classification terms have only supporting evidence the entire text has the final say. (3) The knowledge-artefact rule. A model that generates a knowledge artefact, e.g. a domain ontology, a knowledge graph or a taxonomy of an application domain, is not performing architectural work. This is not a software architecture but domain knowledge.

Sheet Included_Studies
A1: Sr | B1: ID | C1: Authors | D1: Title | E1: Year | F1: Venue | G1: Contribution type | H1: LLM / Gen AI used | I1: Architectural task addressed | J1: Evaluation type | K1: Family | L1: Coverage and independence
A2: 1 | B2: S1 | C2: Maranhão & Guerra | D2: A Prompt Pattern Sequence Approach to Apply Generative AI in Assisting Software Architecture Decision-making | E2: 2024 | F2: EuroPLoP 2024 | G2: Technique and pattern-language contribution; there is no empirical work attached. There are five prompt patterns of architectural decision making (Software Architect Persona, Architectural Project Context, Quality Attribute Question, Technical Premises, Uncertain Requirement Statement), and they are documented in the forms of a lengthy Coplien and have a list of consequences of two sides. At the top of the catalogue, and of the headline of the paper: a fixed five stage process plus a conditional decision flow with an architect evaluate- and refine gate following the application of each pattern applied. Novelty has partiality and is proclaimed: three of the five specialise published patterns of White et al. (Persona, Question Refinement, Fact Check List) and only two proclaim no specialisation. Usefulness is reported as a practitioner appreciation provided in each of the known-uses sections of the patterns being used by the authors. | H2: ChatGPT or GPT. | I2: The support for architectural decision-making is performed along with quality attribute trade-off and uncertainty handling as well. | J2: An illustrative application is used along with two industrial scenarios and one fictional case; qualitative practitioner feedback is also used. However, there is no baseline. | K2: F1 | L2: 37 meaning units (11 / 7 / 5 / 6 / 6 / 2 across themes T1 to T6). Introduces five patterns; S2 says that there is no assessment of these five patterns in this paper. Shared links are executed transcripts.
A3: 2 | B3: S2 | C3: Maranhão Junior, Melegati & Guerra | D3: Applying a Prompt Pattern Sequence for Decision-Making in Microservices Architectures | E3: 2025 | F3: ESOCC 2025, LNCS 15547, pp. 18-32 | G3: Empirical study, retrospective multi-case (2 cases, 2 participants), assessing patterns shown in S1. The 5 patterns are described again in the paper (both is a contribution and also an evaluation), therefore it constitutes both a re-presentation and an evaluation. | H3: GPT-4o. | I3: The support for architectural decision making is done especially for microservices architectures. | J3: Case study is used, 2 industrial decisions completed that were re-enacted, semi-structured interviews with 2 architects who made the decisions | K3: F1 | L3: 32 meaning units (9 / 5 / 7 / 5 / 5 / 1 across themes T1 to T6). Not independent of S1: 5 patterns, same two Brazilian companies (car financing; 3000 store pharmacy retail), and both published prompt transcript URLs are same as 2 of S1's. Count as one family with S1 when reporting coverage.
A4: 3 | B4: S3 | C4: Diaz-Pace, Tommasel, Capilla & Ramírez | D4: Architecture Exploration and Reflection meet LLM-based Agents | E4: 2025 | F4: ICSA-C 2025 | G4: Agent architecture + Proof of Concept (PoC), and Technique. | H4: GPT-4o-mini, via LlamaIndex. | I4: The study performs exploration for architecture alternatives, tactic and pattern search along with assesment and decision support. | J4: Evaluation involved initial evaluation and a case study published earlier, which was reused (13 requirements); two different agent configurations were evaluated against the original published one; no human subjects were involved. | K4: F2 | L4: 29 meaning units (8 / 4 / 6 / 6 / 4 / 1 across themes T1 to T6). Independent of F1. First study in the corpus to fill sub-themes 1.1, 1.4, 2.3 and 3.2.
A5: 4 | B5: S4 | C5: Dhar, Vaidhyanathan & Varma | D5: Can LLMs Generate Architectural Design Decisions? An Exploratory Empirical Study | E5: 2024 | F5: ICSA 2024 | G5: A comparison in a controlled way is given for three adaptation approaches, Empirical study. | H5: 18 models are used: GPT-2/3/3.5/4 families and T5, T0, Flan-T5 families. | I5: The generation of decision for an architecture decision record from its existing context is done; means architecture knowledge management (AKM). | J5: This is an experiment that is replicated across multiple public repositories (95 records), is compared to an automatic metric of the experiment, and is also manually evaluated on a subset. | K5: F3 | L5: 34 meaning units (7 / 7 / 9 / 6 / 3 / 2 across themes T1 to T6). Not dependent on F1 and F2.
A6: 5 | B6: S5 | C6: Soliman & Keim | D6: Do Large Language Models Contain Software Architectural Knowledge? An Exploratory Case Study with GPT | E6: 2025 | F6: ICSA 2025 | G6: Empirical study, evaluation of embedded knowledge. | H6: GPT-3.5 is used and is stated as the most trending and stable version at the time, as is called via API. | I6: Discussing the architectural knowledge of an existing system: components and connectors, quality-attribute solutions, rationale. | J6: Exploratory single-embedded case study, with 14 engineers, 236 questions, precision/recall/F1 measures, and a manually created ground truth, along with Likert quality and trustworthiness ratings, and a content analysis of the justifications given. | K6: F4 | L6: 36 meaning units (9 / 4 / 8 / 6 / 7 / 2 across themes T1 to T6). Independent of F1-F3. First time of study in the corpus that employs a distinction between trustworthiness and accuracy, (a) constructs a ground truth for an existing system, (b) quantifies the uncertainty in model output, and (c) calls model output randomness as a threat to validity.
A7: 6 | B7: S6 | C7: Ramachandran | D7: Empowering Software Architects with Artificial Intelligence: Analyzing GitHub Copilot's Role in Modern Architecture Design | E7: 2025 | F7: CSECS 2025 | G7: Empirical generation-and-comparison study, single author, practitioner authored, no research design is named, no research question and no threats-to-validity section. A few note-takes are created to build the model manually, then scored by copilot against the four sets of UML diagrams, generated by the same copilot from the requirements specification, that have been published, using a borrowed similarity score in the graph where both the nodes and edges take equal weight, then taken a few adjustments to meet a fixed threshold of 0.6, giving a score of use case 0.56 (which was adjusted up to 0.61), class 0.61, sequence 0.66, and state 0.70. The important part is the deviation annotation per-diagram, with the named annotation omissions and relabellings plus correct material the model generated, which the metric penalises, and a public catalog of prompts; generated markups and scores. | H7: GitHub Copilot and attributes output to ChatGPT. | I7: Creating UML design diagrams (use case, class, sequence, state) from requirements specification. | J7: One reference document is used along with four diagrams, there is one rater, no section for threats-to-validity, no baselines, and no repeatition of experiments. | K7: F5 | L7: 28 meaning units (8 / 3 / 6 / 6 / 3 / 2 across themes T1 to T6). Independent family F5. Co-writes with S19. Second family to reach sub-themes 1.1 and 3.2, so they are no longer single-family. Use its numerical results as an approximation: the stopping rule sets the scores just below 0.6.
A8: 7 | B8: S7 | C8: Eisenreich, Speth & Wagner | D8: From Requirements to Architecture: An AI-Based Journey to Semi-Automatically Generate Software Architectures | E8: 2024 | F8: Designing '24, IEEE/ACM International Workshop on Designing Software | G8: A six-step process is proposed. A vision paper in which one small exploratory test is performed of its first step only. | H8: Currently testing Llama2-70B and GPT-3.5 (chat versions) and considering Llama, Falcon, and Yi for full proposed pipeline, not have been used yet. | I8: Comprehensive pipeline: from requirements to the domain model to multiple architecture candidates to automated evaluation to human selection. | J8: No metric or rater, narrative observation, informal exploratory test of domain-model generation only (91 requirements, MobSTr dataset). Proposal of the stages of architecture generation and evaluation, which have not been tested. Two full studies were planned, but not carried out. | K8: F6 | L8: 26 meaning units (8 / 4 / 4 / 5 / 3 / 2 across themes T1 to T6). Independent (F6). All pipeline-level claims—architecture candidate quality, usefulness of ADR, automation of evaluation; are proposed, not demonstrated, with the domain-model claim being the only one with any sort of empirical support, and the support is informal.
A9: 8 | B9: S8 | C9: Díaz-Pace, Tommasel & Capilla | D9: Helping Novice Architects to Make Quality Design Decisions Using an LLM-Based Assistant | E9: 2024 | F9: ECSA 2024 | G9: Technique and an initial evaluation is performed, ArchMind (a multi-copilot assistant) is used, and its described as an experiment by the authors. | H9: OpenAI GPT-3.5 is used, via Chroma vector store and a Langchain. | I9: Creating architecture decision records for specific requirements: pattern suggestion, decision evaluation, consistency checking, ADR generation | J9: One student project is used as a single system, generated 16 records, five of them were reviewed manually by the authors themselves against the student formed records that were not treated as ground truth. | K9: F2 | L9: 31 meaning units (9 / 5 / 5 / 6 / 4 / 2 across themes T1 to T6). Family member of S3 (F2).
A10: 9 | B10: S9 | C10: Dhar, Vaidhyanathan & Varma | D10: Leveraging Generative AI for Architecture Knowledge Management | E10: 2024 | F10: ICSA-C 2024 | G10: Proposed vision and approach with nothing constructed and nothing assessed. In two steps, proposes using a multi-modal retrieval-augmented generation for a system that can retrieve AK from a project's own repositories, import it from other sources, check the correctness of query results with an Oracle verifier and store the results with an AK generator; and for a retrieval phase that returns the result to open-ended and/or template questions that are appropriate to the question poser's role. Four engineering challenges the system would need to overcome are stated in the motivation section. The paper contains no empirical claims in it other than a rewritten summary of the own exploratory study of creating architecture decision records (this corpus contains the complete original study as S4). | H10: T5 based model family and GPT; the proposed fusion/extraction/ or retrieval pipeline itself uses no named model, being unbuilt. | I10: The entire AKM lifecycle: Extracting AK from a system, combining it with external knowledge, validating it and answering stakeholder questions against it. | J10: It is an empirical section that summarizes S4's exploratory study (same models, metrics, GitHub repository, and conclusions), but does not include any extraction, fusion, verification and retrieval components, nor is there any implementation or evaluation of those components. | K10: F3 | L10: 29 meaning units (9 / 5 / 3 / 7 / 3 / 2 across themes T1 to T6). Same family as S4 (F3): all three authors are the same, and S4's reference list mentions that this is 'companion work'.
A11: 10 | B11: S10 | C11: Jahić & Sami | D11: State of Practice: LLMs in Software Engineering and Software Architecture | E11: 2024 | F11: ICSA-C 2024 | G11: It is an empirical study of mixed methods, containing experiments on zero-shot generation with an industrial survey that is used for validation. | H11: For reproducibility; GPT 3.5 has been chosen over GPT-4, both are tried and compared. | I11: Creating C4-model based views (System Context, Container, Component) and tool-chain suggestion based on requirements description | J11: 50 experiments in 5 real projects, manually analyzed and blindly reviewed with 4 original project authors as reviewers; industry survey of 15 companies as a validation. | K11: F7 | L11: 35 meaning units (10 / 4 / 6 / 8 / 5 / 2) for themes T1 to T6.
A12: 11 | B12: S11 | C12: Ahmad, Waseem, Liang, Fahmideh, Aktar & Mikkonen | D12: Towards Human-Bot Collaborative Software Architecting with ChatGPT | E12: 2023 | F12: Ease 2023 | G12: Three activities human-bot cooperative architecting process with example “process proposal + illustrative case study.” The authors characterize the results as preliminary and explicitly set the empirical results from the third phase out of the scope of the study. | H12: ChatGPT (date of use and the settings of version are not stated anywhere in the article). | I12: The complete architecting process, which involves architecturally significant requirements elicitation from an architecture story, architecturally significant UML class and component models (architectural synthesis), and architecturally significant scenarios (SAAM) | J12: One case study of a campus bike-sharing application was used as an exemplifying case study; one architect, no other participants, no baseline, no metric, no repetition. S6 will not be able to analyse threats to validity as it has them under internal, external and conclusion validity. | K12: F8 | L12: 32 meaning units (10 / 4 / 5 / 8 / 3 / 2) for themes T1 to T6.
A13: 12 | B13: S12 | C13: Keim, Kaplan, Koziolek & Mirakhorli | D13: Does BERT Understand Code?, An Exploratory Study on the Detection of Architectural Tactics in Code | E13: 2020 | F13: ECSA 2020 | G13: Empirical study and technique (BERT fine-tuned as a multi-class code classifier) with comparative evaluation against 7 prior ML baselines. | H13: BERT-base, fine-tuned with transfer learning (TL) for classification. | I13: Architecture analysis/recovery: Identification of the architectural tactics implemented by an existing code class (of a predefined set of five) to facilitate recovery of the traceability link from the code back to the quality-driven design decisions. | J13: 10-fold cross-validation of a reused dataset (Mirakhorli et al. 2016) + replication on Apache Hadoop HDFS; benchmarked against 7 other classifiers: SVM, Slipper, J48, Bagging, AdaBoost, Bayesian, Mirakhorli's Tactic Detector; evaluated using Precision/Recall/F1; Friedman significance test for classifiers. | K13: F9 | L13: 29 meaning units (8 / 5 / 4 / 5 / 6 / 1) around themes T1 to T6.
... A24: 23 | B24: S23 | C24: Jafari Sarvejahani | D24: Towards Architectural Pen Test Case Generation and Attack Surface Analysis to Support Secure Design | E24: 2025 | F24: ICSA-C 2025 | G24: States three research questions and some initial ideas on how to derive penetration test cases from architectural models, how to prioritise the test cases based on their severeness and how to score alternative architectures based on attack-surface complexity, which in turn can be used as inputs to a recommender for the architects. The paper is about work that is proposed not work that has been done. | H24: It is one of three proposed strategies, and the plan will be to first develop a non-model algorithm (over public weaknesses, attack-pattern and vulnerability collections) and, only after the development of the non-model algorithm, consider whether a model can be used to replace parts of the algorithm, or enhance parts of the algorithm; the algorithm to be used as a baseline. | I24: The whole point of it is that it aids architectural design - that is, it takes architectural models as input, returns secure design decisions as output, and the architect is the intended user. The model is also placed at the analysis end of design support, which is the first time in the corpus that it was done instead of the generation end: The architecture is evaluated and rated for architects. | J24: An evaluation strategy is expressed, but no evaluation has been performed for the self-built algorithm (non-model) or against comparable published algorithms in the autonomous-vehicle domain, for accuracy, precision, recall and effectiveness. | K24: F18 | L24: 36 meaning units (10 / 6 / 7 / 8 / 3 / 2) for themes T1 to T6.

Sheet Withdrawn_Studies
A1: Original Corpus ID | B1: Authors | C1: Full title | D1: Year | E1: Family | F1: Units withdrawn | G1: Reason for Exclusion
A2: S10 | B2: Shethiya | C2: LLM-Powered Architectures: Designing the Next Generation of Intelligent Software Systems | D2: 2023 | E2: F17 | F2: 8 | G2: The contribution is an architectural knowledge of a class of LLM based systems and no model carries out any architectural task. It was determined that second limb of criterion "architecture for LLM-based systems" was not considered and adopted, thus the system was withdrawn. This is a scope decision and not a quality judgement. A study without narration, system, case run and evaluation. It outlines architectural patterns to apply LLM in software systems (like RAG, Prompt Chain, Agent Orchestration, Synchronous and Asynchronous Pipelines) and presents a generic reference diagram and governance framework including scope of the model, prompt auditing, bias mitigation, privacy and lifecycle management, all authored by the author. There were 2 scope independent source verified quality defects. No reference to the text: 11 citations, but none of these to the claim they support. The stated issue date is April 2023, which doesn't match the text which says model input limits are 8K to 128K tokens.
A3: S16 | B3: Smirnov, Levashova & Ponomarev | C3: Decision Support Based on Large Language Models: Ontology-based Architecture and Generalized Scenario | D3: 2026 | E3: F12 | F3: 23 | G3: No model does any architectural task, the contribution is architectural knowledge of a class of LLM-based systems. The second limb of criterion for architecture for LLM based systems was discussed but not included. This is a scope decision as opposed to a quality decision, as there are a number of sources in Group C that are the best in the list of candidates and most rich in RQ4. Architectural designs are the work of the human authors; no model does architectural work, all four workflows are designed by the human authors. The one positive row at 1.1 is a modelling of an application domain conceptually (that is, a domain ontology, not software-architecture work) as opposed to the modelling of software-architectures made by S54. During this phase, conceptual models are developed which are not tested empirically, according to the paper. Counted as an external anchor reference for RQ4 and not in total count.
A4: S17 | B4: Santhosh, Baskar & Janani | C4: Intelligent Multi-Agent Architecture Leveraging Large Language Models for Transparent, Interactive Financial Analysis and Strategic Investment Recommendation | D4: 2026 | E4: F13 | F4: 29 | G4: In the financial analysis, application paper. The task object of the model is not a software architecture, but a financial analysis, and a recommendation on investment. There is no architectural task and no architectural contribution in 1.1-1.4, because all the rows are negative in this range.
A5: S18 | B5: Guo, Guo, Li, Huang, Zhu & Zou | C5: Disturbance-Aware Closed-Loop Rescheduling for Airport Ground Operations via LLM-Enhanced Decision Support | D5: 2026 | E5: F14 | F5: 28 | G5: Application paper for the airport ground service. The model's task object is not a software architecture, but a modified schedule for performing the ground operations. There is no positive row in each of 1.1 – 1.4 so there is no architectural task, and no architectural contribution.
A6: S19 | B6: Park, Park & Kim | C6: WildfireKR: An LLM-Agent Decision Support Framework for Autonomous Wildfire Spread Simulation in South Korea | D6: 2026 | E6: F15 | F6: 32 | G6: Application paper: for emergency and environmental modelling. The task object of the model is not the software architecture, but a simulation of the spread of wild fires. There are no positive rows at any of 1.1-1.4 so there is no architectural task and no architectural contribution.
A7: S22 | B7: Sarao | C7: Next-Gen AI Decision Support in Software Engineering: Leveraging Complexity with Quantum Computing, DevOps Automation, and Responsible Machine Learning | D7: 2025 | E7: F19 | F7: 26 | G7: A positive row at position 1.3 (where one application was designed by the authors), however this row is not associated with any architectural work by any model. In such a paper, if the design extends to other contexts and becomes a basis for creating a transferable set of guidance, then this guidance is the result of the building of the system and is not the contribution of that paper.
A8: S23 | B8: Narsepalle, Bolla & Bandaru | C8: A Cloud-Native Generative AI Agent Architecture for Predictive Cardiovascular Health Analytics | D8: 2026 | E8: F20 | F8: 25 | G8: Application paper, a clinical analytical application. The task object for the model is a cardiovascular risk analysis and not a software architecture. There is no architectural task (and no architectural contribution), since there are no positive rows at any of 1.1-1.4.
A9: S24 | B9: Li, Zhang, Zhang, Zhou, Bai, Li, Gu, Li, Du, Li, Chen & Wu | C9: Large Language Model Driven Auxiliary Decision System for Substation Equipment Status Assessment and Technical Retrofit | D9: 2025 | E9: F21 | F9: 25 | G9: Application paper, a clinical analytical application. The task object for the model is a cardiovascular risk analysis and not a software architecture. There is no architectural task (and no architectural contribution), since there are no positive rows at any of 1.1-1.4.
A10: S25 | B10: Lu, Zhu, Xu, Liu, Xing & Whittle | C10: A Taxonomy of Foundation Model based Systems through the Lens of Software Architecture | D10: 2024 | E10: F22 | F10: 38 | G10: The contribution is the knowledge of the architecture of a class of LLM based systems, with no model doing any architectural work. Not adopted due to the second criterion; architecture for LLM based systems, which was considered. None of the models are actually run, the paper itself is a systematic literature review and the result is a classification. All the six positive rows at 1.2 and 1.3 are authors' own catalogue or proposals such as architecture options catalogued, deployment options catalogued along 3 dimensions, an AI bill of materials, a co-versioning registry and standardised reporting. It is on the same area of land as S31, and withdrawn for the same reason. The total will not include counting which will be used as an anchor for RQ4.
A11: S26 | B11: Kumar, Sagar & Jain | C11: Autonomous Multi Agent Collaborators for Enterprise Decision Support: An Agentic AI Framework to Hybrid RAG and Text-to-SQL | D11: 2026 | E11: F23 | F11: 28 | G11: Paper to be used in Enterprise Analytics. The model doesn't represent a software architecture, but rather a business question that is answered by the hybrid retrieval and text-to-SQL model. The row at each of 1.1-1.4 is negative, there is no architectural task and no architectural contribution.
A12: S27 | B12: Becattini, Verdecchia & Vicario | C12: An Accountability-Based Architectural Tactic for Agent Cooperation in LLM-Based Multi-Agent Systems | D12: 2025 | E12: F24 | F12: 33 | G12: No model doing any architectural action, no contribution is an architectural knowledge of a class of systems based on LLM. The second part of the criterion (architecture for LLM-based systems) was taken into account and not adopted. The authors' architecture builds on their own previous architecture and is designed based on the architectural tactic, agent types, relationship types, operating scope, knowledge split and operating layer split. The reported architectural choices of the agents do not contain any output; all architectural constraints in this case study are human Authored (not human chosen) constraints.
A13: S28 | B13: Wu, Guo, Luo & Zhou | C13: Zero-Shot Autonomous Dialogue Agent for Efficient Electric Power Data Inquiry | D13: 2025 | E13: F25 | F13: 27 | G13: Form to be filled out to gain access to a set of data. The task object and response of the model is in natural language (data query) instead of software architecture. There is no architectural task and no architectural contribution for any positive row at any of 1.1-1.4.
... A36: S58 | B36: Klot, Dordevic, Tsaramirsis & Nassereddine | C36: Goal-Based Multi-Agent AI Systems for Academic Advising: A Survey of Policies, Risk Detection, and Intervention Frameworks | D36: 2026 | E36: F51 | F36: 9 | G36: No Model used and no evaluation reported. Architecture content is the property of the authors. They present in Section VI an Academic Multi-Agent Advising System (AMAS), which they describe as a multi-agent, goal-driven and governance-aware system. It consists of five agents: a Student Context Agent that maintains the context of the student, a Risk Detection Agent that predicts risk of course failure, probation or dropout, a Policy and Compliance Agent that compares recommendations to prerequisites, credit limits and probation rules, a Goal and Planning Agent that creates multi-semester plans, and an Intervention Agent that identifies nudges, advisor alerts, referrals and timetable adjustments. Taxonomy is appended to the Table II, which categorizes the advising systems based on goals representation, planning horizon, risk awareness, autonomy in intervention and governance. Two reasons were given for excluding the paper. First, all agents play a part in the tasks of academic advising, or student risk, progression plans and interventions and not a software architecture. No architectural task is performed by any model and no model is specified to perform an architectural task. Second, the architecture and the taxonomy are architectural knowledge about a class of AI-based systems, authored by the researchers.

Sheet Thematic_Map
A1: Study | B1: Year | C1: Meaning unit | D1: Code | E1: Sub-theme | F1: Theme | G1: Trend signal | H1: Source | I1: Row type | J1: Approach/Type
A2: S2 | B2: 2025 | C2: What is being exercised here is the "decision" that was made about already existing microservices architectures, e.g. the two retrospective cases replay decisions that have been made and compare the answers of the model with what was actually implemented. | D2: Decision support assessed on the created systems, not on the generation of the architecture. | E2: 1.1 Architecture generation and synthesis from requirements | F2: T1. LLMs Application / Usage for Architecture Design | H2: Section 1, Section 2, Section 3 | I2: Related activity | J2: T1: design production (1.1-1.3)
A3: S1 | B3: 2024 | C3: The approach is applicable to an architecture that the architect is designing. The pattern of the persona instructs the model to concentrate on named qualities, the pattern of the question is to question the architect before giving answers, and what returns is suggestions with justifications. | D3: No suggestions generated in a decision dialogue. | E3: 1.1 Architecture generation and synthesis from requirements | F3: T1. LLMs Application / Usage for Architecture Design | H3: Section 3-Section 7, Known Uses | I3: Related activity | J3: T1: design production (1.1-1.3)
A4: S3 | B4: 2025 | C4: A textual requirement is given with a short description of the corresponding system and the design agents generate design solutions independently from one another, with the result of each agent trajectory being a solution, and the results being summarised, ranked and presented to the user. | D4: Agent produces ranked design solutions from text requirements. | E4: 1.1 Architecture generation and synthesis from requirements | F4: T1. LLMs Application / Usage for Architecture Design | H4: Section III, Figure 3 | I4: Evidenced | J4: T1: design production (1.1-1.3)
A5: S5 | B5: 2025 | C5: The study is asking what the model already knows about an existing system in terms of the architecture and comparing it to a ground truth. Nothing here produces an architecture, it is a general capacity of language models to show up in the introduction and as other people's work in related work. | D5: If there is information in the model, it is recalled and nothing is created. | E5: 1.1 Architecture generation and synthesis from requirements | F5: T1. LLMs Application / Usage for Architecture Design | H5: Section I, Section II | I5: Related activity | J5: T1: design production (1.1-1.3)
A6: S4 | B6: 2024 | C6: The generation task is the Decision of an architecture decision record that was created from the Context of that record. | D6: The object produced is a decision field, and not an architecture. | E6: 1.1 Architecture generation and synthesis from requirements | F6: T1. LLMs Application / Usage for Architecture Design | H6: Section I, Section III | I6: Related activity | J6: T1: design production (1.1-1.3)
A7: S6 | B7: 2025 | C7: From a requirements specification, a set of four UML design diagram types (use case, class, sequence and state) are generated, and the output is requested to be in a textual diagram-markup format, which can be used to render the design diagrams by standard diagramming tools. | D7: A collection of four UML diagram types that have been created from a requirements document. | E7: 1.1 Architecture generation and synthesis from requirements | F7: T1. LLMs Application / Usage for Architecture Design | H7: Section I, Section VII, Section VIII | I7: Evidenced | J7: T1: design production (1.1-1.3)
A8: S6 | B8: 2025 | C8: The requirements were pre-processed before prompting, where the functionality of the product and its requirements in the specification were summarised into functional categories and the content of these were used as the prompt. Neither is it a step spelled out in an imperative nor is it a step that is attributed to a person. | D8: Requirements summarized into functional categories and not prompted. | E8: 1.1 Architecture generation and synthesis from requirements | F8: T1. LLMs Application / Usage for Architecture Design | H8: Section VII, Table II | I8: Evidenced | J8: T1: design production (1.1-1.3)
A9: S6 | B9: 2025 | C9: All four produced the same type of diagrams which were the same as the reference, with reported similarity scores of 0.61 for use case, 0.61 for class, 0.66 for sequence and 0.7 for state. | D9: Partial match for any of the four diagram types | E9: 1.1 Architecture generation and synthesis from requirements | F9: T1. LLMs Application / Usage for Architecture Design | H9: Section X, Table III | I9: Evidenced | J9: T1: design production (1.1-1.3)
A10: S7 | B10: 2024 | C10: A proposed process is six steps: generate a domain model from the textual requirements and automatically generate use-case scenarios, manually edit both of these, automatically generate multiple architecture candidates and design decisions, automatically assess the candidates, manually edit the candidates, and then manually select the best fit. | D10: Requirements to selected architecture pipeline is shown as a 6-step process. The 6-step pipeline from requirements to selected architecture is demonstrated. | E10: 1.1 Architecture generation and synthesis from requirements | F10: T1. LLMs Application / Usage for Architecture Design | H10: Section 3, Figure 1 | I10: Evidenced | J10: T1: design production (1.1-1.3)
A11: S7 | B11: 2024 | C11: The authors contrast this with Kof's previous semi-automatic domain model generation, which demanded significant manual work to draft the requirements documents, and conclude that recently developed LLMs can significantly decrease that manual work. | D11: Located as the answer to manual effort compared to previous semi-automatic tasks | E11: 1.1 Architecture generation and synthesis from requirements | F11: T1. LLMs Application / Usage for Architecture Design | H11: Section 1, Section 2 | I11: Evidenced | J11: T1: design production (1.1-1.3)
A12: S8 | B12: 2024 | C12: The end-to-end scenarios are scenarios that are selected and passed through the copilot pipeline and the output is a set of sixteen architecture decision records. | D12: Requirements should be passed down to decision records, not an architecture. | E12: 1.1 Architecture generation and synthesis from requirements | F12: T1. LLMs Application / Usage for Architecture Design | H12: Section 3.1, Section 4 | I12: Related activity | J12: T1: design production (1.1-1.3)
A13: S9 | B13: 2024 | C13: One of six proposed query templates, Candidate Architecture, is designed to create a candidate architecture for a new system that is similar to an existing, documented one, but is not meant to be used to extract knowledge about a documented system. | D13: One type of query template suggests generating candidate architectures for new systems | E13: 1.1 Architecture generation and synthesis from requirements | F13: T1. LLMs Application / Usage for Architecture Design | H13: Section IV-B | I13: Evidenced | J13: T1: design production (1.1-1.3)
... A495: S16 | B495: 2025 | C495: Absence: No model is specified and no cost, latency, or configuration value is provided anywhere in the entire paper, or indeed anywhere in the three case studies. The generative model is described as an LLM agent consistently in the paper, but no model, version, provider, temperature, context setting, token count, cost, or call count appears anywhere in the paper, nor in the three case studies. The single piece of cost-related information provided in the paper is explicitly qualitative and not quantitative, the caption noting that the trendlines shown do not provide actual quantitative values. | D495: Absence: No model named and no cost, latency or reproducibility figure is found anywhere. | E495: 3.3 Cost, latency and reproducibility of the reported setups | F495: T3. Techniques for Evaluation | H495: Sections IV-B, V, VI-B, Figure 10 caption; would have appeared in Section V | I495: Coded silence | J495: T3: evaluation technique
A497: S1 | B497: 2024 | C497: The contribution lies in a chain of prompting with conditional branches and an evaluation gate following each prompt, instead of a single prompt. | D497: Multi-step conditional chain is an alternative to single-prompt use. | E497: 4.1 From single-prompt assistance towards agentic and multi-agent architecting | F497: T4. Emerging Trends | G497: No signal | H497: Section 8, Section 8.1 | I497: Evidenced | J497: T4: emerging trend
A498: S2 | B498: 2025 | C498: The two architects independently request that the fixed sequence be changed to an interactive dialogue with further questions and the authors agree in their future work with respect to this, suggesting a departure from the idea of a fixed prompt sequence. | D498: Fixed sequence moved in direction of interactive dialogue | E498: 4.1 From single-prompt assistance towards agentic and multi-agent architecting | F498: T4. Emerging Trends | G498: Explicit | H498: Section 5, Section 6 | I498: Evidenced | J498: T4: emerging trend
A499: S3 | B499: 2025 | C499: The framework used by the authors is that current architectural work is based on fixed-model prompting and is lagging behind code agents, and that architectural tools need to be transformed into design agents which will have autonomy and tool usage, multiple agents working together to address different needs being mentioned as the next step. | D499: Stand alone prompting replaced by design agents | E499: 4.1 From single-prompt assistance towards agentic and multi-agent architecting | F499: T4. Emerging Trends | G499: Explicit | H499: Section I, Section V, Section VI | I499: Evidenced | J499: T4: emerging trend
A500: S6 | B500: 2025 | C500: Absence: A single assistant takes care of prompts in an editor. There is no mention of any agent, orchestration or delegation. | D500: Absence: An absence of agency, multi-agency direction | E500: 4.1 From single-prompt assistance towards agentic and multi-agent architecting | F500: T4. Emerging Trends | G500: No signal | H500: whole paper | I500: Coded silence | J500: T4: emerging trend
A501: S5 | B501: 2025 | C501: Absence: the study invokes one model through an API. There is no mention of an agent, tool use, delegation or orchestration in either the study or the directions the authors lay out. | D501: Absence: No control or agency by one or more agents | E501: 4.1 From single-prompt assistance towards agentic and multi-agent architecting | F501: T4. Emerging Trends | G501: No signal | H501: whole paper | I501: Coded silence | J501: T4: emerging trend
A502: S4 | B502: 2024 | C502: Absence: all configurations consist of a single model invocation per record. There is no mention of an agent, tool use, orchestration or delegation in either the study or the directions the authors indicate their work is heading toward. | D502: Absence: No agentic or multi-agent direction | E502: 4.1 From single-prompt assistance towards agentic and multi-agent architecting | F502: T4. Emerging Trends | G502: No signal | H502: whole paper | I502: Coded silence | J502: T4: emerging trend
A503: S7 | B503: 2024 | C503: It is proposed that the proposed process explicitly alternates automatic generation and manual refinement over three stages (the domain model, architecture candidates and final selection) instead of generating an architecture from one invocation. | D503: Three stages of explicitly interleaved generation and human refinement. | E503: 4.1 From single-prompt assistance towards agentic and multi-agent architecting | F503: T4. Emerging Trends | G503: Explicit | H503: Section 3, Figure 1 | I503: Evidenced | J503: T4: emerging trend
A504: S8 | B504: 2024 | C504: The pipeline consists of a four-step protocol with task-specialized copilots, optionally with a question-and-answer task, conducted by a senior architect who can intervene at certain points to provide input or refine output. This is a set process instead of agents which can plan and delegate, and the authors describe the tool as experimental and not heading toward autonomy. | D504: A human intervention points-based fixed task pipeline, not Autonomous agents | E504: 4.1 From single-prompt assistance towards agentic and multi-agent architecting | F504: T4. Emerging Trends | G504: Explicit | H504: Section 3.1, Section 3.3 | I504: Related activity | J504: T4: emerging trend
A505: S9 | B505: 2024 | C505: Unlike the generative approach taken by the existing systems, the suggested system is built around the concept of two chained processes - extraction and retrieval, with the former broken down into four separate sub-processes executed by different components. | D505: The whole system was carefully broken into sequential multi-step process.The overall system was carefully divided into cascaded multi-step processes. | E505: 4.1 From single-prompt assistance towards agentic and multi-agent architecting | F505: T4. Emerging Trends | G505: Explicit | H505: Section IV, Figure 1, Figure 2 | I505: Evidenced | J505: T4: emerging trend
A506: S10 | B506: 2024 | C506: Absence: In both controlled experiments and the survey there is no mention of agents, orchestration or delegation; none of those is included in the list of future expectations asked about in a research aimed at recording the existing practices and expectations for the future. | D506: Absence: no agentic or multiple agentic direction | E506: 4.1 From single-prompt assistance towards agentic and multi-agent architecting | F506: T4. Emerging Trends | G506: No signal | H506: whole paper | I506: Coded silence | J506: T4: emerging trend
A507: S11 | B507: 2023 | C507: The collaboration suggested by the authors is based on three separate processes of architecting (analysis, synthesis and evaluation), which have been borrowed from the architecting process, developed on the basis of five industrial approaches, and performed as separate steps of one single dialogue, rather than a generative request. | D507: A process was broken down to three sequential architecting activities. | E507: 4.1 From single-prompt assistance towards agentic and multi-agent architecting | F507: T4. Emerging Trends | G507: Explicit | H507: Section 2.1, Section 2.2, Figure 2, Figure 3 | I507: Evidenced | J507: T4: emerging trend
A508: S11 | B508: 2023 | C508: According to the authors, within the domain of software architecting the application of AI technologies in general and development bots in particular has been reduced only to answering questions or providing recommendations concerning erosion and maintenance of architectures, and there is no research studying the application of these bots in the architecting process. | D508: The authors mention that current bots are limited to the question and answer/Recommendation area. | E508: 4.1 From single-prompt assistance towards agentic and multi-agent architecting | F508: T4. Emerging Trends | G508: Explicit | H508: Section 2.1 | I508: Evidenced | J508: T4: emerging trend
... A670: S23 | B670: 2025 | C670: Absence: lack of governance of the generated artifact: it is unclear who reviews the generated attack scenario by the model before the architect acts on it and what will happen if the rating is incorrect. | D670: Absence: No monitoring or assurance of attack scenarios generated by a model | E670: 4.5 Trust, governance and responsible adoption in industrial settings | F670: T4. Emerging Trends | G670: No signal | H670: whole paper | I670: Coded silence | J670: T4: emerging trend
A671: S3 | B671: 2025 | C671: Limitations of the approach that are identified in the Discussion include three. Some of the recommendations obtained by the agents are not patterns or tactics found in the literature; they are referred to as hallucinations. The recommendations have been identified as being too generic, while coping with both of these problems remains difficult. The value of the approach is stated to depend on its tools being based on the proper architectural knowledge, while the validation of this approach by means of practical experiments and metrics is seen as essential for its improvement. Two additional problems with the run in question – duplication of the patterns that increase the burden of inference and the failure of the tree search agent to use its decision assessment tool – are marked by the codes 3.3 and 5.2 respectively. | D671: Hallucinated options, over-general recommendations and a grounding dependence | E671: 5.1 Reported limitations in practice | F671: T5. Limitations | H671: Section IV, Discussion; Section IV results | I671: Evidenced | J671: T5: limitation
A672: S14 | B672: 2026 | C672: Absence: There is no limitation in practice observed. The article claims that there is a significant F1 improvement over its industrial baseline, and there are significant benefits of dependency context; however, the article does not note any specific conditions, costs, and failures of its approach except for these two. | D672: Absence: (no limitations reported) next to the measured gains | E672: 5.1 Reported limitations in practice | F672: T5. Limitations | H672: whole paper | I672: Coded silence | J672: T5: limitation
A673: S1 | B673: 2024 | C673: Among the drawbacks noted are prolonged planning period, delay of time-sensitive projects, increase in the cognitive load, and scope creep in case multiple quality attributes are targeted at the same time. | D673: Structured prompting slows and complicates decision process. | E673: 5.1 Reported limitations in practice | F673: T5. Limitations | H673: Section 5, Section 6 Consequences | I673: Evidenced | J673: T5: limitation
A674: S1 | B674: 2024 | C674: The persona is noted to potentially introduce unintentional bias and to limit response flexibility in case the constraints are defined too strictly. | D674: Over-constrained persona presents bias and rigidity. | E674: 5.1 Reported limitations in practice | F674: T5. Limitations | H674: Section 3 | I674: Evidenced | J674: T5: limitation
A675: S1 | B675: 2024 | C675: The Architectural Project Context pattern demonstrated low flexibility under different project contexts, especially in case of pharmacy retail domain, and possibly requires removal of its variables. | D675: Unfortunately, context transfer is not that good between projects. | E675: 5.1 Reported limitations in practice | F675: T5. Limitations | H675: Section 4 Known Uses | I675: Evidenced | J675: T5: limitation
A676: S2 | B676: 2025 | C676: It was noticed by architects that in some cases, the model would provide general or too broad recommendations failing to provide necessary specificity for highly complex technical environments. Concrete examples were provided by the pharmacy architect who needed the test types to be specified, and also expected the use of Kubernetes for management and scaling. | D676: The suggested resources or tools are not specific enough for complex environments. | E676: 5.1 Reported limitations in practice | F676: T5. Limitations | H676: Section 4.2, Section 5 | I676: Evidenced | J676: T5: limitation
A677: S2 | B677: 2025 | C677: There were two concrete problems noted in the practical use of the model: the recommendation of micro front-ends without prior questioning of the backend configuration, and the underestimation of implementation time compared to the needs of the project. | D677: General failures: lack of focus, unrealistic goals, lack of commitment, lack of drive. | E677: 5.1 Reported limitations in practice | F677: T5. Limitations | H677: Section 4.1, Section 4.2 | I677: Evidenced | J677: T5: limitation
A678: S2 | B678: 2025 | C678: The authors note that results should be interpreted in the context of microservices because of the numerous publications on that topic that helped to train the model and probably explain the correctness of its responses. | D678: Abundant training material seemed to be a part of the reason for good performance. | E678: 5.1 Reported limitations in practice | F678: T5. Limitations | H678: Section 5 Limitations | I678: Evidenced | J678: T5: limitation
A679: S4 | B679: 2024 | C679: All of the three output methods fall short of human-level output; the best 0-shot model provides correct formatting but not the full decision. | D679: Not quite human, but format adherence achieved; decision content Sub-human. | E679: 5.1 Reported limitations in practice | F679: T5. Limitations | H679: Section V-A, Section VI-A | I679: Evidenced | J679: T5: limitation
A680: S4 | B680: 2024 | C680: The most accurate models, according to the paper, are cloud service models; hence, their use requires transmission of data from the project to a third party, which, according to the authors, poses issues with privacy, intellectual property rights and legality. | D680: With the cloud-only strong models, there are concerns about data transmission. | E680: 5.1 Reported limitations in practice | F680: T5. Limitations | H680: Section VI-A | I680: Evidenced | J680: T5: limitation
A681: S5 | B681: 2025 | C681: In all three concepts, the recall values are higher than precision values (recall value of 0.594 as compared to a precision value of 0.395), which suggests that the model returns a large number of possible concepts but most are incorrect. | D681: Recall is greater than precision; model is more inclusive | E681: 5.1 Reported limitations in practice | F681: T5. Limitations | H681: Section III-A, Table III | I681: Evidenced | J681: T5: limitation
A682: S5 | B682: 2025 | C682: Accuracy varies greatly between the knowledge concepts and within them; precision for components and connectors is significantly higher than that of quality solutions and rationale, and precision for the security knowledge attribute is significantly higher than that of performance and maintainability. | D682: There is a great deal of variability across knowledge concepts and attributes when it comes to accuracy | E682: 5.1 Reported limitations in practice | F682: T5. Limitations | H682: Section III-A, Section III-C, Figs 3 & 5 | I682: Evidenced | J682: T5: limitation
... A765: S23 | B765: 2025 | C765: Absence: There is no discussion of hallucinations, lack of determinism and reproducibility despite the fact that the suggested solution is supposed to generate attack paths for safety-critical systems, and any imaginary attack path will make testers or architects chase a phantom vulnerability. | D765: Individuals with no treatment for either hallucination or non-determinism.Hallucination and non-determinism no treatment. | E765: 5.2 Reported reliability problems: hallucination, inconsistency, non-determinism | F765: T5. Limitations | H765: whole paper | I765: Coded silence | J765: T5: limitation
A767: S1 | B767: 2024 | C767: Loss of criticality due to dependence on generative solutions is given as a current threat, and the need to validate any technical assumptions generated by AI against the actual project context is seen as a key requirement. | D767: Over-reliance and unvalidated assumptions identified as unaddressed risks | E767: 6.1 Open challenges and stated future work | F767: T6. Challenges | G767: Explicit | H767: Section 9 | I767: Evidenced | J767: T6: challenge
A768: S1 | B768: 2024 | C768: The authors mention that AI can give results which are technically correct but inappropriate for the actual task without human input. | D768: Correct - but not applicable output as an unsolved problem | E768: 6.1 Open challenges and stated future work | F768: T6. Challenges | G768: Explicit | H768: Section 9 | I768: Evidenced | J768: T6: challenge
A769: S2 | B769: 2025 | C769: Future work, according to the authors, includes adding more interactivity to the process, customization to particular project cases, and testing in relation to architectural styles other than microservices. | D769: Future work: interactivity, other architectural styles | E769: 6.1 Open challenges and stated future work | F769: T6. Challenges | G769: Explicit | H769: Section 6 | I769: Evidenced | J769: T6: challenge
A770: S3 | B770: 2025 | C770: Hallucinations and broad guidelines are identified as still remaining challenges, and future work has four components – user intervention opportunities, coordination among multiple agents that would make ATAM evaluation possible, integration with existing methodologies and solvers, and retrieval augmentation. | D770: The overall structure of the agenda is as follows: interaction, multi-agent, methods, grounding. | E770: 6.1 Open challenges and stated future work | F770: T6. Challenges | G770: Explicit | H770: Section IV, Section VI | I770: Evidenced | J770: T6: challenge
A771: S4 | B771: 2024 | C771: As of early 2024, the authors claim that software architecture has been relatively unaffected by generative AI, and that, as far as they know, no previous research has generated design decisions using such models, which serves as a convenient starting point to date the development path of the field. | D771: In early-2024, it was claimed that much of the area was unexplored. | E771: 6.1 Open challenges and stated future work | F771: T6. Challenges | G771: Explicit | H771: Section III | I771: Evidenced | J771: T6: challenge
A772: S4 | B772: 2024 | C772: Future work that the authors mention includes the fine-tuning of larger models to generate at human levels, as well as providing more knowledge through retrieval and other means such as design diagrams and codebase, and conducting live experiments with architects; standardized adoption is claimed as being out of reach yet. | D772: Bigger, richer, live studies: agenda. | E772: 6.1 Open challenges and stated future work | F772: T6. Challenges | G772: Explicit | H772: Abstract, Section VIII | I772: Evidenced | J772: T6: challenge
A773: S5 | B773: 2025 | C773: They claim that there are no previous studies empirically testing these models on architectural knowledge of an existing system, and thus offer their results as a first baseline for further improvement. | D773: This evaluation task is located on the first baseline. | E773: 6.1 Open challenges and stated future work | F773: T6. Challenges | G773: Explicit | H773: Section I, Section VII | I773: Evidenced | J773: T6: challenge
A774: S5 | B774: 2025 | C774: Future work is mentioned as repeating the evaluation using other architectures and training data sets, along with developing new methods and tools to increase accuracy when dealing with architectural questions. | D774: Model: more models; accuracy improving tooling: accuracy improving. | E774: 6.1 Open challenges and stated future work | F774: T6. Challenges | G774: Explicit | H774: Section VIII | I774: Evidenced | J774: T6: challenge
A775: S6 | B775: 2025 | C775: This future work agenda contains four points: repeating the comparison in another field, employing more sophisticated techniques in prompt engineering, comparing different vendor models based on the same similarity metric, and creating a specialized model for software architecture. | D775: The primary idea of Agenda is to provide other domains, use better prompts, cross-vendor support, and custom model. | E775: 6.1 Open challenges and stated future work | F775: T6. Challenges | G775: Explicit | H775: Section XI, Section XII | I775: Evidenced | J775: T6: challenge
A776: S6 | B776: 2025 | C776: The related work mentions a prior result in which the particular version of the general chat model investigated there was shown to be less capable at software architecture tasks compared to software development tasks. | D776: Prior work cited reporting architecture lags code performance | E776: 6.1 Open challenges and stated future work | F776: T6. Challenges | G776: Explicit | H776: Section II | I776: Evidenced | J776: T6: challenge
A777: S7 | B777: 2024 | C777: There are four clear, numbered research questions, stated as the evaluation roadmap of the paper and all are still open as of now: Is the current NLP technology capable of creating reproducible, accurate domain models? Can architectures be created which appropriately meet the requirements? Can evaluation and trade-offs be automated? Will the entire approach increase quality while decreasing time? | D777: The whole agenda is framed with four explicit open research questions | E777: 6.1 Open challenges and stated future work | F777: T6. Challenges | G777: Explicit | H777: Section 1 | I777: Evidenced | J777: T6: challenge
A778: S7 | B778: 2024 | C778: The paper clearly states itself to be a vision paper outlining a process and research roadmap, and presents the planned reference-architecture and industrial field studies as future work, not results. | D778: Explicitly stated in the form of a vision paper; results are future work | E778: 6.1 Open challenges and stated future work | F778: T6. Challenges | G778: Explicit | H778: Abstract, Section 5, Section 6 | I778: Evidenced | J778: T6: challenge
... A805: S23 | B805: 2025 | C805: Two questions are assumed as prerequisites (whether there is enough information in architectural models for generating test cases and whether language models are able to contribute to this) and are identified as independent research directions. | D805: These are two feasibility questions, NOT assumptions, which are carried along. | E805: 6.1 Open challenges and stated future work | F805: T6. Challenges | G805: Explicit | H805: Section IV-A RQ1; Section IV-B Strategy 2 | I805: Evidenced | J805: T6: challenge

Sheet Themes_Overview
A1: Theme (and RQ answered) | B1: Sub-themes | C1: Meaning units | D1: Evidenced | E1: Coded silences | F1: Related activity | G1: Studies (evidentiary) | H1: Independent families | I1: Study | J1: Units in T1 | K1: Units in T2 | L1: Units in T3 | M1: Units in T4 | N1: Units in T5 | O1: Units in T6 | P1: Total
A2: T1. LLMs Application / Usage for Architecture Design (RQ1) | B2: • 1.1 Generation of architecture and requirements synthesis • 1.2 Support in design decisions; tactic, pattern and technology suggestions • 1.3 Architecture documentation, rationale capture and design records • 1.4 Analysis of architecture, recovery, smell detection and conformence • 1.5 The role given to the model: assistant, autonomous agent, or co-designer • 1.6 Benefits reported in practice | C2: =COUNTIFS(Thematic_Map!$F$2:$F$805,LEFT($A2,2)&"*",Thematic_Map!$I$2:$I$805,"<>") -> 218 | D2: =COUNTIFS(Thematic_Map!$F$2:$F$805,LEFT($A2,2)&"*",Thematic_Map!$I$2:$I$805,"Evidenced") -> 167 | E2: =COUNTIFS(Thematic_Map!$F$2:$F$805,LEFT($A2,2)&"*",Thematic_Map!$I$2:$I$805,"Coded silence") -> 7 | F2: =COUNTIFS(Thematic_Map!$F$2:$F$805,LEFT($A2,2)&"*",Thematic_Map!$I$2:$I$805,"Related activity") -> 44 | G2: =SUMPRODUCT((COUNTIFS(Thematic_Map!$A$2:$A$805,$I$2:$I$24,Thematic_Map!$F$2:$F$805,LEFT($A2,2)&"*",Thematic_Map!$I$2:$I$805,"Evidenced")>0)*1) -> 23 | H2: 20 | I2: S1 | J2: =COUNTIFS(Thematic_Map!$A$2:$A$805,$I2,Thematic_Map!$F$2:$F$805,"T1*",Thematic_Map!$I$2:$I$805,"<>") -> 11 | K2: =COUNTIFS(Thematic_Map!$A$2:$A$805,$I2,Thematic_Map!$F$2:$F$805,"T2*",Thematic_Map!$I$2:$I$805,"<>") -> 7 | L2: =COUNTIFS(Thematic_Map!$A$2:$A$805,$I2,Thematic_Map!$F$2:$F$805,"T3*",Thematic_Map!$I$2:$I$805,"<>") -> 5 | M2: =COUNTIFS(Thematic_Map!$A$2:$A$805,$I2,Thematic_Map!$F$2:$F$805,"T4*",Thematic_Map!$I$2:$I$805,"<>") -> 6 | N2: =COUNTIFS(Thematic_Map!$A$2:$A$805,$I2,Thematic_Map!$F$2:$F$805,"T5*",Thematic_Map!$I$2:$I$805,"<>") -> 6 | O2: =COUNTIFS(Thematic_Map!$A$2:$A$805,$I2,Thematic_Map!$F$2:$F$805,"T6*",Thematic_Map!$I$2:$I$805,"<>") -> 2 | P2: =SUM(J2:O2) -> 37
A3: T2. Techniques for Optimization (RQ2) | B3: • 2.1 Strategies for prompting; few-shot, chain-of-thought, role and self-refinement • 2.2 Grounding for knowledge; knowledge graphs, RAG and architecture repositories • 2.3 Model adaptation, fine-tuning, and multi-agent orchestration | C3: =COUNTIFS(Thematic_Map!$F$2:$F$805,LEFT($A3,2)&"*",Thematic_Map!$I$2:$I$805,"<>") -> 129 | D3: =COUNTIFS(Thematic_Map!$F$2:$F$805,LEFT($A3,2)&"*",Thematic_Map!$I$2:$I$805,"Evidenced") -> 96 | E3: =COUNTIFS(Thematic_Map!$F$2:$F$805,LEFT($A3,2)&"*",Thematic_Map!$I$2:$I$805,"Coded silence") -> 32 | F3: =COUNTIFS(Thematic_Map!$F$2:$F$805,LEFT($A3,2)&"*",Thematic_Map!$I$2:$I$805,"Related activity") -> 1 | G3: =SUMPRODUCT((COUNTIFS(Thematic_Map!$A$2:$A$805,$I$2:$I$24,Thematic_Map!$F$2:$F$805,LEFT($A3,2)&"*",Thematic_Map!$I$2:$I$805,"Evidenced")>0)*1) -> 23 | H3: 20 | I3: S2 | J3: =COUNTIFS(Thematic_Map!$A$2:$A$805,$I3,Thematic_Map!$F$2:$F$805,"T1*",Thematic_Map!$I$2:$I$805,"<>") -> 9 | K3: =COUNTIFS(Thematic_Map!$A$2:$A$805,$I3,Thematic_Map!$F$2:$F$805,"T2*",Thematic_Map!$I$2:$I$805,"<>") -> 5 | L3: =COUNTIFS(Thematic_Map!$A$2:$A$805,$I3,Thematic_Map!$F$2:$F$805,"T3*",Thematic_Map!$I$2:$I$805,"<>") -> 7 | M3: =COUNTIFS(Thematic_Map!$A$2:$A$805,$I3,Thematic_Map!$F$2:$F$805,"T4*",Thematic_Map!$I$2:$I$805,"<>") -> 5 | N3: =COUNTIFS(Thematic_Map!$A$2:$A$805,$I3,Thematic_Map!$F$2:$F$805,"T5*",Thematic_Map!$I$2:$I$805,"<>") -> 5 | O3: =COUNTIFS(Thematic_Map!$A$2:$A$805,$I3,Thematic_Map!$F$2:$F$805,"T6*",Thematic_Map!$I$2:$I$805,"<>") -> 1 | P3: =SUM(J3:O3) -> 32
A4: T3. Techniques for Evaluation (RQ2) | B4: • 3.1 Designs for evaluation; case studies, benchmarks, expert judgement, and experiments • 3.2 Quality criteria and Metrics used to judge the generated architectures • 3.3 Latency, cost, and reproducibility of the reported setups | C4: =COUNTIFS(Thematic_Map!$F$2:$F$805,LEFT($A4,2)&"*",Thematic_Map!$I$2:$I$805,"<>") -> 137 | D4: =COUNTIFS(Thematic_Map!$F$2:$F$805,LEFT($A4,2)&"*",Thematic_Map!$I$2:$I$805,"Evidenced") -> 105 | E4: =COUNTIFS(Thematic_Map!$F$2:$F$805,LEFT($A4,2)&"*",Thematic_Map!$I$2:$I$805,"Coded silence") -> 30 | F4: =COUNTIFS(Thematic_Map!$F$2:$F$805,LEFT($A4,2)&"*",Thematic_Map!$I$2:$I$805,"Related activity") -> 2 | G4: =SUMPRODUCT((COUNTIFS(Thematic_Map!$A$2:$A$805,$I$2:$I$24,Thematic_Map!$F$2:$F$805,LEFT($A4,2)&"*",Thematic_Map!$I$2:$I$805,"Evidenced")>0)*1) -> 22 | H4: 20 | I4: S3 | J4: =COUNTIFS(Thematic_Map!$A$2:$A$805,$I4,Thematic_Map!$F$2:$F$805,"T1*",Thematic_Map!$I$2:$I$805,"<>") -> 8 | K4: =COUNTIFS(Thematic_Map!$A$2:$A$805,$I4,Thematic_Map!$F$2:$F$805,"T2*",Thematic_Map!$I$2:$I$805,"<>") -> 4 | L4: =COUNTIFS(Thematic_Map!$A$2:$A$805,$I4,Thematic_Map!$F$2:$F$805,"T3*",Thematic_Map!$I$2:$I$805,"<>") -> 6 | M4: =COUNTIFS(Thematic_Map!$A$2:$A$805,$I4,Thematic_Map!$F$2:$F$805,"T4*",Thematic_Map!$I$2:$I$805,"<>") -> 6 | N4: =COUNTIFS(Thematic_Map!$A$2:$A$805,$I4,Thematic_Map!$F$2:$F$805,"T5*",Thematic_Map!$I$2:$I$805,"<>") -> 4 | O4: =COUNTIFS(Thematic_Map!$A$2:$A$805,$I4,Thematic_Map!$F$2:$F$805,"T6*",Thematic_Map!$I$2:$I$805,"<>") -> 1 | P4: =SUM(J4:O4) -> 29
A5: T4. Emerging Trends (RQ3) | B5: • 4.1 From assistance of single prompt towards agentic and multi-agent architecting • 4.2 Integration with formal artefact generation and model-driven engineering • 4.3 Changing role of the architect and Human-AI collaboration • 4.4 Movement from assistance from design-time towards runtime and continuous architecting • 4.5 Goverance, trust and responsible adoption in industrial settings | C5: =COUNTIFS(Thematic_Map!$F$2:$F$805,LEFT($A5,2)&"*",Thematic_Map!$I$2:$I$805,"<>") -> 170 | D5: =COUNTIFS(Thematic_Map!$F$2:$F$805,LEFT($A5,2)&"*",Thematic_Map!$I$2:$I$805,"Evidenced") -> 122 | E5: =COUNTIFS(Thematic_Map!$F$2:$F$805,LEFT($A5,2)&"*",Thematic_Map!$I$2:$I$805,"Coded silence") -> 45 | F5: =COUNTIFS(Thematic_Map!$F$2:$F$805,LEFT($A5,2)&"*",Thematic_Map!$I$2:$I$805,"Related activity") -> 3 | G5: =SUMPRODUCT((COUNTIFS(Thematic_Map!$A$2:$A$805,$I$2:$I$24,Thematic_Map!$F$2:$F$805,LEFT($A5,2)&"*",Thematic_Map!$I$2:$I$805,"Evidenced")>0)*1) -> 22 | H5: 19 | I5: S4 | J5: =COUNTIFS(Thematic_Map!$A$2:$A$805,$I5,Thematic_Map!$F$2:$F$805,"T1*",Thematic_Map!$I$2:$I$805,"<>") -> 7 | K5: =COUNTIFS(Thematic_Map!$A$2:$A$805,$I5,Thematic_Map!$F$2:$F$805,"T2*",Thematic_Map!$I$2:$I$805,"<>") -> 7 | L5: =COUNTIFS(Thematic_Map!$A$2:$A$805,$I5,Thematic_Map!$F$2:$F$805,"T3*",Thematic_Map!$I$2:$I$805,"<>") -> 9 | M5: =COUNTIFS(Thematic_Map!$A$2:$A$805,$I5,Thematic_Map!$F$2:$F$805,"T4*",Thematic_Map!$I$2:$I$805,"<>") -> 6 | N5: =COUNTIFS(Thematic_Map!$A$2:$A$805,$I5,Thematic_Map!$F$2:$F$805,"T5*",Thematic_Map!$I$2:$I$805,"<>") -> 3 | O5: =COUNTIFS(Thematic_Map!$A$2:$A$805,$I5,Thematic_Map!$F$2:$F$805,"T6*",Thematic_Map!$I$2:$I$805,"<>") -> 2 | P5: =SUM(J5:O5) -> 34
A6: T5. Limitations (RQ3) | B6: • 5.1 Limitations reported in practice • 5.2 Problems reported about reliability; hallucination, inconsistency, non-determinism | C6: =COUNTIFS(Thematic_Map!$F$2:$F$805,LEFT($A6,2)&"*",Thematic_Map!$I$2:$I$805,"<>") -> 94 | D6: =COUNTIFS(Thematic_Map!$F$2:$F$805,LEFT($A6,2)&"*",Thematic_Map!$I$2:$I$805,"Evidenced") -> 86 | E6: =COUNTIFS(Thematic_Map!$F$2:$F$805,LEFT($A6,2)&"*",Thematic_Map!$I$2:$I$805,"Coded silence") -> 8 | F6: =COUNTIFS(Thematic_Map!$F$2:$F$805,LEFT($A6,2)&"*",Thematic_Map!$I$2:$I$805,"Related activity") -> 0 | G6: =SUMPRODUCT((COUNTIFS(Thematic_Map!$A$2:$A$805,$I$2:$I$24,Thematic_Map!$F$2:$F$805,LEFT($A6,2)&"*",Thematic_Map!$I$2:$I$805,"Evidenced")>0)*1) -> 23 | H6: 20 | I6: S5 | J6: =COUNTIFS(Thematic_Map!$A$2:$A$805,$I6,Thematic_Map!$F$2:$F$805,"T1*",Thematic_Map!$I$2:$I$805,"<>") -> 9 | K6: =COUNTIFS(Thematic_Map!$A$2:$A$805,$I6,Thematic_Map!$F$2:$F$805,"T2*",Thematic_Map!$I$2:$I$805,"<>") -> 4 | L6: =COUNTIFS(Thematic_Map!$A$2:$A$805,$I6,Thematic_Map!$F$2:$F$805,"T3*",Thematic_Map!$I$2:$I$805,"<>") -> 8 | M6: =COUNTIFS(Thematic_Map!$A$2:$A$805,$I6,Thematic_Map!$F$2:$F$805,"T4*",Thematic_Map!$I$2:$I$805,"<>") -> 6 | N6: =COUNTIFS(Thematic_Map!$A$2:$A$805,$I6,Thematic_Map!$F$2:$F$805,"T5*",Thematic_Map!$I$2:$I$805,"<>") -> 7 | O6: =COUNTIFS(Thematic_Map!$A$2:$A$805,$I6,Thematic_Map!$F$2:$F$805,"T6*",Thematic_Map!$I$2:$I$805,"<>") -> 2 | P6: =SUM(J6:O6) -> 36
A7: T6. Challenges (RQ3) | B7: • 6.1 Stated future work and open challenges | C7: =COUNTIFS(Thematic_Map!$F$2:$F$805,LEFT($A7,2)&"*",Thematic_Map!$I$2:$I$805,"<>") -> 39 | D7: =COUNTIFS(Thematic_Map!$F$2:$F$805,LEFT($A7,2)&"*",Thematic_Map!$I$2:$I$805,"Evidenced") -> 37 | E7: =COUNTIFS(Thematic_Map!$F$2:$F$805,LEFT($A7,2)&"*",Thematic_Map!$I$2:$I$805,"Coded silence") -> 2 | F7: =COUNTIFS(Thematic_Map!$F$2:$F$805,LEFT($A7,2)&"*",Thematic_Map!$I$2:$I$805,"Related activity") -> 0 | G7: =SUMPRODUCT((COUNTIFS(Thematic_Map!$A$2:$A$805,$I$2:$I$24,Thematic_Map!$F$2:$F$805,LEFT($A7,2)&"*",Thematic_Map!$I$2:$I$805,"Evidenced")>0)*1) -> 22 | H7: 19 | I7: S6 | J7: =COUNTIFS(Thematic_Map!$A$2:$A$805,$I7,Thematic_Map!$F$2:$F$805,"T1*",Thematic_Map!$I$2:$I$805,"<>") -> 8 | K7: =COUNTIFS(Thematic_Map!$A$2:$A$805,$I7,Thematic_Map!$F$2:$F$805,"T2*",Thematic_Map!$I$2:$I$805,"<>") -> 3 | L7: =COUNTIFS(Thematic_Map!$A$2:$A$805,$I7,Thematic_Map!$F$2:$F$805,"T3*",Thematic_Map!$I$2:$I$805,"<>") -> 6 | M7: =COUNTIFS(Thematic_Map!$A$2:$A$805,$I7,Thematic_Map!$F$2:$F$805,"T4*",Thematic_Map!$I$2:$I$805,"<>") -> 6 | N7: =COUNTIFS(Thematic_Map!$A$2:$A$805,$I7,Thematic_Map!$F$2:$F$805,"T5*",Thematic_Map!$I$2:$I$805,"<>") -> 3 | O7: =COUNTIFS(Thematic_Map!$A$2:$A$805,$I7,Thematic_Map!$F$2:$F$805,"T6*",Thematic_Map!$I$2:$I$805,"<>") -> 2 | P7: =SUM(J7:O7) -> 28
I8: S7 | J8: =COUNTIFS(Thematic_Map!$A$2:$A$805,$I8,Thematic_Map!$F$2:$F$805,"T1*",Thematic_Map!$I$2:$I$805,"<>") -> 8 | K8: =COUNTIFS(Thematic_Map!$A$2:$A$805,$I8,Thematic_Map!$F$2:$F$805,"T2*",Thematic_Map!$I$2:$I$805,"<>") -> 4 | L8: =COUNTIFS(Thematic_Map!$A$2:$A$805,$I8,Thematic_Map!$F$2:$F$805,"T3*",Thematic_Map!$I$2:$I$805,"<>") -> 4 | M8: =COUNTIFS(Thematic_Map!$A$2:$A$805,$I8,Thematic_Map!$F$2:$F$805,"T4*",Thematic_Map!$I$2:$I$805,"<>") -> 5 | N8: =COUNTIFS(Thematic_Map!$A$2:$A$805,$I8,Thematic_Map!$F$2:$F$805,"T5*",Thematic_Map!$I$2:$I$805,"<>") -> 3 | O8: =COUNTIFS(Thematic_Map!$A$2:$A$805,$I8,Thematic_Map!$F$2:$F$805,"T6*",Thematic_Map!$I$2:$I$805,"<>") -> 2 | P8: =SUM(J8:O8) -> 26
I9: S8 | J9: =COUNTIFS(Thematic_Map!$A$2:$A$805,$I9,Thematic_Map!$F$2:$F$805,"T1*",Thematic_Map!$I$2:$I$805,"<>") -> 9 | K9: =COUNTIFS(Thematic_Map!$A$2:$A$805,$I9,Thematic_Map!$F$2:$F$805,"T2*",Thematic_Map!$I$2:$I$805,"<>") -> 5 | L9: =COUNTIFS(Thematic_Map!$A$2:$A$805,$I9,Thematic_Map!$F$2:$F$805,"T3*",Thematic_Map!$I$2:$I$805,"<>") -> 5 | M9: =COUNTIFS(Thematic_Map!$A$2:$A$805,$I9,Thematic_Map!$F$2:$F$805,"T4*",Thematic_Map!$I$2:$I$805,"<>") -> 6 | N9: =COUNTIFS(Thematic_Map!$A$2:$A$805,$I9,Thematic_Map!$F$2:$F$805,"T5*",Thematic_Map!$I$2:$I$805,"<>") -> 4 | O9: =COUNTIFS(Thematic_Map!$A$2:$A$805,$I9,Thematic_Map!$F$2:$F$805,"T6*",Thematic_Map!$I$2:$I$805,"<>") -> 2 | P9: =SUM(J9:O9) -> 31
I10: S9 | J10: =COUNTIFS(Thematic_Map!$A$2:$A$805,$I10,Thematic_Map!$F$2:$F$805,"T1*",Thematic_Map!$I$2:$I$805,"<>") -> 9 | K10: =COUNTIFS(Thematic_Map!$A$2:$A$805,$I10,Thematic_Map!$F$2:$F$805,"T2*",Thematic_Map!$I$2:$I$805,"<>") -> 5 | L10: =COUNTIFS(Thematic_Map!$A$2:$A$805,$I10,Thematic_Map!$F$2:$F$805,"T3*",Thematic_Map!$I$2:$I$805,"<>") -> 3 | M10: =COUNTIFS(Thematic_Map!$A$2:$A$805,$I10,Thematic_Map!$F$2:$F$805,"T4*",Thematic_Map!$I$2:$I$805,"<>") -> 7 | N10: =COUNTIFS(Thematic_Map!$A$2:$A$805,$I10,Thematic_Map!$F$2:$F$805,"T5*",Thematic_Map!$I$2:$I$805,"<>") -> 3 | O10: =COUNTIFS(Thematic_Map!$A$2:$A$805,$I10,Thematic_Map!$F$2:$F$805,"T6*",Thematic_Map!$I$2:$I$805,"<>") -> 2 | P10: =SUM(J10:O10) -> 29
I11: S10 | J11: =COUNTIFS(Thematic_Map!$A$2:$A$805,$I11,Thematic_Map!$F$2:$F$805,"T1*",Thematic_Map!$I$2:$I$805,"<>") -> 10 | K11: =COUNTIFS(Thematic_Map!$A$2:$A$805,$I11,Thematic_Map!$F$2:$F$805,"T2*",Thematic_Map!$I$2:$I$805,"<>") -> 4 | L11: =COUNTIFS(Thematic_Map!$A$2:$A$805,$I11,Thematic_Map!$F$2:$F$805,"T3*",Thematic_Map!$I$2:$I$805,"<>") -> 6 | M11: =COUNTIFS(Thematic_Map!$A$2:$A$805,$I11,Thematic_Map!$F$2:$F$805,"T4*",Thematic_Map!$I$2:$I$805,"<>") -> 8 | N11: =COUNTIFS(Thematic_Map!$A$2:$A$805,$I11,Thematic_Map!$F$2:$F$805,"T5*",Thematic_Map!$I$2:$I$805,"<>") -> 5 | O11: =COUNTIFS(Thematic_Map!$A$2:$A$805,$I11,Thematic_Map!$F$2:$F$805,"T6*",Thematic_Map!$I$2:$I$805,"<>") -> 2 | P11: =SUM(J11:O11) -> 35
I12: S11 | J12: =COUNTIFS(Thematic_Map!$A$2:$A$805,$I12,Thematic_Map!$F$2:$F$805,"T1*",Thematic_Map!$I$2:$I$805,"<>") -> 10 | K12: =COUNTIFS(Thematic_Map!$A$2:$A$805,$I12,Thematic_Map!$F$2:$F$805,"T2*",Thematic_Map!$I$2:$I$805,"<>") -> 4 | L12: =COUNTIFS(Thematic_Map!$A$2:$A$805,$I12,Thematic_Map!$F$2:$F$805,"T3*",Thematic_Map!$I$2:$I$805,"<>") -> 5 | M12: =COUNTIFS(Thematic_Map!$A$2:$A$805,$I12,Thematic_Map!$F$2:$F$805,"T4*",Thematic_Map!$I$2:$I$805,"<>") -> 8 | N12: =COUNTIFS(Thematic_Map!$A$2:$A$805,$I12,Thematic_Map!$F$2:$F$805,"T5*",Thematic_Map!$I$2:$I$805,"<>") -> 3 | O12: =COUNTIFS(Thematic_Map!$A$2:$A$805,$I12,Thematic_Map!$F$2:$F$805,"T6*",Thematic_Map!$I$2:$I$805,"<>") -> 2 | P12: =SUM(J12:O12) -> 32
I13: S12 | J13: =COUNTIFS(Thematic_Map!$A$2:$A$805,$I13,Thematic_Map!$F$2:$F$805,"T1*",Thematic_Map!$I$2:$I$805,"<>") -> 8 | K13: =COUNTIFS(Thematic_Map!$A$2:$A$805,$I13,Thematic_Map!$F$2:$F$805,"T2*",Thematic_Map!$I$2:$I$805,"<>") -> 5 | L13: =COUNTIFS(Thematic_Map!$A$2:$A$805,$I13,Thematic_Map!$F$2:$F$805,"T3*",Thematic_Map!$I$2:$I$805,"<>") -> 4 | M13: =COUNTIFS(Thematic_Map!$A$2:$A$805,$I13,Thematic_Map!$F$2:$F$805,"T4*",Thematic_Map!$I$2:$I$805,"<>") -> 5 | N13: =COUNTIFS(Thematic_Map!$A$2:$A$805,$I13,Thematic_Map!$F$2:$F$805,"T5*",Thematic_Map!$I$2:$I$805,"<>") -> 6 | O13: =COUNTIFS(Thematic_Map!$A$2:$A$805,$I13,Thematic_Map!$F$2:$F$805,"T6*",Thematic_Map!$I$2:$I$805,"<>") -> 1 | P13: =SUM(J13:O13) -> 29
I14: S13 | J14: =COUNTIFS(Thematic_Map!$A$2:$A$805,$I14,Thematic_Map!$F$2:$F$805,"T1*",Thematic_Map!$I$2:$I$805,"<>") -> 9 | K14: =COUNTIFS(Thematic_Map!$A$2:$A$805,$I14,Thematic_Map!$F$2:$F$805,"T2*",Thematic_Map!$I$2:$I$805,"<>") -> 4 | L14: =COUNTIFS(Thematic_Map!$A$2:$A$805,$I14,Thematic_Map!$F$2:$F$805,"T3*",Thematic_Map!$I$2:$I$805,"<>") -> 4 | M14: =COUNTIFS(Thematic_Map!$A$2:$A$805,$I14,Thematic_Map!$F$2:$F$805,"T4*",Thematic_Map!$I$2:$I$805,"<>") -> 7 | N14: =COUNTIFS(Thematic_Map!$A$2:$A$805,$I14,Thematic_Map!$F$2:$F$805,"T5*",Thematic_Map!$I$2:$I$805,"<>") -> 4 | O14: =COUNTIFS(Thematic_Map!$A$2:$A$805,$I14,Thematic_Map!$F$2:$F$805,"T6*",Thematic_Map!$I$2:$I$805,"<>") -> 1 | P14: =SUM(J14:O14) -> 29
I15: S14 | J15: =COUNTIFS(Thematic_Map!$A$2:$A$805,$I15,Thematic_Map!$F$2:$F$805,"T1*",Thematic_Map!$I$2:$I$805,"<>") -> 10 | K15: =COUNTIFS(Thematic_Map!$A$2:$A$805,$I15,Thematic_Map!$F$2:$F$805,"T2*",Thematic_Map!$I$2:$I$805,"<>") -> 4 | L15: =COUNTIFS(Thematic_Map!$A$2:$A$805,$I15,Thematic_Map!$F$2:$F$805,"T3*",Thematic_Map!$I$2:$I$805,"<>") -> 5 | M15: =COUNTIFS(Thematic_Map!$A$2:$A$805,$I15,Thematic_Map!$F$2:$F$805,"T4*",Thematic_Map!$I$2:$I$805,"<>") -> 5 | N15: =COUNTIFS(Thematic_Map!$A$2:$A$805,$I15,Thematic_Map!$F$2:$F$805,"T5*",Thematic_Map!$I$2:$I$805,"<>") -> 3 | O15: =COUNTIFS(Thematic_Map!$A$2:$A$805,$I15,Thematic_Map!$F$2:$F$805,"T6*",Thematic_Map!$I$2:$I$805,"<>") -> 1 | P15: =SUM(J15:O15) -> 28
I16: S15 | J16: =COUNTIFS(Thematic_Map!$A$2:$A$805,$I16,Thematic_Map!$F$2:$F$805,"T1*",Thematic_Map!$I$2:$I$805,"<>") -> 7 | K16: =COUNTIFS(Thematic_Map!$A$2:$A$805,$I16,Thematic_Map!$F$2:$F$805,"T2*",Thematic_Map!$I$2:$I$805,"<>") -> 6 | L16: =COUNTIFS(Thematic_Map!$A$2:$A$805,$I16,Thematic_Map!$F$2:$F$805,"T3*",Thematic_Map!$I$2:$I$805,"<>") -> 6 | M16: =COUNTIFS(Thematic_Map!$A$2:$A$805,$I16,Thematic_Map!$F$2:$F$805,"T4*",Thematic_Map!$I$2:$I$805,"<>") -> 8 | N16: =COUNTIFS(Thematic_Map!$A$2:$A$805,$I16,Thematic_Map!$F$2:$F$805,"T5*",Thematic_Map!$I$2:$I$805,"<>") -> 5 | O16: =COUNTIFS(Thematic_Map!$A$2:$A$805,$I16,Thematic_Map!$F$2:$F$805,"T6*",Thematic_Map!$I$2:$I$805,"<>") -> 1 | P16: =SUM(J16:O16) -> 33
I17: S16 | J17: =COUNTIFS(Thematic_Map!$A$2:$A$805,$I17,Thematic_Map!$F$2:$F$805,"T1*",Thematic_Map!$I$2:$I$805,"<>") -> 7 | K17: =COUNTIFS(Thematic_Map!$A$2:$A$805,$I17,Thematic_Map!$F$2:$F$805,"T2*",Thematic_Map!$I$2:$I$805,"<>") -> 5 | L17: =COUNTIFS(Thematic_Map!$A$2:$A$805,$I17,Thematic_Map!$F$2:$F$805,"T3*",Thematic_Map!$I$2:$I$805,"<>") -> 5 | M17: =COUNTIFS(Thematic_Map!$A$2:$A$805,$I17,Thematic_Map!$F$2:$F$805,"T4*",Thematic_Map!$I$2:$I$805,"<>") -> 6 | N17: =COUNTIFS(Thematic_Map!$A$2:$A$805,$I17,Thematic_Map!$F$2:$F$805,"T5*",Thematic_Map!$I$2:$I$805,"<>") -> 3 | O17: =COUNTIFS(Thematic_Map!$A$2:$A$805,$I17,Thematic_Map!$F$2:$F$805,"T6*",Thematic_Map!$I$2:$I$805,"<>") -> 1 | P17: =SUM(J17:O17) -> 27
I18: S17 | J18: =COUNTIFS(Thematic_Map!$A$2:$A$805,$I18,Thematic_Map!$F$2:$F$805,"T1*",Thematic_Map!$I$2:$I$805,"<>") -> 8 | K18: =COUNTIFS(Thematic_Map!$A$2:$A$805,$I18,Thematic_Map!$F$2:$F$805,"T2*",Thematic_Map!$I$2:$I$805,"<>") -> 7 | L18: =COUNTIFS(Thematic_Map!$A$2:$A$805,$I18,Thematic_Map!$F$2:$F$805,"T3*",Thematic_Map!$I$2:$I$805,"<>") -> 5 | M18: =COUNTIFS(Thematic_Map!$A$2:$A$805,$I18,Thematic_Map!$F$2:$F$805,"T4*",Thematic_Map!$I$2:$I$805,"<>") -> 9 | N18: =COUNTIFS(Thematic_Map!$A$2:$A$805,$I18,Thematic_Map!$F$2:$F$805,"T5*",Thematic_Map!$I$2:$I$805,"<>") -> 4 | O18: =COUNTIFS(Thematic_Map!$A$2:$A$805,$I18,Thematic_Map!$F$2:$F$805,"T6*",Thematic_Map!$I$2:$I$805,"<>") -> 2 | P18: =SUM(J18:O18) -> 35
I19: S18 | J19: =COUNTIFS(Thematic_Map!$A$2:$A$805,$I19,Thematic_Map!$F$2:$F$805,"T1*",Thematic_Map!$I$2:$I$805,"<>") -> 10 | K19: =COUNTIFS(Thematic_Map!$A$2:$A$805,$I19,Thematic_Map!$F$2:$F$805,"T2*",Thematic_Map!$I$2:$I$805,"<>") -> 8 | L19: =COUNTIFS(Thematic_Map!$A$2:$A$805,$I19,Thematic_Map!$F$2:$F$805,"T3*",Thematic_Map!$I$2:$I$805,"<>") -> 7 | M19: =COUNTIFS(Thematic_Map!$A$2:$A$805,$I19,Thematic_Map!$F$2:$F$805,"T4*",Thematic_Map!$I$2:$I$805,"<>") -> 10 | N19: =COUNTIFS(Thematic_Map!$A$2:$A$805,$I19,Thematic_Map!$F$2:$F$805,"T5*",Thematic_Map!$I$2:$I$805,"<>") -> 3 | O19: =COUNTIFS(Thematic_Map!$A$2:$A$805,$I19,Thematic_Map!$F$2:$F$805,"T6*",Thematic_Map!$I$2:$I$805,"<>") -> 2 | P19: =SUM(J19:O19) -> 40
... I24: S23 | J24: =COUNTIFS(Thematic_Map!$A$2:$A$805,$I24,Thematic_Map!$F$2:$F$805,"T1*",Thematic_Map!$I$2:$I$805,"<>") -> 10 | K24: =COUNTIFS(Thematic_Map!$A$2:$A$805,$I24,Thematic_Map!$F$2:$F$805,"T2*",Thematic_Map!$I$2:$I$805,"<>") -> 6 | L24: =COUNTIFS(Thematic_Map!$A$2:$A$805,$I24,Thematic_Map!$F$2:$F$805,"T3*",Thematic_Map!$I$2:$I$805,"<>") -> 7 | M24: =COUNTIFS(Thematic_Map!$A$2:$A$805,$I24,Thematic_Map!$F$2:$F$805,"T4*",Thematic_Map!$I$2:$I$805,"<>") -> 8 | N24: =COUNTIFS(Thematic_Map!$A$2:$A$805,$I24,Thematic_Map!$F$2:$F$805,"T5*",Thematic_Map!$I$2:$I$805,"<>") -> 3 | O24: =COUNTIFS(Thematic_Map!$A$2:$A$805,$I24,Thematic_Map!$F$2:$F$805,"T6*",Thematic_Map!$I$2:$I$805,"<>") -> 2 | P24: =SUM(J24:O24) -> 36
I25: Total | J25: =SUM(J2:J24) -> 218 | K25: =SUM(K2:K24) -> 129 | L25: =SUM(L2:L24) -> 137 | M25: =SUM(M2:M24) -> 170 | N25: =SUM(N2:N24) -> 94 | O25: =SUM(O2:O24) -> 39 | P25: =SUM(P2:P24) -> 787

Sheet StudyWise_SAS_Extension
A1: Study | B1: Authors | C1: Core contribution | D1: Locus of the architectural work | E1: Sub-themes touched | F1: What breaks / is missing for SAS | G1: Framework reading (link grade) | H1: Best fit and why | I1: Possible extension for SASS (testable), with preconditions and risks | J1: Grounding
A2: S1 | B2: Maranhão & Guerra | C2: Five reusable prompt patterns in a sequence of decisions with a decision flow that is gated behind an evaluate-and-refine check by an architect. | D2: Design time | E2: 1.1(A), 1.2, 1.3, 1.4(A), 1.5, 1.6, 2.1, 2.2(A), 2.3(A), 3.1, 3.2, 3.3, 4.1, 4.2(A), 4.3, 4.4(A), 4.5, 5.1, 5.2, 6.1 | F2: (a) Adaptation space: there was no output generated which could be adapted. The input was an architecture, model or artefact that could be changed (1.1, related activity) and the output were the suggestions that a loop produced within a decision dialogue. (b) Autonomy: each of the five-patterns is preceded and followed by an architect's evaluate-and-refine check and the Software Architect Persona is written specifically to avoid making any decisions that are beyond the architect's knowledge and control (1.5, 2.1). (c) Assurance: Only human reading of the premise list can be a safeguard against a false premise; and the justifications of the model itself may not cover complex scenarios (5.2). (d) Timeliness and reproducibility: model is not described as ChatGPT v1, v1.5, v2 etc. of ChatGPT, but as ChatGPT and free of any latency or cost, and free of any version, temperature, run count anywhere (3.3). (e) Liveness: coded silence for use, continuous re-architecting not addressed (4.4). Evidence: Two illustrative applications for two scenarios; one industrial and one fictional, relevance determined subjectively, no baseline (3.1, 3.2). | G2: The five-pattern sequence is a Plan activity (produces a design decision and a justification is attached), and the Technical Premises list is a fragment of Knowledge (a record of what the design decision assumes). There isn't any Monitor and Analyze input: the situation enters the model by being written as prose by an architect. Execute is the architect who takes action on the decision. The authors don't mention a loop, so we do everything in this map. Rainbow (Inferred): The position of the evaluate-and-refine gate is the same as the position of a constraint evaluation, and the dimensions which a utility function would require are the same as the name of the question that forms the Quality Attribute pattern; but there is no architecture model, no strategy set and no executor. Model@run.time (Not applicable): There is no model kept of anything. The artefacts are a prompt transcript and a premise list which are neither directly related to a running system. But, there are also some requirements that are not known at design time, such as awareness requirements, which are an unassailable requirement and are the design-time counterpart of a requirement monitored at runtime. (1.2) | H2: MAPE-K, at Plan. The object of the sequence is a decision and the reason is the result of Plan, the only thing in the paper that resembles Knowledge. The rainbows fit the gate, but if it's not the right model then there's no constraints, and if there's no executor then nothing fits the gate. There is no support for the models@run.time system. Awareness requirements are applied to the approach, not the pattern. | I2: Convert the evaluate-and-refine gates to machine-checkable acceptance conditions and the Technical Premises list to a checkable precondition record for the decision, so that a human action (evaluate and refine) in design time can be performed as a constraint check in runtime. Proved by the ability to be tested both by a sequence that can be automatically re-elected against the premises as they still stand and can be automatically rejected when one of the premises fails, and against an architect's own opinion on the same cases. Preconditions: quality attributes as thresholds to be monitored, not as questions; premises in a testable format. Risks: The paper reports shifting the verification burden to the architect to a step without an architect (5.2); an over-constrained persona leads to bias and rigidity (5.1); and there is no model version or setting reported, so no result here is reproducible as a baseline (3.3). | J2: Extrapolated
A3: S2 | B3: Maranhão Junior, Melegati & Guerra | C3: The S1 sequence can be verified with a retrospective evaluation, which shows that it can replicate real architectural decisions, and documents failure scenarios: the omission of the precondition to the backend, the underestimated timeframe for the architectural planning, and the vendor bias in a recommendation. | D3: Design time | E3: 1.1(A), 1.2, 1.3(A), 1.4(A), 1.5, 1.6, 2.1, 2.2(A), 2.3(A), 3.1, 3.2, 3.3, 4.1, 4.2(A), 4.3, 4.4(A), 4.5, 5.1, 5.2, 6.1 | F3: (a) Object setting is NOT the object. As a part of an existing architecture, 2 decisions of microservices are re-enacted without producing anything new, or changing anything (1.1 related activity, 1.4 coded silence). (b) Autonomy (1.5): it is offered as a way for the architect to explore the possibilities and think aloud, and to then choose the options to pursue. (c) Accountability: There is no decision record or rationale artefact produced, the system of adaptation does not have an artefact to record (1.3, coded silence). (d) Assurance: hallucination is answered by requesting it to come up with its logic so the architect can check it, AWS and Azure were recommended, Google is not (5.2). (e) Liveness: the assessment takes the perspective of what has already happened; there is no operation while running, no adaptation whatsoever is mentioned (4.4, coded silence). ( f) Evidence: two companies, two architects, prompts developed by the researcher, not by the practitioner, and the same two URLs published in the accompanying paper (3.1, 3.3). | G3: MAPE-K (Inferred): same as MAPE but with evidence that a plan is what a team actually decided. No Monitoring and Analysing, and the test of the plan is a human who is recalling the outcome. Not the authors', ours! Rainbow (Inferred): The architect who makes the selection of one of the options presented by the model. No architecture model, constraint set or executor. Models@run.time (Not applicable): No model of the system is maintained, only the two case systems are described using prose to prompt the person. Dynamic software product lines (Inferred): decisions are made for existing microservices options, which is a variant choice but there is no variability model written down. | H3: MAPE-K, at Plan, for the same reason as S1; in the strongest evidence in the family, the paper brings a decision that a team reaches to Plan; no evidence at all, that anything could trigger or accept that decision without a person. Rainbow and dynamic product lines each describe one facet of the decision and none of its machinery; Models@run.time has nothing to attach to. | I3: Evaluate a runtime planner by replaying what the planner had decided to do, and compare whether a model, based on its state at that time, reaches the same one. That is the way this paper's processes transitioned from design to adaptation, and they start without the need for a running system. Testable by agreement with the recorded decision over a set of past adaptations, with the two types of failures the paper names as categories to count: a precondition that the model did not ask about and a quantity that it underestimated (5.1). Level 1: Preconditions: a log of past adaptations with state of what was decided, and a judge who knows.Level 2: Preconditions: a log of past adaptations with the state that triggered a specific one, and a judge who knows. Risks: Not providing enough information for complex environments (5.1) and favoring vendor solutions in technology decisions (5.2) due to the rich amount of information available about microservices around the web. | J3: Extrapolated
A4: S3 | B4: Diaz-Pace, Tommasel, Capilla & Ramírez | C4: An autonomous agent explores, compares and assesses architectural patterns via chained tool calls and reflection, using ReAct and tree-search (LATS) strategies; observed skipping its own assessment tool when using tree search. | D4: Design time and agent driven | E4: 1.1, 1.2, 1.3(A), 1.4, 1.5, 1.6, 2.1, 2.2, 2.3, 3.1, 3.2, 3.3, 4.1, 4.2, 4.3, 4.4, 4.5, 5.1(A), 5.2, 6.1 | F4: Change to a system: the agent loops through and filters the published patterns/tactics on a requirements document and outputs a set of ranked design solutions instead of changing the system (1.1, 1.2). From the previous prototype, which had to have the agent type the search to be executed, this prototype is an advance in autonomy in that this one chains reasoning across patterns without the guard (1.5), but it was observed that the agent does not attempt to run its own decision-asessment tool (5.2), so the only check in the workflow is one that the agent is free to choose not to run. (c) Assurance: some of the options returned in the ranking were not even a pattern or a tactic in the literature, that names the authors (hallucinations 5.2). (d) Timeliness: a run count, temp, token cost or latency reported are not reported — case study appears to have been repeated only once, not many times (case study repeated output noted as inference work 3.3). (e) Liveness: “Designed only at design time” operation does not run; no operation that is designed; no adaptation loop is provided (4.4, coded silence). Grounding: The authors talk about grounding but do not plan or implement it (2.2), meaning that the knowledge that is used to reason about is in the model. | G4: Analyse and Plan: the agent's acts are Analyse and Plan in one loop of its own, as it makes its decision and does its assessment, and reflection is a second pass over its own actions. There is no monitor; and the parameters of the model are Knowledge, hence the authors call grounding as necessary. Ours; the authors describe ReAct and tree search, not MAPE-K. Rainbow (Inferred): closer here than in S1 or S2, as the agent is evaluating candidate architectures against a set of criteria and choosing from them; this is what the adaptation engine of Rainbow does with adaptation strategies. What's missing is the architecture model and the constraints: the criteria are prompt text judged by the model itself. No model kept between runs (Not applicable): no model used between runs and solutions summarised for a reader (1.3, related activity). FORMS (Inferred): is a reflection step which is an LLM-as-a-judge pass on the agent's own three criteria, not a system; in this way it is the shape of a reflective subsystem. | H4: Rainbow. This is the one design-time decision paper of which the machinery is similar to architecture-based adaptation: candidates judged based on criteria and then a selection. MAPE-K is a sequence in the agent's internal program that is not paired with any Monitor or anything to be operated on. No models are stored in the Models@run.time. FORMS is designed to cover the reflection step only. The difference here is that while Rainbow's constraint evaluation was external and enforced, this was an evaluation that the agent didn't use. | I4: Make the evaluation step independent of the agent and mandatory: Present a proposal to the agent and have it evaluated by someone outside the agent (a checker) who has architectural information, and only apply a proposal that passes. This paper is the evidence to support this reason, its own agent ignored the assessment tool under tree search (5.2). Comparable to the speed with which invalid proposals are disallowed, testing by comparing the agent's own evaluation to an external evaluator of the same proposals. Preconditions: Conditions expressed before the prompt; a checker that is not a part of the agent's model. Limitations: hallucinated patterns being added to the candidate set (5.2), trajectory lock-in after setting a search direction (5.2), duplicate work that increases cost without showing any budget (3.3), and finally the paper's own claim that LLMs for self-adaptive systems is a different line of research (4.4). | J4: Partly grounded
A5: S4 | B5: Dhar, Vaidhyanathan & Varma | C5: Shows a quality of ~248M parameter model is fine-tuned to the same level as a 175-billion-parameter model few-shot. | D5: Documenttaion step and at design time | E5: 1.1(A), 1.2, 1.3, 1.4(A), 1.5, 1.6, 2.1, 2.2, 2.3, 3.1, 3.2, 3.3, 4.1(A), 4.2(A), 4.3, 4.4(A), 4.5, 5.1, 5.2, 6.1 | F5: Object: generated object is a decision field of an architecture decision record (related activity) not an architecture (1.3 makes the scope narrowing explicit). (b) Autonomy: stated conclusion: models can make design decisions, but not in autonomy - even the best performer is not able to capture the decision entirely and the model will assist with the decision, but it cannot take the decision itself (1.5). (c) the quality of the plan; maintaining adherence to the plans in terms of format, but failing to adequately engage with the content of the decision (5.1), is the most important failure mode for a planner. (d) Liveness: generation takes place while documentation occurs, no generation takes place during execution, no mention of adaptation (coded silence 4.4). (e) Dependence: the best models are cloud services, in this case, project data is transferred to a third party, and this involves some privacy, IP and legal concerns (5.1, 4.5). The input consists of a context of a human authored architecture (1.4, coded silence) and there is no analysis of the existing architecture. | G5: MAPE-K (Inferred): This is a Knowledge contribution, NOT a Plan contribution. The result of the model is the record of a decision; in a loop, Knowledge contains the results of a previous decision for the later activity to read. The authors do not pose this question like this. Rainbow (Not applicable): No Architecture Model, No Constraint Evaluation, No Strategy; about text generation for a record. Models@run.time (Inferred): a decision record created from a stated context is the design-time form of a rationale associated with a change to the runtime model, but none of this is attached to a running system. Dynamic software product lines (No variability, No binding): not possible. Three-layer (Inferred): A decision is not a change, therefore it would go under goal management, and their contribution would go under that. | H5: MAPE-K, at Knowledge. What makes a Knowledge step affordable to be included in a loop is its contribution, which is a record of a decision and its reasoning, and the result measured by the paper, that a 248M fine-tuned model matches a much bigger model prompted few-shot (2.3). Rainbow or dynamic product lines have no place to hang the record, while the three-layer reading, as in the above examples, describes only where the record would reside, not what the paper does. | I5: This will involve creating the adaptation record from the Analyse result and the goal it serves from a small locally-hosted fine-tuned model as opposed to a cloud model, so that a loop can write a rationale for each change without having to send runtime data to another location. This paper provides both sides of the argument: fine-tuning a small model gets roughly the same performance as a very large model (2.3); and the data-transmission issue is answered by the locally-hosted small models (1.6, 4.5). Testable by whether engineers can replicate why an adaptation has occurred from the generated record, compared with handwritten records of the same adaptations, using a small with fine tuning to the adaptation and a cloud model as the two arms. Preconditions: context-to-decision pairs for adaptations, which an adaptation log supplies; hardware for local hosting. Risks: decision content below the level of human (5.1); hallucination varies with model size and adaptation method (5.2); and the caution in the paper that the validation and test sets are the same (3.1). | J5: Extrapolated
A6: S5 | B6: Soliman & Keim | C6: Compares the accuracy of a model that answers questions regarding the architecture of an existing system (HDFS) to a hand-built ground truth and demonstrates that errors are primarily those involving confusion between concepts, rather than a wrong answer in general or a different specific instance. | D6: Comprehension of the built system and at design time | E6: 1.1(A), 1.2(A), 1.3, 1.4, 1.5, 1.6, 2.1, 2.2, 2.3, 3.1, 3.2, 3.3, 4.1(A), 4.2, 4.3, 4.4(A), 4.5, 5.1, 5.2, 6.1 | F6: (a) Object: probing is knowledge already possessed in the model of an existing system, which doesn't generate anything, and that doesn't change (1.1, 1.2, both related activity). (b) Autonomy: Expressed opinion: The model gives a preliminary grasp of an architecture but it should not be considered as an expert analysis and needs to be further refined and validated by experts (1.5). (c) Accuracy is not evenly distributed: accuracy is greater than precision and the model is too generous and the accuracy varies greatly from one knowledge concept to another, and from one quality attribute to another (5.1). Errors: (d) Assurance: Errors in the absence of arguments and lack of provenance (5.2) are the most difficult to detect by automatic checking, and are within-concept confusions, not errors in the categories (the right type of answer, the wrong instance). (e) Liveness: the study investigates already existing system and the question answering is performed on it; it is not discussed whether anything operates during the run of the system or not (4.4 coded silence). (f) Source of truth: It was necessary to check the training-data coverage of the target system before running the study, and a fix is proposed – repository grounding with traceability – which is the knowledge and not the system. | G6: MAPE-K (Inferred): this refers to Analyse reading from Knowledge, but in this case the Knowledge is the parameters of the model and not a Knowledge the system writes. That measured result is the accuracy of the Analyse step, per concept; exactly what a loop would need to know before using it! The authors do not specify a loop. Rainbow (Inferred): There is no evaluation of constraints, no selection of strategy; the three concepts tested in the study; components and connectors, quality solutions, rationale are the content of the model; how well a model can answer the questions it is designed to answer gets tested in the study. Models@run.time (Inferred): the best reading in this location. The accuracy of recovering the components, connectors and quality solutions from a built system is measured in this paper, and a runtime model would be the means of keeping it current. But there is no repetition: It's one snapshot, not from the system, but from parameters. FORMS (Inferred): the description recovered is a reflection model of the subject system, of which FORMS is attributing the role. | H6: Models@run.time. The purpose of the paper is to describe a system's architecture without a human authoring it – which is a runtime model – and to compare the accuracy of such a description to a ground truth, constructed from issues, documents, code and discussions. In MAPE-K its name is the activity, while in Rainbow it is the content of the model (as opposed to the adaptation); FORMS deals with the artefact and does not refer to its production. | I6: To keep the architecture description derived from the model up to date, query the system instead of the model parameters, and use the accuracy numbers per concept to choose which parts of the model description can be trusted by a loop, and which ones must be verified before using the model. The per-concept figures are proposed for exactly this purpose (1.6) and repository grounding and traceability are proposed as the route (2.2). Testable by accuracy of the description after a change, compared to the accuracy before, over an evolving system; the study's precision, recall and F1 against a manual ground truth are the pre-given test; Inputs: system instead of the source to be queried, and at least one ground truth for the system. Weakness: confusion between concepts, which a downstream check wouldn't catch because the answer is the correct shape (5.2); inclusiveness (inflating recall) that could lead to a loop of plausible components that don't exist (5.1); randomness in the output between runs (5.2); a closed model whose hidden changes cannot be excluded (5.2). | J6: Partly grounded
A7: S6 | B7: Ramachandran | C7: Uses UML diagrams to map out a requirements specification, using GitHub Copilot; only thing we were able to reliably conclude is that the output sometimes lacked or mislabeled content from the prompt. | D7: Diagram production and design time | E7: 1.1, 1.2(A), 1.3(A), 1.4(A), 1.5, 1.6, 2.1, 2.2(A), 2.3, 3.1, 3.2, 3.3, 4.1(A), 4.2, 4.3, 4.4(A), 4.5, 5.1, 5.2, 6.1 | F7: (a)It is not an architecture to adapt, no architecture is recommended, and no rationale is captured, (1.1; 1.2 and 1.3, both as part of the same activity). (b) Autonomy: tool used as an assistant to increase design productivity; the quality of the diagrams generated was limited (1.5), but in some cases the generated diagrams were more satisfactory than the human generated diagrams, and/or the tool was used as an assistant to speed up design. Content (c) Fidelity (the deciding break): Explicit reference to the content prompt was not mentioned or was reworded in the output (5.2) and omissions were recorded to each diagram type (5.1). A model that refuses to comply with the instructions of a loop is not affected by a loop. No following repeat generation was performed, so there is no variability examined (5.2 coded silence) and tool version and underlying model is not reported (3.3) (d) Determinism. (e) Liveness: Design time documentation, no action takes place during execution, no mention of adaptation (4.4, coded silence). Evidence: 1 evidence document, 4 diagrams, 1 rater, no validity, no second rater, similarity score (3.1, 3.2) behind matching procedure. | G7: MAPE-K (Inferred): a Plan output in the narrow sense as a diagram is a proposed structure and there is no Monitor, Analyse or Execute around it and no Knowledge store. There is no reading thinner in the corpus than ours, which is the MAPE-K reading. Rainbow (Not applicable): no architecture model that is evaluated, no constraints, no strategy, no executor. Models@run.time (Inferred): a runtime model must be machine-readable and the generated diagram is the only model that the paper aims its output at: existing modelling toolchains (4.2). But it's a product which is produced once, not from a system, and which doesn't have any causal relationship with anything. EUREMA (Inferred): output that is intended to be used for a modelling toolchain is in the form of parts of a megamodel, but no executable parts are present here. | H7: Models@run.time, weakly. The one property this study contributes towards self-adaptation is that a model can emit a machine-readable model in an established notation, which is the precondition for a runtime model being generated rather than hand-built. MAPE-K has only one activity present and no loop; Rainbow has nothing to attach to; EUREMA needs executability the paper does not offer. The finding that works against it is in the same paper: the notation came out incomplete relative to the prompt. | I7: Check a generated model element-wise against the input model that it was generated from and reject it if any elements are not present or moved to different names in the input. The drop or relabeling of prompt-specified content (5.2) is the only reliable finding in this study; it is necessary for this content. Testable by the proportion of models generated that satisfy such a completeness test; and whether the omissions identified in this paper by hand are correctly identified by such a test. Preconditions: an input that is precisely specified, such that it can be checked; a comparison which acts on notation, not prose. Risks: generation that is not repeatable (5.2), no tool version or model identity, thus no baseline available (3.3), and no similarity score matching procedure, so the reported degree of matching cannot be reproduced (3.2). | J7: Extrapolated
A8: S7 | B8: Eisenreich, Speth & Wagner | C8: Proposing architecture regeneration as requirements change with a vision paper, while taking into account both the quality gain and the need to deviate from the existing architecture, and reducing the amount of unnecessary change. | D8: Repeated design iterations and at design time | E8: 1.1, 1.2, 1.3, 1.4, 1.5, 1.6, 2.1, 2.2(A), 2.3, 3.1, 3.2, 3.3, 4.1, 4.2, 4.3, 4.4(A), 4.5, 5.1, 5.2, 6.1 | F8: (a) Autonomy: deliberately limited: The process is limited to known standard procedures which are more easily applied semi-automatically, and because the process is expected to be supervised by an experienced architect, and because there is no training data for the process — the authors' own exploratory test has indicated that the process does not currently perform well if it is fully automated (1.5). The human is trusted to make the final decision: some of the requirements are not recorded because everyone knew them and some are suspected to be added later (1.5). There is no architect or unspoken requirements for a run-time loop. (c) Evidence: Only the first step of narrative observation was formally tested and informally evaluated for 91 requirements, generation and evaluation of architecture (3.1, 3.2) is proposed and fully untested. (d) Quality of that one tested step: both models identified domain concepts but first modelled the system instead of the domain and basic prompt rewording made a crucial difference in the quality of the output (1.6, 2.1). (e) Grounding: domain knowledge is not retrieved but rather is pretrained (2.2 coded silence). (f) Timeliness: there is no reported cost, latency or version pinning (3.3). | G8: MAPE-K (Inferred): the pipeline is Plan, followed by an Analyse stage to which an established evaluation method and quality metrics should be automated over (1.4) and the architect is the Execute authority. The one activity that has no counterpart is Monitor: change comes in the form of a revised requirements document, not as a measurement. Rainbow (Inferred): the most similar design-time paper, based on the shape of the decision, to the one we have. The candidates are generated, then automatically evaluated by metrics of quality, and one is chosen (Rainbow's evaluate-then-select, the formalism (4.2) is the model). The missing components are the running system and the executor. Models@run.time (Inferred): the architecture is not a single artefact, but a model with a life, as it is changed in each iteration and is re-generated as the requirements evolve. Three layer (Inferred): most robust reading of structure. Goal management is what changes are worth making: it is the layer that the studies in the implemented corpus do not reach, since it focuses on deciding an architecture from changed requirements, weighing the gain in quality of the change against the cost of departing from the existing architecture and preferring candidates that differ as little as possible (4.4). Awareness requirements (Inferred): a requirement that evolves as changes are made and thus is a monitor of requirement failure that leads to adaptation, in design-time form. | H8: Self-managed systems: 3 layers architecture. Only S21 produces an architecture multiple times; all other studies produce an architecture but only once; and, of the studies that do produce an architecture, none considers changing an existing architecture. In this study, this is made an explicit cost-benefit decision with a minimum requirement of smallest change that a quality requirement justifies. That is the question to ask before a self-adaptive system can restructure itself, the goal-management layer has to ask. Rainbow fits the evaluate and select mechanism, not whether or not to change, MAPE-K names the activities, no Monitor; no Monitor to Models@run.time, it names the artefact, not its purpose. | I8: Regenerate from a monitored requirement, rather than from an edited requirements document, and use the change-minimisation rule of the paper as the planner's goal: regenerate the affected part of the architecture with the minimal change to the running one, except for a larger change when a quality requirement justifies the cost. The reason that this is testable without a running system is that the rule (4.4) and the evaluation step (1.4) that would be used to award this are already stated in the paper. It is testable because the regenerated fragments can be compared with an architect's own fragments for the same change in requirements and can be scored for the quality gained, as well as for proximity to the current architecture. Preconditions: conditions that can be checked; the automated evaluation step that the paper proposes but the paper has not implemented; an architecture in the formality named by the paper. Risks: the step tested is the wrong step, the model is tested on the system, not the domain (1.6); the quality of the output depends on the prompt wording of the step (2.1); the implicit requirements the paper passes on to the architect, which are not monitored in any way; the proposed generation and evaluation steps have not been demonstrated (3.1). | J8: Partly grounded
A9: S8 | B9: Díaz-Pace, Tommasel & Capilla | C9: ArchMind: the first working retrieval-augmented generation implementation in the corpus. | D9: Decision support with a record and at design time | E9: 1.1(A), 1.2, 1.3, 1.4, 1.5, 1.6, 2.1, 2.2, 2.3, 3.1, 3.2(A), 3.3, 4.1(A), 4.2, 4.3, 4.4(A), 4.5, 5.1, 5.2, 6.1 | F9: (a) Object: requirements do not go to a decision record as part of an architecture (1.1, related activity); so what changes in the pipeline is documentation? (b) Autonomy: the design is based on two role model: the deciding "senior architect" is a human being, and the “copilots” are “cognitive architect” humans who can articulate the design and provide critique at any time, but the human can intervene at any point to alter the pattern or edit the decision or write a new one (1.5). It is the critique which they add and not the decision. (c) Missing problem framing: Errors were found to be a result of the absence of a first step in problem framing, which humans take when asking for options: The explicit problem statement based on a requirement is missing (5.1). This is a situation that is not covered by any type of loop. Partial grounding (2.2): retrieval is of external pattern knowledge; not of the project-specific context, which a half a runtime loop would need. (e) Liveness: decision support in design: No runtime/execution-time behaviour is mentioned anywhere (4.4, coded silence). Evidence and cost: explicitly scoped as an initial characterisation, one system, no metric or rubric, no cost or latency figures (3.1, 3.2, 3.3) is a system reviewed by the authors and not against ground truth. | G9: MAPE-K (Inferred): The five copilots split the tasks of Analyse (to verify whether a candidate decision conflicts with previous decisions), Plan (to develop a candidate pattern decision, rank it and instantiate), and Knowledge (to present the consolidated MADR record and to present the structured rationale that was captured prior to recording). Human is the one that is not monitored and is called Execute. The division by task is the most similar to loop activities of all design time studies in the corpus. Rainbow (Inferred): When an evaluation of consistency with previous decisions occurs, it is done by someone other than the proposer, and when the retrieval step fails, it fails closed, not by generating an answer (2.2, 5.2). Two of the three parts of Rainbow are those. The architecture model is not there, and so are no programs that run. Regraded by Rainbow: describes a running system within an architectural model and selects an adaptation; none of these is the Check outside the generator, a Coverage rule or a Proposed utility and are not applied to a running system. Machine-readable: the record is directed towards existing MADR template (4.2) and hence is machine-readable, but not a model of a system but a record of a decision. ActivFORMS (Inferred): a check that will not answer if it does not answer well; only what has been confirmed will pass through; but nothing here is formally confirmed. | H9: Rainbow, on the basis of the fail closed check. In this case, it is a candidate decision that determines whether a candidate decision can proceed: the consistency copilot promotes it based on the previous decisions; in the event that it cannot ground an answer, retrieval returns something generic instead of nothing. A loop requires a separation between Plan and Execute; that's what the proposer/ checker is. The copilots are mapped in a clean fashion with no Monitor and no Execute, but Models@run.time fits the template and not the object, and ActivFORMS fits the disposition, but not the verification. | I9: Place the consistency copilot in the middle of an adaptation plan and its implementation: a proposed change is provided to a planner; a separate checker applies the proposed change to the adaptation decisions already in place; a change that cannot be supported is not answered but rejected. Testable by the rate of false-positive plans from true-negative plans and true-negative plans from false-positive plans (incorrectly blocked) vs true-negative plans from true-negative plans (correctly blocked): paper's two strategies used as arms, retrieval with a failure closed against zero-shot with always a true answer but some may be false (5.2). Preconditions: decisions in force as represented in a form checkable by the checker (2.2); retrieval corpus that covers the project – this paper does not have. The risks are that the check returns no value, so that a loop that needs action remains stalled (5.1); runtime has no value supplied to solve the problem, which does not get framed either (5.1); a plain reconfiguration may be ignored, in favour of a catalogued pattern (1.6); and no cost figure for a pipeline of five model calls (3.3). | J9: Partly grounded
A10: S9 | B10: Dhar, Vaidhyanathan & Varma | C10: The concept of a first verification of fused architectural knowledge before storing it, possibly with the help of formal methods, was introduced as the idea of the Oracle Verifier within the corpus: the proposal is to use an Oracle Verifier to determine the validity of the fused architectural knowledge. | D10: Proposed at design time | E10: 1.1, 1.2, 1.3, 1.4, 1.5, 1.6(A), 2.1(A), 2.2, 2.3, 3.1(A), 3.2(A), 3.3(A), 4.1, 4.2, 4.3, 4.4(A), 4.5, 5.1, 5.2, 6.1 | F10: (a) Nothing exists: the extraction, fusion, verification and retrieval components are suggested but not constructed, components 3.1 and 3.2 related, and the empirical content of the paper represents a restatement of the earlier study by the paper's family (both related activity). Explicitly Unresolved Engineering Challenges: There are four engineering domain challenges that are left open, explicitly unresolved (5.1). No benefit in practice reported (coded silence) (1.6): (b) no benefit in practice reported. The costs and the latencies are not given for a system that does not exist (coded silence): (c) Timeliness: none of the costs or latencies are provided for a system that doesn't exist (3.3, coded silence). (d) Reliability: There is no mechanism in place in the proposed system itself (5.2 coded silence); The Oracle Verifier is a specification. (e) is liveness; runtime logs are named as one source knowledge can be mined from, and nothing more; is a documentation input, not an adaptation input (4.4, coded silence). (f) Autonomy: if there are manual tools, then they are not used; the same knowledge is presented in multiple forms that depend on the person who is asking (4.3); the system is an instrument that people want to use to ask a question of it. | G10: MAPE-K (Inferred): a Knowledge proposal, virtually all. The Knowledge component is the job of a pipeline to learn from artefacts within a project and merge that knowledge with knowledge from somewhere else and to validate and respond to queries based on the knowledge. Two query templates penetrate Plan; one to generate candidate architectures for new systems, the other to propose architectural changes to new features (1.1, 1.2). But no selection and execution of a strategy, no architecture model Rainbow depends on, and the proposed structural validity check is the constraint evaluation: Rainbow (Inferred). Models@run.time (Inferred): the proposal is closer than any paper that is not built as far as using the knowledge base, with sources being repositories and documents, and logs being named as a source for mining. The first non-human verification concept in the corpus is the Oracle Verifier which validates the validity of fused knowledge before it is stored in the database and which may rely on formal methods (4.2, 5.2); the framework defined on the basis of the Oracle Verifier is called ActivFORMS, and only what is verified is accepted. FORMS (Inferred): a collection of artefacts drawn from a system, which are reasoned over, is a reflection model in FORMS's sense. | H10: ActivFORMS. The innovative concept of the paper is not the knowledge base itself, as several studies suggest, but the gate in front of the knowledge base: knowledge is not stored, until it has been verified by a verifier, which can be formal. None of them specify that what enters a knowledge store is to be gated by the presence of a machine-checkable condition, and none of them suggest a formal verifier for what enters a knowledge store, except for S13 where the presence of one model call is compared to another model call, and S18 where the input is supposed to be in the form of a formal model, but none of them. MAPE-K is located at Knowledge and does not mention the gate; FORMS is located at the artefact but does not mention the running system; Models@run.time does not mention the Knowledge, the paper mentions it. | I10: Define the Oracle Verifier as the gateway between an adaptation plan and its execution, not between fused knowledge and its storage and tell what the Oracle Verifier checks: whether the plan conforms to the architecture metamodel, whether the plan contradicts an adaptation decision already in force and whether the preconditions of the plan are met in the current state. The paper provides the concept and its formal-methods ambition and does not provide any of the three conditions. Testable because of the speed with which it rejects invalid plans and it rejects valid plans; requires only a plan generator and a metamodel and not the rest of the proposed system. Common skills: a representation of the plan to be read by the checker; a metamodel to check against; adaptation decisions held in an queryable manner. What are the risks here? Specification; the verifier is unbuilt, and there is no reliability mechanism for the proposal itself (5.2); aggregating knowledge is demonstrated as the diagram, documentation and code all in one (5.1); and a formal check that is sound, but too slow to fit inside an adaptation interval; the paper gives no figure at all (3.3). | J10: Extrapolated
A11: S10 | B11: Jahić & Sami | C11: The best evidence for the reliability of the corpus: selected a model version which was more reproducible, and two identical runs of an identical prompt resulted in different architectures. Seems to believe that the technology fails to satisfy the authors own requirements for an engineering technique, an aid to engineering, or a methodology for engineering and "is a ritual, not an engineering practice. | D11: State of practice surveyed and at design time | E11: 1.1, 1.2, 1.3, 1.4(A), 1.5, 1.6, 2.1, 2.2(A), 2.3(A), 3.1, 3.2, 3.3, 4.1(A), 4.2, 4.3, 4.4(A), 4.5, 5.1, 5.2, 6.1 | F11: In particular, the main result of the corpus analysis on determinism is that repeated instances of each prompt type gives rise to different structures (a); repeated instances of each prompt type have a failure mode, but a successful one to counter that failure mode is not possible in the newer model; and the newer model fails to have a suitable alternative structure to compensate for its failure mode, where repeated instances of the older prompt type did (5.2). (b) Own assessment: The model does not meet three standards the authors put forward for engineering tools, assistance tools and methodology: It does not provide a same output with a same input; it will not guarantee a same output when repeated with a same input; it does not specify steps towards success; it does not describe a context where success is not possible. They feel it is a ritual help to be used as an inspiration aid (1.5). (c) Autonomy: The role of the architect is not to create from scratch, but to filter such alternatives and the risk of uncritical acceptance is recognized as a risk to quality and the architect's own innovation (4.3). The problems reported by test subjects (5.1) were: (d) Quality of output – missing hierarchy, undefined boundaries, missing stakeholders and problems in the visual presentation. No retrieval, single unmodified model (v.2.2 and 2.3 coded silence). Ongoing engineering and technology monitoring, as in f.) IsLive, no active process exists during the run-time. | G11: MAPE-K (Inferred): a Plan output, generated zero-shot into the C4 view model, with no Monitor, Analyse, Execute or Knowledge. The contribution the study makes to a MAPE-K reading is negative and load-bearing: It is a measure of how far the Plan activity can be relied on to be repeatable. Rainbow (Inferred): The generated C4 views are the architecture model Rainbow runs on; and the prompts ask for advice on pattern, tactic and anti-pattern in relation to quality properties (1.2) which is the content of a utility function; but there are no automatic selections and no constraint evaluated. The output of Models@run.time (Inferred) is machine-readable and can be used to seed a runtime model, but the paper illustrates two executions of the same prompt resulting in structurally different models, which can't be a property of a runtime model. ActivFORMS (Inferred): this study argues in favour of by exclusion. If the outputs are not reproducible and the conditions of success are not known then nothing can be executed until it is verified against anything other than the generator (which is the ActivFORMS position). Control-theoretic adaptation (Inferred): The authors' three criteria; same output for same input; logically similar outputs; stated conditions of success; are properties that a controller must have before it can be reasoned about, and the paper reports that none of these properties is present. | H11: ActivFORMS. This study does not actually adapt, but it sets the premise that the remainder of the RQ4 argument rests on: The architectural output of a language model is not reproducible, but the authors prove it, not concede it. For a self-adaptive system the result is exactly ActivFORMS' rule: Only change approved to a verified model is allowed to be done. Both MAPE-K and Rainbow have a single part present, while the result from the paper contradicts Models@run.time as it lacks the properties mentioned in the control theory. | I11: Instead of a caveat, treat non-determinism as a measurable property of the planner; repeat the same adaptation situation, and ensure the proposed plans vary only within a tolerable margin across the runs, before actually implementing a plan. This paper provides the method (repeated identical prompts) and the reason, because it discovered that for each prompt type, there was a success and a failure across each repeat. It could be tested by looking at what proportion of adaptation situations involve a consensus of repeated runs; and by whether the need for consensus results in more bad plans being required than good ones. Resources: A structural comparison of two proposed plans, an adaptation interval that lasts for a few runs. Risks: several runs multiply latency and cost in a loop that must act within an interval (3.3); and agreement across runs is not correctness, as the paper's subjects discovered common bugs, such as missing hierarchy, undefined boundaries, in outputs that were consistently generated for review. | J11: Partly grounded
A12: S11 | B12: Ahmad, Waseem, Liang, Fahmideh, Aktar & Mikkonen | C12: The three-activity Human-Bot Collaborative Architecting process (Human-Bot CP), which iterates the established Architecting process, end to end, was accommodated within a single conversation with ChatGPT on one campus bike sharing case study to create and rate evaluation scenarios using the model. The only study in the corpus to take the full analyse-synthesise-evaluate turn and to push an established scenario-based evaluation method through the model. | D12: End to end conversation and at design time | E12: 1.1, 1.2, 1.3, 1.4, 1.5, 1.6(A), 2.1, 2.2(A), 2.3(A), 3.1, 3.2(A), 3.3, 4.1, 4.2, 4.3, 4.4(A), 4.5, 5.1, 5.2, 6.1 | F12: (a) Autonomy (1.5) claimed not evidenced: the bot is considered intelligent enough to perform the architecting process during a conversation and under supervision of human and the architect gives the role to the bot. (b) Determinism: the same query produces different architectural styles, and the variability of this also radiates through any artefacts that are scripted and correspond to the process the query is using, in this instance, the frequency of the recommendations as detailed in the training data (5.2). The stated fix (2.1) is an iterative dialogue, in other words a person, but under the supervision of the architect. (c) No validated benefit: validation of the results is put aside from the study in a third phase (1.6 coded silence, 5.1). Grounding: 1 unmodified conversational model (2.2, 2.3 coded silence); no retrieval. A model version, model settings, number of runs, cost and latency are not reported anywhere, and the replication package is behind an anonymised review link (3.3). (f) Liveness: the whole process is performed before the implementation and it is based on an architect's conversation; self-adaptation is not discussed (4.4, coded silence). | G12: MAPE-K (Inferred): the three activities map onto Analyse (eliciting architecturally significant requirements from an architecture story), Plan (synthesising UML class and component models) and a second Analyse (evaluating the architecture by an established method, yielding a prioritised scenario list). There is no Monitor, no Execute and no Knowledge store; the conversation is the state. Rainbow (Inferred): Evaluation activity is closest to the one in Rainbow, which evaluates a model of an architecture (1.4) using an established scenario method, in that the same method and the same model are used in the evaluation activity. The missing part is that the answer is provided as an answer instead of a strategy selection. модеled@run.time (Inferred): The output is specifically designed to be compatible with known modelling and evaluation formalisms (4.2) and the scripted artefacts are machine-readable, but the paper also reports that the artefacts vary between runs of the same query (5.2) which is disqualifying for a system a model would rely on. The three-layer (Inferred): the intelligence-equilibrium idea, balancing machine intelligence against human intellect, and the three modes of requirement articulation, which span the spectrum of human-involvement (4.3), is a clear representation of the place of the human—where the human should be placed and it is answered in three-layer architecture. | H12: Rainbow. This is the only study that executes a recognized architecture evaluation method against an architecture that it created, and reports the result as a prioritized scenario list (S7 and S22 propose an evaluation step of this kind but do not execute one, and S19's automated checks are code-quality and security scanners). This is the Rainbow's cycle without the executor. MAPE-K maps the three activities, but Monitor and Execute and Knowledge are blanked out by the paper's own non-determinism finding; Models@run.time is undercut by the paper's own non-determinism finding. | I12: Run the evaluation activity automatically over a candidate adaptation instead of a design: for a proposed structural change, automatically generate the quality-attribute scenarios it would need to meet, and rank the change against the quality-attribute scenarios, for the architect to decide whether it should go ahead. The paper already presents the scenarios and the ranking (1.3, 1.4); what it does not present is the action of the ranking. Can be tested as follows: an automatically ranked list of candidate adaptations is ranked by an architect, and the results of the two rankings are compared. Commitment: Identify a candidate set to rank and a set of precondition quality-attribute scenarios that derive from the goals that are currently in force. Risks: different styles of the same query (5.2); recommendation bias for frequent in training data - also at runtime, frequent in the common configuration (5.2); generated component that was another privacy/regulatory exposure (4.5); no cost/no latency anywhere, so unknown how many scenarios can be generated per adaptation (3.3). | J12: Extrapolated
... A24: S23 | B24: Jafari Sarvejahani | C24: A research program for introducing penetration testing in the design phase. Input are architectural models, from which penetration test cases are generated, prioritised by severity with public vulnerability data, with which one may compare alternative architectures, feeding a recommender that tells the architect what design decisions make the system vulnerable. Three approaches are suggested as follows: threat modelling only, language modelling of public weakness and attack-pattern database, and a hybrid approach, with the addition of domain threat modelling. No implementation or evaluation in place. | D24: A research plan and at design time. | E24: 1.1(A), 1.2, 1.3(A), 1.4, 1.5, 1.6, 2.1, 2.2, 2.3, 3.1, 3.2, 3.3, 4.1(A), 4.2, 4.3, 4.4(A), 4.5, 5.1(A), 5.2, 6.1 | F24: Evaluation: no model run, no orchestration, no advantage/disadvantage observed = advantage is expected from a model run, no disadvantage/disadvantage observed from an orchestration = advantage is expected from a plan (3.1, 2.3, 5.1, coded silence / absence). The model's role is undecided: A non-model algorithm is being developed and it is later determined if the model will supplant or enhance pipeline steps (1.5). (c) Direction: architecture is input, artefact is never created: This results in the generation of test cases, a severity ranking and an attack-surface rating. (1.1, related activity). (d) By design and even more so: everything is done at runtime, and the paper is about taking an activity that's taking place at runtime and bringing it up to the deployment phase (4.4, coded silence). (e) Assurance: No treatment of hallucination or non-determinism; no oversight or assurance with attack scenarios generated by the model; other irrelevant outputs are called the expected failure mode (4.5, 5.2). There is no model-level attack-surface complexity/atk severity derived priority and a DTL feedback to architect (3.2, 6.1) is not present. | G24: MAPE-K (Inferred): Analyze on Knowledge base of public weakness, attack-pattern and vulnerability collections, generating a ranking for a human. Plan and Execute, Monitor is not designed. Rainbow (Inferred): Utility reading that is clear in the corpus. The idea is to rate alternative architectures by attack-surface complexity (which is a utility function over alternative architectural choices, the thing Rainbow selects strategies with) and the second criteria is severity-derived priority (3.2), and feed this rating to a recommender for architects (1.2, 1.4). There are criteria and their sources that are specified, which is more than just an analogy; nothing computes them and no architecture is evaluated. Not that - a regraded reason: Rainbow thinks about a running system on top of an architecture model, and decides on an adaptation; a check outside the generator, a coverage rule or a proposed utility does not that, and none of this is done on a running system. Models driven throughout the approach (including the whole approach) and the proposed intermediate formal artefact is an attack tree (4.2), but the models are design artefacts which are not kept updated. ActivFORMS (Inferred): rating a design before it is built, against formally derived attack trees, is verification ahead of operation – there is no verification of the model's output – which is termed by the paper as a gap (4.5). An awareness requirement is a statement of which properties must hold, and how much the failure of that property costs, and is written in the form of a severity-ranked test case. | H24: Rainbow. This study proposes to compute such a measure: attack-surface complexity, based on public vulnerability data, over competing architectural models, and to consider this measure for choosing between different configurations in a self-adaptive system. It is indeed a utility function in the sense of Rainbow, and the paper states that the lack of such a mechanism is an open problem - no formal method computes these factors at the model level. The activity is placed by MAPE-K, the formal input is fitted by Models@run.time, the before-operation posture is fitted by ActivFORMS, the ranking is fit by awareness requirements. They are all suggestions here and that's why the grounding is what it is. | I24: Calculate attack surface rating on candidate runtime configurations, not design alternatives, and rank a reconfiguration based on the attack surface, in addition to the latency, so that a reconfig that widens the attack surface is scored and not waved through. The paper presents the criterion, the data source and it claims that there is not a formal method that computes it at the model level, which is what a self-adaptive system should be able to fill. Testable to see if the rating improves when it shows an inferior configuration before another configuration with known vulnerabilities, before any loop is constructed. Preconditions: architectures held in the component-model description language the approach requires; the rating is computable within a rating period short enough to allow for scoring candidates within an adaptation period, where there is no concrete figure (3.3). Risks: The whole approach is planned, rather than built; the role of the model itself is not decided (1.5, 3.1); there is no oversight of attack scenarios generated by the model, which would be used as input to a scoring function (4.5); and a rating is computed on a design model that may have drifted away from the running system, because there is no way to keep it current. | J24: Extrapolated

Sheet SAS_Extension
A1: Sub-theme carried forward | B1: RQ | C1: What it already offers architectural design | D1: What breaks or is missing for self-adaptive systems | E1: Self-adaptation concepts it touches | F1: Extension to SASS (testable), with preconditions and risks | G1: Supporting studies (evidenced; mechanism support where it applies) | H1: Grounding
A2: 1.1 Architecture generation and synthesis from requirements | B2: RQ1 | C2: A model is used to create architecture based on a requirement in writing. The following five design agents produce successive C4 views across 5 real projects: S3: Generates ranked design solutions per agent trajectory; S6: Generates 4 UML view types from a specification; S7: Defines a 6-step pipeline from requirements through domain model and candidate architectures to finally a selected design; S10: Generates successive C4 views across 5 real projects; S11: Synthesises class and component diagrams from an architecture story; S17: A dedicated design agent synthesises architecture from a generated specification; S19: Derives service boundaries, APIs and data models and persists the diagrams; S21: Builds an architecture from a single-node baseline, under a declared vocabulary of structural operations. | D2: Change goals and acceptance during the run-time. Generation only runs once, when the requirements are written at design time, and the goals of a self-adaptive system change during the run. In 11 studies, an architectural object is manufactured and in 10 of these, the stimulus is not a measurement, but a written document by a person. Both at the ends S21 is the exception, S21 evolution is hypothesized to be due to diagnostic failure, which was observed, and S21 root causes were identified by model analyses as structural and prompt changes. The second challenge of the problem is acceptance. In every other place, a person must make the choice – and that is the reason why S7 carefully leaves the final choice to the architect, as there are implicit requirements that have not been written down that have to be taken into account. | E2: MAPE-K: No Monitor input anywhere, Plan at design time. Rainbow: S7 is closest, proposes to create candidates, and suggest to check them automatically against quality measures before choosing one. To seed the runtime model, a generated architecture might be used, and S20 demonstrates a generated component model in a model-based toolchain as well as a hand-built one, but nothing is saved. Three-layer: the deliberate planning, the work of goal management (S7, S22) is the regeneration of an architecture from prioritised drivers. None of these studies has a failing monitored requirement, so the regeneration of part of an architecture is the natural trigger for it. | F2: To reprovision the portion of the architecture that failed when the requirement is violated by a failing scenario, and to compare the new architecture with architectural constraints prior to use. S7 provides the rule for making this bounded instead of open-ended – prefer the candidate that is the least different from the running architecture; only accept a bigger change where a quality requirement calls for it. Testable by comparing the regenerated fragments with an architect's own for the same requirement change, with scores made on quality gain and on distance from the current architecture. Preconditions are conditions that can be monitored, and they are a validation step outside of the generator, only S21 has. Risks: generation that contradicts what the prompt said (S6) and omission of what the reference said (S6, S10); structurally different architectures from identical prompts in different repeats (S10, S11); style bias towards what is common in the training data (S11); and implicit requirements S7 places on a human, which no one monitors. | G2: S3, S6, S7, S9, S10, S11, S17, S19 (Mechanism support), S20 (Mechanism support), S21 (Mechanism support), S22 | H2: Partly grounded
A3: 1.2 Design decision support: pattern, tactic and technology recommendation | B3: RQ1 | C3: The model suggests patterns, tactics and technologies with respect to the stated drivers. S1 involves a sequence of prompts that elicit quality attributes and uncertainties before the model returns a justified decision, while S2 exemplifies the sequence that two industrial teams followed in their decision-making for the selection of the technology; S3 decomposes the architecting and divides its functions into callable pattern-selection tools; S22 proposes pattern and prior-solution knowledge as the source of the recommendation, the trade-off weighting being performed over competing drivers. | D3: Autonomous and trade-off reasoning. Fourteen studies have a model recommend a pattern, tactic or technology, and in thirteen a person accepts the recommendation. It is only S21 who automatically accepts and what S21 accepts is an edit to its workflow and not a recommendation to anyone. The adapters' reasoning used in the process of making an adaptation decision is the weakest part: S1 must add a pattern specifically in order to make the model state its premises, S4 thinks the format is right, the decision content is not high enough for people to grasp, and S8 blames it on a problem framing step that people do before they consider options. When competing goals, making a selection of adaption is precisely a trade-off decision. | E3: The person accepting the recommendation (MAPE-K: Plan) would require the authority to execute. A recommender might back strategy selection in the adaptation engine (Rainbow) which S23 suggests is related to the utility such a selection requires, and hence rates alternative architectures by attack-surface complexity. Models@run.time: not engaged; the recommendations are for an architecture and not over a model of one. Deliberative decision support is a component of goal management (three layer). A variability model is used to restrict the possible recommendations for a dynamic product lines like S22's pattern and prior-solution knowledge base. | F3: Let a model give a list of adaptation strategies and provide a motivation; then use a utility function or a check outside the model to make the final choice. S23 adds the utility dimension the corpus is missing and S8 presents the architecture: a proposing step, and a separate consistency step that checks the proposed changes against the decisions already in force. Tested against just a utility-based selection on a self-adaptive exemplar: do the ranking and the utility disagree? Preconditions: a set of pre-defined strategies; a utility function, the computation of which is done at model level and no formal method is provided by S23. Risks: a missing problem-framing step (S8); recommendations are too generic to work out in complex environments (S2); vendor and style bias due to training-data frequency (S2, S11); and non-catalogue options may be overlooked in favour of catalogue options (S8), so a plain reconfiguration may be missed. | G3: S1, S2, S3, S4, S7, S8 (Mechanism support), S9, S10, S11, S17, S19 (Mechanism support), S21 (Mechanism support), S22, S23 (Mechanism support) | H3: Partly grounded
A4: 1.3 Architecture documentation, decision records and rationale capture | B4: RQ1 | C4: Structured artefacts used to record decisions and reasons. S4 generates decision text from a given context; S8 captures structured rationale in an assessment step and presents it as a summary in an MADR-template decision record; S1 externalises the rationale as a list of premises to be checked; S7 auto-extracts the decision records specifically to document choices that the tooling would otherwise make "in the background", and S9 translates the source artefacts into structured knowledge formats and proposes an Oracle Verifier to check the fused knowledge before it is stored. | D4: Accountability at runtime. Fourteen studies yield a record and all of these yield it for someone else to read after. An adapting system makes decisions that also require a record; which is written as it is made and recorded with the thing that it changed. S17 creates architectural artifacts which have no meaning whatsoever; S19 contains no meaning at all, nor does S21's proposals survive an iteration. The exception is S13, which displays the shape; this selection's decision module explains each selection as it is made, at runtime. | E4: MAPE-K: Knowledge, with the rationale for each adaptation. S4 tells you the price of creating such a record, and it has an optimized model that matches one about 700 times larger, which is why it is feasible to write one once an adaptation. Rainbow: not directly engaged; there is no reason to use a strategy; a reason is not a constraint. The closest form in the corpus is a model with a rationale, as attached history of the runtime model in Models@run.time, where the confidence value and written justification of each judgement is attached. Three-layer: Why a change is necessary should be managed in goal management, not in the change itself. FORMS: A record of why a reflective subsystem acted is a part of its reflective state. | F4: For each adaptation, record the decision as a record of the Analyse result and the goal it served, rather than from just the change itself; and attach it to the version of the run-time model it changed. Use a small, locally hosted model, which is highly trained and reaches similar accuracy, eliminating the need for sending runtime data to a third party, as done in S4. It is testable if engineers can explain the reasons for an adaptation from the record without any knowledge of the individual except for the record itself, when the explanation is written by hand for the same adaptation. Preconditions: context-to-decision pairs, which an adaptation log supplies; hardware for local hosting. Risks: a correct format but a wrong rationale, with no reader catching it; format correct, but lower level design content (S4); produced without ever being checked (S21's position); exposure to data-sovereignty, but at runtime it relates to the state of live systems (S4 and S11). | G4: S1, S4, S5, S7, S8 (Mechanism support), S9, S10, S11, S14 (Mechanism support), S17, S18 (Mechanism support), S19 (Mechanism support), S20 (Mechanism support), S21 (Mechanism support) | H4: Partly grounded
A5: 1.4 Architecture analysis, recovery, conformance and smell detection | B5: RQ1 | C5: Model is of an actual architecture. Multi-view architecture reconstruction from legacy code (S14); Recovering presence of an architectural tactic from documentation and code and tracing to source (S12); Subsystem and function decomposition from a formal model on each run (S18); Proposing attack-surface analysis on competing architectural models (S18); Checking a candidate decision for conflict with previous decisions in the system (S8); Checking a requirement set against a candidate model for gaps, contradictions, and duplication (S23); Extracting a candidate model from documentation and code, and tracing to source (S20). | D5: An existing architecture is studied in 14 studies and each of these is executed off-line on a snapshot: source code, documentation, design model, repository at a point in time. As of the writing of this document, S20 makes its point quite clear: No measurement from a running system ever enters the pipeline and no link is maintained while the system is running. The warning attached is S12, a classifier that performs as well as the state-of-the-art when tested under cross-validation, but not as well under the condition that an adaptation loop encounters when it is outside of its training set. As a system runs, there is no item in the corpus that keeps a structural model up to date. | E5: MAPE-K: Analyze, and Monitor if analysed again. Rainbow: conformance checking with respect to sufficiency rule is a constraint evaluation (S18); S23 introduces a quality measure to rate competing architectures, the utility side. Models@run.time: the closest model in the corpus. S20 presents a generated component model used by a model-based tool chain as well as a manual one and argues for the concept of adequacy from purpose, not fidelity, to the generated model; S14 presents how a model of a repository that is too big to re-read can be built in merge-able chunks, since it may be modified between runs; S18 re-reads the formal architecture on each run, because it may have evolved. FORMS: recovered architecture is a reflection model of the subject system (S5, S14, S20). Megamodels' parts are in S14's shape, which is the mechanically mergeable partial diagrams.The shape of the parts of a megamodel is the shape of S14's mechanically mergeable partial diagrams. | F5: For any and all changes, do the recovery and conformance checking not just once on a snapshot, but re-derive what part of the architecture was touched, and merge the change into the existing architecture model, thus ensuring that a loop reads an architecture – a change is out of date at most times at most places. S14 provides the mechanism (bounded-overlap grouping, an output grammar selected such that partial models can be joined together), S20 the division of labour which removes non-determinism from the critical one and S18 the habit of re-reading, since the architecture can have changed. Testable based on the number of violations that can be detected once injected on a dynamic system, and the accuracy of the maintained model with regard to a full re-recovery after a number of commits. Preconditions: 1) There is a model that supports the architecture to code traceability, as indicated by S20; 2) the parts that are impacted by the change events can be mapped. Failure to generalise beyond the training data (S12), failure of local-scope bias to get worse on fragments, leading to hallucinated identifiers (S14), code-only extraction which fails outright on some projects (S20), undocumented components, which a loop would never know exist (S20), and no cost or runtime anywhere to repeat the work (S14, S20). | G5: S3, S5, S7, S8 (Mechanism support), S9, S11, S12, S14 (Mechanism support), S18 (Mechanism support), S19 (Mechanism support), S20 (Mechanism support), S21 (Mechanism support), S22, S23 (Mechanism support) | H5: Partly grounded
A6: 1.5 The role assigned to the model: assistant, co-designer or autonomous agent | B6: RQ1 | C6: The purpose of the model is explicitly presented and is enclosed nearly everywhere. S13 introduces two roles of human in the reconfiguration process, and a second model validates the first against the stated intent before being trusted; S3 introduces a shift from human-controlled modules to an autonomous agent; S8 puts the copilots in the role of critiquing the model, giving the human a possibility to override it, a situation where the human-only critique role is known to be weak; S16 restricts the role of the model to that of an assistant, as it is stated in the design; S7 restricts the model to a standard procedure, and human selection remains, motivated by documented human-only critique weakness; S25 (external anchor, outside the 23; identified on the Method sheet and listed under Withdrawn studies, and counted nowhere) catalogues the whole spectrum ranging from prompting every task to an autonomous agent, and catalogues three distinct verifiers (human, AI, hybrid human-in-the-loop agent). | D6: Security of self-determination. At run-time, a self-adaptive system does not require a human; and the consensus of the corpus is nearly unanimous the other way around: twenty-two papers say that there is a role for the model, while only a few papers have no human in it. In S16, the cap is a design requirement and the human validation of the cap is required. At low temp, S18 restricts the model behind a deterministic API to a value of the confidence, an explanation and an escape category and therefore states what it doesn't know instead of speculating. The guard is the part that differs when autonomy is used: S21 for altering the integrity of the graph, S19 for a validation pipeline, S13 for another try of the agent's model call against the stated goal, S3 for an agent that was witnessed evading a tool. | E6: MAPE-K: autonomic manager's degree of autonomy, and the Human is an approval gate ahead of Execute. Rainbow: the gate is placed in front of the adaptation executor; the validation pipeline implemented by S19 and the deploy-if-valid rule implemented by S21 are both placed in the gate. Not directly engaged with models.Not actively involved with models. Three-layer: S16 comes to layering with its design; the reasoning layer on top of a model of the running system on top of the automation ; and it states as principle that it is only the non-deterministic sub-tasks what belong in the reasoning layer. ActivFORMS premise is restated as a requirement: A generative model must be based on a formal model and must be asked systematically before it has any meaning as a result. | F6: Graded autonomy; the loop functions independently for low-risk reversible changes and raises the bar for high-risk changes, the risk dictates which guard is used. S21 demonstrates the asymmetry already; gating structural changes and un-gating prompt changes; S18 demonstrates the interface an escalation needs, a structured judgment and a confidence value, and an explicit escape category. The changes could be tested by the rate of escalation as well as the error rate with which the changes were carried out without one. Inputs: classification of adaptation actions by risk; a threshold of confidence that the escalation can reach. Contains risks of over-reliance on the model output (S10: the same prompts produce different architectures), guard that cannot be refused by the agent (S3), cheapest change is least checked (S21: hallucination rate is 20 per cent, even if the detection is handled by the agent). | G6: S1, S2, S3, S4, S5, S6, S7, S8 (Mechanism support), S9, S10, S11, S13 (Mechanism support), S14 (Mechanism support), S15 (Mechanism support), S16 (Mechanism support), S17, S18 (Mechanism support), S19 (Mechanism support), S20 (Mechanism support), S21 (Mechanism support), S22, S23 (Mechanism support) | H6: Partly grounded
A7: 1.6 Reported benefits in practice | B7: RQ1 | C7: The 23 studies report on 21 of them as benefits, and 11 of the 23 studies measure them for design-time. The company claims that it shortens development time from 9 days to about 2 days for the same input from one cohort to another. S14 scores significantly higher than its industrial baseline in eight repositories in both models tested in terms of the diagram F1. S20 eliminates the hindrance of the previous hand-maintained architecture model that was hard to adopt, and finds the quality of the model to be purpose relative, a smaller model outperforming a larger one on the same project with similar measured performances. On all available baselines, datasets and models, S21 beats three baselines. S6 created diagrams which contained the right materials not included in the reference. The qualitative benefits: Targeting, scope control and early risk visibility (S1), Structure, risk concerns never left out (S2), Natural language, lowers barrier to formal-representation (S3), Exploration capacity, beyond what students considered (S8), Design space narrowed and unconsidered patterns surfaced (S10), per-concept accuracy, as a guide to what needs checking (S5). It is also reported that for three datasets, the proportion of students achieving S15 is 94 per cent, 88 per cent and 84 per cent, and that, in a benchmarks context, output quality has increased 14.2 per cent, but not in a clinical context. S12 matches, not beats, in terms of accuracy, and it's for this reason that it is beneficial elsewhere: a task can be trained on a rather small data set. The other two studies, S9 and S11 have no built or validated. | D7: Samples of benefit at runtime. There are 21 studies reporting benefits, and nearly all of them are design-time: diagrams were created quicker, documentation was written, a decision was made that was consistent with a team decision. The figures that are available are elapsed time (S19: nine days to two) or accuracy compared to a ground truth (S14, S20) or practitioner approval (S2, S10). There is no study quantifying the advantage of adaptation on the running system's behaviour. There are loops, S13, S15 and S16, and S21, all reporting the benefits of the loop's output; one is the ablation (S15) one is the accuracy under degraded prompts (S13), and the third is the accuracy on the loop's output across iterations of evolution (S21), all of which are different quantities. Two studies show none at all; S9, S11, there was not a building or a valid one constructed. With regard to accuracy, S12 does not outperform the existing approach, but it claims a as yet own benefit: A task can be trained on a rather small data set. The difference is that you can't take a figure from a benchmark and conclude that it means there's a benefit in practice, let alone under runtime conditions: S15 only reports benchmark gains, not clinical evaluation. | E7: MAPE-K: no activity, gap is in evidence, not mechanism. Rainbow, Models@run.time, three-layer: not engaged. Control-theoretic adaptation: The measurements a loop would have to report; time to adapt, goal satisfaction after adaptation, stability; are the control-theoretic ones; two studies measure convergence: S15's iteration curve, where accuracy increases across iterations, but slows after the third; and S21's evolution curve, whose convergence over the validation set determines the rest of the search. | F7: Adaptation benefits in terms of: Time to adapt (including model reasoning time), Goal satisfaction after adaptation, Percentage of proposal rejected by the check, compared with a static configuration and a rule-based policy respectively. Comparative design (S19) and ablation (S15) are shown for the design. Testable in the moment, as it is more of a protocol rather than a mechanical process. Training: a process for increasing the ability to adjust to a set base condition. The risks are headline percentages which cannot be recomputed (S19), no repetition or variance (S21) and benefit claimed from practitioner approval (S2, S10, S17, S22) which are the defects of S19, and S22's forty per cent attached to three different quantities. | G7: S1, S2, S3, S4, S5, S6, S7, S8 (Mechanism support), S10, S12, S13 (Mechanism support), S14 (Mechanism support), S15 (Mechanism support), S16 (Mechanism support), S17, S18 (Mechanism support), S19 (Mechanism support), S20 (Mechanism support), S21 (Mechanism support), S22, S23 (Mechanism support) | H7: Partly grounded
A8: 2.1 Prompting strategies: chain-of-thought, few-shot, role and self-refinement | B8: RQ2 | C8: Prompting is considered a human engineered, documented and sometimes measured variable. S1 documents its technique as a reusable pattern form, tunes the ordering empirically into a fixed five-step sequence, and puts an after each step evaluate-and-refine gate; S4 compares zero-shot, few-shot and fine-tuning head to head and reports that when using prompt wording, format adherence improved but decision content didn't; S3 treats prompt refinement as an experimental variable and shows a three-version refinement with the detection result after each; S18 publishes both operative prompts in full with their output schemas, and puts an after each step evaluate-and-refine gate; S21 declares the operation vocabulary in the prompt itself. | D8: Automatic prompt construction. 19 studies report that a prompting strategy is used and 18 of those studies indicate that a person writes the prompt for the situation. The exception here being S21, where the prompt evolution gives immediate suggestions to change the system prompt of the node, and then it's directly applied because it changes the graph, not the prompt, so the prompt has been written based on the fails. The best-specified cases are more, not less, dependent: S18 publishes the full prompt in its operative form, as well as its output schema, and considers a change in the prompt to be a variable; S20 publishes four prompts verbatim, and was forced to break up reasoning from serialisation because combining them together produced malformed output. A loop has to recreate the prompt based on the measurements that it has taken. The only study that does this is S21, but this is diagnostic failures on a training set; S13 generates the prompt based on a supervisor's stated intent, rather than some measure. | E8: MAPE-K: Mapping interface between Knowledge and Analyse or Plan: a prompt would be composed in this interface. Rainbow: Strategy templates as patterns of prompts, S1 is actually at design time an expression of those five patterns. Models@run.time: prompt context at runtime, in the case of S18, according to a formal architecture model, the most similar model the corpus offers. Dynamic product lines: S21 considers prompt revision as one of the two equally important classes of architectural modification and quantifies it as the higher valued one, hence prompt revision variants are bound by the loop. | F8: Automatically complete prompt-pattern slots with runtime model and monitoring data; don't have the model remember a method description for a structural planning step. S18 provides the grounding form, S1 the pattern form and S20 the reason that the reasoning call and formatting call should be distinct. It can be tested by comparing the quality of output from automatically filled slots with the output from architectally filled slots, on the same situations. Preconditions: Runtime model that is queryable in the shape of the slots; monitoring data mapped to slots. Some of the risks are that they are often not reported, and so little to build upon: prompting is not often reported (S1, S11, S14, S15, S19); output structure moving with prompt wording (S4, S7); (at runtime) mal-formed structured output on long prompts (S20); (at runtime) role instructions interfering with one another (S1); measurable degradation as the instruction becomes vaguer (S13). | G8: S1, S2, S3, S4, S5, S6, S7, S8 (Mechanism support), S10, S11, S13 (Mechanism support), S15 (Mechanism support), S16 (Mechanism support), S17, S18 (Mechanism support), S19 (Mechanism support), S20 (Mechanism support), S21 (Mechanism support), S23 (Mechanism support) | H8: Partly grounded
A9: 2.2 Knowledge grounding: RAG, knowledge graphs and architecture repositories | B9: RQ2 | C9: The corpus has the greatest strength and variety in the grounding. S8 implements retrieval over pattern catalogues with an explicit fail-closed behaviour (no match, no model call) and not by guessing; S15 constructs an offline domain-specific vector index, keeping the source metadata for filtering, and presents a multi-layered retrieval fallback, plus term boosting instead of failing on an inexact query; S14 proposes to use structural grounding using an AST reference graph, instead of retrieval; S16 proposes to use a digital twin split into descriptive and procedural knowledge, on empirical grounds cited in the paper, and to position retrieval as a targeted fix for one failure mode, not as a default component of the system; S9 builds its retrieval phase on RAG principles and proposes multi-modal extension, the paper says that the resources are presumably in the training data, so this is an inference by the authors rather than a verification. | D9: Fifteen studies ground the model in something beyond the prompt and twelve record an absence of grounding; the two counts are per facet rather than a partition of the corpus, and S17, S18, S19 and S20 appear in both, grounded on one facet and silent on another. What is retrieved is static design knowledge: pattern catalogues (S8), prior solutions (S22), a biomedical index (S15), a formal architecture model (S18), AST reference graphs (S14). Almost none of it is the state of a running system: S16’s digital twin is the exception, and it is a model of a physical process rather than of the software. S9 names runtime logs as a source knowledge could be mined from and goes no further. Where retrieval is absent the knowledge is whatever is in the model, and S5 probed whether its target system was represented in the training data before the study could run at all, inferring coverage from the model’s own answers about itself. | E9: MAPE-K: Knowledge, and the activity the corpus engages least. Rainbow: the architecture model and style knowledge as the retrieval base; S18’s formal model is that base, read on every run. Models@run.time: the runtime model as the retrieval source, which is the most direct fit and which one study occupies ; S16’s digital twin, split deliberately into descriptive and procedural knowledge; no other study retrieves over a model of a running system. Three-layer: a knowledge base shared across layers. FORMS: retrieved architectural knowledge is reflective state about the subject system. | F9: Retrieve over the runtime model and the adaptation history rather than over design documents, with the retrieval failing closed when it cannot ground an answer. S8 supplies the fail-closed behaviour and the measured consequence of its absence ; zero-shot always answers and drifts towards generality; S16 supplies the runtime model to retrieve from; S15 supplies a graduated fallback that degrades rather than failing. Testable by the accuracy of answers about the current system state compared with the same questions answered from documentation. Preconditions: a queryable runtime model, which only S16 has; retrieval that covers the current state of the system and not only its documents ; S8 retrieves prior project decisions from its system repository, which is the nearest thing in the corpus, but the repository is a record of decisions already taken rather than a model kept current with a running system. Risks: stale retrieval when the model lags the system; a retrieval step that returns nothing, stalling a loop that must act (S8); pasting whole documents instead, which filled three quarters of a local model’s context before any question (S7); and the one retrieval comparison available, which is discouraging and narrow at once: S20’s retrieval-augmented baseline has the lowest average F1 of the five baselines needing no architecture model, though it beats the next-lowest on three of five projects and fails on the other two by recall rather than precision ; and the task is trace-link recovery, so it bears on retrieval over documents and not on retrieval over a runtime model. | G9: S3, S4, S5, S8 (Mechanism support), S9, S14 (Mechanism support), S15 (Mechanism support), S16 (Mechanism support), S17, S18 (Mechanism support), S19 (Mechanism support), S20 (Mechanism support), S21 (Mechanism support), S22, S23 (Mechanism support) | H9: Partly grounded
A10: 2.3 Fine-tuning, model adaptation and multi-agent orchestration | B10: RQ2 | C10: Adaptation of the model itself, and orchestration of several. S4 fine-tunes five models on context-to-decision pairs and reports a small fine-tuned model comparable to far larger ones; S12 fine-tunes BERT-base with a linear head and adds a confidence threshold of 0.9 to raise precision; S7 prefers open-source models specifically to keep fine-tuning open, and splits work between models and classical algorithms by task type; S9 combines models with graph neural networks, AST parsing and deterministic tools; S8 orchestrates five task-specialised copilots without fine-tuning; S14 runs a four-agent pipeline; S18 treats batch size as a tuned control with cross-item contextualisation named as the mechanism being traded. | D10: Timeliness and dependence. Eighteen studies adapt the model or orchestrate several, and the cost of doing so is reported by almost none. S13 is the exception and the reference point: token usage and latency across problem sizes, with self-debugging needing about 1.5 attempts on average. Elsewhere the multiplication is visible and unpriced ; S8’s five copilots, S14’s four agents, S17’s four agents with orchestration the authors themselves call financially unsustainable at scale and no figure to size it, S15’s loop of up to three passes with web access as the dominant latency. Dependence is the other half: the strongest models are cloud services, which S4 and S11 both flag, and S7 notes that hosting a useful model locally needs heavy hardware. | E10: MAPE-K: each loop activity could use a separately adapted model; S15 is the only study that assigns models to roles deliberately, using four model types across five agents on stated task-fit grounds, with one model serving two of them. Rainbow: not engaged directly. Models@run.time: not engaged. Control-theoretic adaptation: latency per activity is the settling-time question, and S13 is the only study that reports it across problem sizes; S15 reports it per component and S21 per phase. Dynamic product lines: S21’s configurable tool list widens the search space without altering the framework, which is variability in the mechanism rather than in the product. | F10: Use small, locally hosted, fine-tuned models for the runtime analysis step to meet a latency budget and remove the cloud dependency. S4 is the evidence: a 248M fine-tuned model reached quality comparable to one roughly 700 times larger, and the authors offer local hosting as the answer to data transmission. S13 supplies the measurement protocol ; accuracy, attempts-to-success, tokens and latency reported separately. Testable by trading latency against accuracy on the same analysis task across model sizes. Preconditions: context-to-decision pairs to fine-tune on; hardware for local hosting. Risks: accuracy loss in smaller models, which S4 measured as uneven across architectures and S20 found purpose-relative, a small model beating a large one on one task; agent counts multiplying calls with no reported budget (S8, S14, S17); orchestration cost named as unsustainable at scale (S17); and a fine-tuned encoder that did not generalise beyond its training data (S12). | G10: S3, S4, S5, S6, S7, S8 (Mechanism support), S9, S12, S14 (Mechanism support), S15 (Mechanism support), S16 (Mechanism support), S17, S18 (Mechanism support), S19 (Mechanism support), S20 (Mechanism support), S21 (Mechanism support), S22, S23 (Mechanism support) | H10: Partly grounded
A11: 3.1 Evaluation designs: benchmarks, case studies, expert judgement, experiments | B11: RQ2 | C11: Evaluation designs range from illustrative to genuinely controlled, and the strong end is strong. S4 runs a GQM-framed experiment over eighteen models and ninety-five records from five public repositories, with automatic metrics supplemented by manual review and threats analysed; S5 runs a single embedded case study with fourteen participants against a manually built ground truth; S10 runs fifty controlled experiments across five real projects validated against an industry survey; S20 uses an established public benchmark, six baselines, Wilcoxon signed-rank tests reported in both directions, and five runs per configuration with standard deviations; S18 declares five numeric success thresholds before reporting results and evaluates against a human reference standard; S2 publishes its interview instrument. | D11: Evaluation over time. Twenty-one studies describe an evaluation design, and the instruments are a benchmark score (S4, S12, S20), a comparison against a reference design (S3, S14), expert or user judgement (S5, S8, S10, S14) and one controlled cohort comparison (S19). Repetition is not absent, though it is partial: S20 runs its entity-matching approach five times and reports means with standard deviations, having set temperature to zero and fixed a seed elsewhere ; which it notes is not possible for one of its models ; and reports no comparable repeat statistics for its other approach or its baselines; S10 runs each question ten times; and S18 sweeps batch sizes across what it calls dozens of runs. What repetition measures is variance under fixed conditions, which is not the same as behaviour under changing ones. Adaptation has to be judged over a sequence of changing conditions, and no study does that. The nearest the corpus comes is S21, which evolves an architecture across iterations until validation accuracy converges and then freezes it, and S15, which measures its loop by ablation and by an iteration curve ; both of them over a fixed data set rather than a changing environment. Expert judgement, which is the commonest instrument here, does not scale to repeated runs. | E11: MAPE-K: the loop, not a single output, is what must be evaluated. Rainbow: S18 declares five numeric success thresholds in advance of its results, which is what a constraint evaluation needs and what almost nothing else in the corpus has. Models@run.time: not engaged. ActivFORMS: verification before execution rather than evaluation after the fact; S18 and S9 both argue for it, neither executes anything. Control-theoretic adaptation: S21’s termination on measured convergence rather than on a fixed budget is a settling criterion. | F11: Evaluate an adaptation loop on an established self-adaptive exemplar over repeated runs with injected changes, reporting the correctness of adaptations over time against static, random and rule-based baselines, with thresholds declared in advance. S19 supplies the cohort design and the discipline of reporting effort and elapsed time separately; S18 supplies explicit numerical success criteria, stated as criteria rather than read off the results, though the paper does not establish when they were fixed ; declaring them ahead of the run is the practice this extension proposes, not one the corpus demonstrates; S21 supplies the convergence criterion and, by freezing at it, the obvious experiment ; inject a shift afterwards and compare a frozen architecture with one allowed to resume. Preconditions: exemplars with ground truth for adaptation decisions; repetition under changing conditions, which no study has ; S20 and S10 repeat under fixed conditions, and S19 and S21 do not repeat at all. Risks: expert judgement not scaling (S5, S8, S10); headline accuracies from unrepeated runs with no between-run variance, at a temperature set to 1.0 for diversity, with the only stability figure measuring consensus across samples within a run (S21); validation and test sets identical (S4); correctness reduced to label agreement with no review of the artefact (S21); and benchmark leakage through closed-model training data, which S20 names and partly answers with locally deployable models. | G11: S1, S2, S3, S4, S5, S6, S7, S8 (Mechanism support), S10, S11, S12, S13 (Mechanism support), S14 (Mechanism support), S15 (Mechanism support), S16 (Mechanism support), S17, S18 (Mechanism support), S19 (Mechanism support), S20 (Mechanism support), S21 (Mechanism support), S23 (Mechanism support) | H11: Partly grounded
A12: 3.2 Metrics and quality criteria used to judge generated architectures | B12: RQ2 | C12: Metrics are specific where the task allows it and honest where it does not. S5 reports precision, recall and F1 against a manual ground truth alongside human quality and trustworthiness scales with defined anchors; S12 uses standard precision/recall/F1 specifically to enable direct baseline comparison; S4 uses four automatic metrics with embedding similarity as primary and names metric validity and style variance as threats; S6 uses graph-based node and edge similarity against a reference diagram; S13 reports accuracy, attempts-to-success, token usage and latency as separate quantities; S15 gives metric definitions with their construction limits acknowledged; S18 declares five numeric thresholds in advance. At the weak end, S1 judges relevance subjectively with no defined metric and S10 measures success as any output at all. | D12: Adaptation metrics. Twenty studies report a metric and there is no standard one even for design output: text similarity against a human-written answer (S4), precision and recall against a manually built ground truth (S5, S20), graph similarity against a reference diagram (S6), a study-specific composite (S14), subjective relevance (S1, S3). None of them can say whether an adaptation was right. S19 shows what goes wrong when the metric is not defined: its three headline percentages are uncomputable from the paper. The two studies that do measure a loop measure its output quality ; S15 by accuracy across passes, S13 by accuracy under degraded instructions ; not whether each decision was correct. | E12: MAPE-K: Analyse needs a utility or goal-satisfaction measure, and the corpus supplies none. Rainbow: utility-based strategy selection needs quality dimensions that are rarely measured; S23 proposes one, attack-surface complexity over competing architectures, and states that no formal method computes it at model level. Models@run.time: S20 argues model adequacy from purpose rather than fidelity, and since its benchmark is built for that purpose the argument is sound there; what makes it interesting here is that purpose-relative adequacy is also the test a runtime model needs, where the purpose changes as the system runs. Control-theoretic adaptation: S15’s confidence score, combining similarity, evidence level and concordance, is a utility function in all but name, with a stated threshold of 0.65. | F12: Measure adaptation outcomes directly ; goal satisfaction after adaptation, time to adapt, and the share of proposals the check rejects ; and build the utility from dimensions that can actually be computed over an architecture. S23’s attack-surface rating is the one candidate the corpus offers; S15’s composite confidence shows how several dimensions combine into a single trigger; S18’s numeric thresholds show what a stated pass condition looks like, though the paper does not establish when they were fixed. Testable by whether the measure ranks known-worse configurations below known-better ones, before any loop is built. Preconditions: goals stated so that satisfaction is computable; a rejection count, which presumes a check. Risks: a fluent but architecturally wrong output passing a similarity metric (S4, S6); metrics reported without a definition and with values that do not follow from each other (S19, whose human-effort row carries no unit and a percentage that matches neither pair of figures in it); the weights of a composite deciding which strategy looks best (S15 reports its threshold and never varies it); and quality attributes such as modifiability going unmeasured throughout. | G12: S1, S2, S3, S4, S5, S6, S7, S10, S12, S13 (Mechanism support), S14 (Mechanism support), S15 (Mechanism support), S16 (Mechanism support), S17, S18 (Mechanism support), S19 (Mechanism support), S20 (Mechanism support), S21 (Mechanism support), S22, S23 (Mechanism support) | H12: Partly grounded
... A21: 6.1 Open challenges and stated future work | B21: RQ3 | C21: The field states its own open problems, and several are precisely the ones RQ4 inherits. S1 flags over-reliance, unvalidated assumptions, and correct-but-inapplicable output as unsolved; S3 sets a four-part agenda of interaction, multi-agent design, methods and grounding; S4 names larger fine-tunes, richer context and live studies, and notes that as of early 2024 the area was largely unexplored; S5 positions itself as the first baseline for its evaluation task and asks for more models and accuracy-improving tooling; S7 frames four explicit open research questions and calls itself a vision paper whose results are future work; S8 names the specific-versus-general copilot trade-off as open; S6 cites prior work reporting that architecture lags code performance. | D21: Runtime on the agenda. Twenty-two studies state future work and runtime barely appears in it. The agendas ask for more models, more projects, better prompts and richer retrieval: S4 for larger fine-tunes and live studies, S5 for more models then accuracy tooling, S10 for ongoing tracking of technology readiness, S20 for its own measured failures. Where runtime is named it is named narrowly: S13 asks for more autonomous agentic configurations, S17 for persistent project memory and platform integration, S21 positions itself as groundwork for future adaptive systems with adaptation as the destination and proposes no mechanism, S19 names event-driven and saga orchestration as architectural targets rather than as adaptation. S14 states no future work or open challenges at all. S21 states the direction quoted above and carries no limitations or threats-to-validity section of any kind, so its destination is named while nothing is said about what stands in the way. | E21: MAPE-K: integration across the lifecycle is, at runtime, a closed loop. Rainbow: the architecture-based adaptation the agenda does not ask for. Models@run.time: persistence is the one runtime property the agendas do request, as S17’s long-term memory and S9’s knowledge base. ActivFORMS: the verification S9 proposes and S18 requires, carried into operation. Three-layer: the separation of goal management from change management is the structure an agenda aiming at runtime would need and none of them states. | F21: Position the contribution against the agenda the corpus actually states: a runtime loop over architecture is the lifecycle integration several studies gesture at without specifying, and runtime verification is S9’s and S18’s formal check carried into operation. The two nearest studies mark the two things to supply ; S21 names adaptation as its destination and leaves the loop frozen, so the contribution is the trigger and the re-entry; S13 asks for greater autonomy and has instructed reconfiguration, so the contribution is the monitor. Testable in the form every claim here should take: an exemplar, repeated runs with injected change, baselines that are static and rule-based, and the reasoning time counted in. Risk: the agenda is drawn from studies that are almost all design-time, so it understates runtime rather than arguing against it ; and two studies state no agenda at all. | G21: S1, S2, S3, S4, S5, S6, S7, S8 (Mechanism support), S9, S10, S11, S12, S13 (Mechanism support), S15 (Mechanism support), S16 (Mechanism support), S17, S18 (Mechanism support), S19 (Mechanism support), S20 (Mechanism support), S21 (Mechanism support), S22, S23 (Mechanism support) | H21: Partly grounded

Sheet Quality_Criterias
A1: Item | B1: Description | C1: Score (0) | D1: Score (1) | E1: Score (2)
A2: Q1 | B2: Problem definition: does the paper say what problem it addresses? | C2: No problem definition. | D2: General problem definition. | E2: Explicit problem definition.
A3: Q2 | B3: Problem context: does it describe the setting the problem sits in? | C3: No context description. | D3: General context description. | E3: Explicit context description.
A4: Q3 | B4: Research design: does it describe how the research was done? | C4: No description of how research was done. | D4: General description of how research was done. | E4: Explicit description of how research was done.
A5: Q4 | B5: Contributions: does it state what it contributes? | C5: No contributions description. | D5: General contributions description. | E5: Explicit contributions description.
A6: Q5 | B6: Insights: does it report what was learned? | C6: No insights description. | D6: General insights description. | E6: Explicit insights description.
A7: Q6 | B7: Limitations: does it state the limitations of the work? | C7: No limitations description. | D7: General limitations description. | E7: Explicit limitations description.
A8: Instrument | B8: Six items, each scored 0, 1 or 2, giving a total between 0 and 12. Carried over unchanged from the exploratory review so that the two studies remain comparable. Do not modify the items or the descriptors: their value is comparability.
A9: What it measures | B9: Reporting completeness, not methodological soundness. A study can score 12 and still have evaluated nothing, and a study with a strong evaluation can score low because it omits a limitations section. State this in the paper. Evidence strength is discussed separately under RQ2.
A10: Procedure | B10: Both authors score every study independently, recording per-item scores before any discussion so that initial rater agreement can be reported. Disagreements are then resolved by discussion to an agreed score. Every score is supported by a located piece of evidence from the source on the Quality evidence sheet.

Sheet Quality_Scores
A1: Study | B1: Authors | C1: Title | D1: Venue | E1: Q1 | F1: Q2 | G1: Q3 | H1: Q4 | I1: Q5 | J1: Q6 | K1: Total | L1: Remarks
A2: S1 | B2: Maranhão & Guerra | C2: A Prompt Pattern Sequence Approach to Apply Generative AI in Assisting Software Architecture Decision-making | D2: EuroPLoP 2024 | E2: 2 | F2: 2 | G2: 1 | H2: 2 | I2: 2 | J2: 2 | K2: 11 | L2: Only Q3 is borderline; research design is presented in a generalized way only.
A3: S2 | B3: Maranhão Junior, Melegati & Guerra | C3: Applying a Prompt Pattern Sequence for Decision-Making in Microservices Architectures | D3: ESOCC 2025, LNCS 15547, pp. 18-32 | E3: 2 | F3: 2 | G3: 2 | H3: 2 | I3: 2 | J3: 2 | K3: 12 | L3: No contested item and all scores are based on a named section.
A4: S3 | B4: Diaz-Pace, Tommasel, Capilla & Ramírez | C4: Architecture Exploration and Reflection meet LLM-based Agents | D4: ICSA-C 2025 | E4: 2 | F4: 2 | G4: 1 | H4: 2 | I4: 2 | J4: 1 | K4: 10 | L4: Q3: Explicit description of artefact; evaluation is only general. Q6: acknowledgement but no limitations section.
A5: S4 | B5: Dhar, Vaidhyanathan & Varma | C5: Can LLMs Generate Architectural Design Decisions? An Exploratory Empirical Study | D5: ICSA 2024 | E5: 2 | F5: 2 | G5: 2 | H5: 2 | I5: 2 | J5: 2 | K5: 12 | L5: Neither contested nor explicit, Section IV and Section VII both are structured
A6: S5 | B6: Soliman & Keim | C6: Do Large Language Models Contain Software Architectural Knowledge? An Exploratory Case Study with GPT | D6: ICSA 2025 | E6: 2 | F6: 2 | G6: 2 | H6: 2 | I6: 2 | J6: 2 | K6: 12 | L6: No item was contested.
A7: S6 | B7: Ramachandran | C7: Empowering Software Architects with Artificial Intelligence: Analyzing GitHub Copilot's Role in Modern Architecture Design | D7: CSECS 2025 | E7: 2 | F7: 2 | G7: 1 | H7: 2 | I7: 2 | J7: 1 | K7: 10 | L7: Q3 and Q6 both 1. The article was found to have three problems with independent verification of the verifiability and consistency of the discussions: (1) Fig. 9 is claimed to have generated a use-case diagram for the study presented as a study on the evaluation of GitHub Copilot, but this figure itself has been generated by ChatGPT; (2) Table III's class-diagram discussion refers to Fig. 14, which is captioned as sequence diagram; and (3) there are no sequence diagrams for space reasons, preventing independent verification of the authors' qualitative claim that Copilot was able to create more detailed and meaningful diagrams than those found in the literature. While a similarity score of 0.66 is claimed for sequence diagrams, reference diagrams that were not included in the paper do not allow for the visual similarity to be reproduced.
A8: S7 | B8: Eisenreich, Speth & Wagner | C8: From Requirements to Architecture: An AI-Based Journey to Semi-Automatically Generate Software Architectures | D8: Designing '24, IEEE/ACM International Workshop | E8: 2 | F8: 2 | G8: 1 | H8: 2 | I8: 2 | J8: 1 | K8: 10 | L8: Both Q3 and Q6 are at the top end of 1. Section 4 tests LLaMA2 70-B and GPT-3.5 on the MobSTr dataset consisting of 91 requirements. Only proposed by architecture generation.
A9: S8 | B9: Díaz-Pace, Tommasel & Capilla | C9: Helping Novice Architects to Make Quality Design Decisions Using an LLM-Based Assistant | D9: ECSA 2024 | E9: 2 | F9: 2 | G9: 1 | H9: 2 | I9: 2 | J9: 1 | K9: 10 | L9: Data for Q3 and Q6 both on the high end of 1. In the sessions, two of the authors did the role of Human and the same two authors judged the output. The names of the models and stack are (GPT-3.5, Langchain, Chroma, Streamlit).
A10: S9 | B10: Dhar, Vaidhyanathan & Varma | C10: Leveraging Generative AI for Architecture Knowledge Management | D10: ICSA-C 2024 | E10: 2 | F10: 2 | G10: 1 | H10: 2 | I10: 2 | J10: 1 | K10: 10 | L10: Family F3 with S4: Section V is the same study provided by S4, as mentioned in his/her report, which is cited as [4] and is therefore not independently sourced evidence. Section V summarizes the results of GPT models under zero-shot, few-shot and fine-tuning settings with 4 metrics and a results figure. The fact is, no model is run on the approach this paper proposes, which is unimplemented. This is a second occurrence of this error since S7.
A11: S10 | B11: Jahić & Sami | C11: State of Practice: LLMs in Software Engineering and Software Architecture | D11: ICSA-C 2024 | E11: 2 | F11: 2 | G11: 2 | H11: 2 | I11: 2 | J11: 1 | K11: 11 | L11: There is a threats heading but it contains only one sentence. This is a study on which the SAS extension depends in order to obtain the reproducibility protocol: Figure 3 is the direct evidence: two structurally different architectures from the same query
A12: S11 | B12: Ahmad, Waseem, Liang, Fahmideh, Aktar & Mikkonen | C12: Towards Human-Bot Collaborative Software Architecting with ChatGPT | D12: Ease 2023 | E12: 2 | F12: 2 | G12: 1 | H12: 2 | I12: 2 | J12: 2 | K12: 11 | L12: Only Q3 is borderline; research design is presented in a generalized way only.
A13: S12 | B13: Keim, Kaplan, Koziolek & Mirakhorli | C13: Does BERT Understand Code?, An Exploratory Study on the Detection of Architectural Tactics in Code | D13: ECSA 2020 | E13: 2 | F13: 2 | G13: 2 | H13: 2 | I13: 2 | J13: 2 | K13: 12 | L13: No contested item and all scores are based on a named section.
... A24: S23 | B24: Jafari Sarvejahani | C24: Towards Architectural Pen Test Case Generation and Attack Surface Analysis to Support Secure Design | D24: ICSA-C 2025 | E24: 2 | F24: 2 | G24: 1 | H24: 2 | I24: 1 | J24: 1 | K24: 9 | L24: There are no results to report and it's difficult to say when there are no limits on what's done.

Sheet Quality_Evidence
A1: Study | B1: Title | C1: Item | D1: Score | E1: Evidence location in the source | F1: Reasoning for each score
A2: S1 | B2: A Prompt Pattern Sequence Approach to Apply Generative AI in Assisting Software Architecture Decision-making | C2: Q1 | D2: 2 | E2: Section 1, paragraphs 1-2 and the goal statement in paragraph 5; Problem field of each of the five patterns (Sections 3-7) | F2: Motivation and problem scope are not only referenced, but stated. While microservices are granular, they are tightly coupled with event-driven styles, making it difficult to get a general view of the overall system, and increasing the likelihood of errors and system behavior that has become too complex to be considered technical debt, according to Section 1. To assist architects with their creation of context-specific recommendations for specific projects based on their preferences. There is also a distinct Problem field for each of the five patterns, which ask questions like “How can we ensure the accuracy and contextuality of AI-generated software architecture content?”. Reached 2 in terms of level of expressed and motivated problem, paper and pattern.
A3: S1 | B3: A Prompt Pattern Sequence Approach to Apply Generative AI in Assisting Software Architecture Decision-making | C3: Q2 | D3: 2 | E3: Section 1, technical background and the three scenario descriptions; Section 8.2; Context field of each pattern | F3: Descriptiveness is the setting stated at three levels. Technical context: microservices and event-driven enterprise systems, and current design patterns and prompt engineering. The three scenarios in the empirical context are a leading automobile financing bank's technological portal, a large network of retail pharmacies in Brazil with over 3,000 stores, and a cloud CRM for small and medium enterprises. Section 8.2 expands on the third aspect in greater detail, allowing for team composition, a 12-month timeline to first release, and angel-investor funding and a limited budget. Each pattern has its own Context field. For an explicit context description, they earned a score of 2.
